Workbook
Name Slicer_PhraseDesc: #N/A
Name Timeline_Week: #N/A

Sheet Q1Pivot
A3: Sum of Unique Visits | B3: PhraseDesc
A4: WeekCode | B4: 2 - Pre-Promo | C4: 3 - Promo | D4: 4 - Post-Promo | E4: 1 - Initial Period | F4: Grand Total
A5: 1 | E5: 1509 | F5: 1509
A6: 2 | E6: 1450 | F6: 1450
A7: 3 | E7: 1306 | F7: 1306
A8: 4 | E8: 1301 | F8: 1301
A9: 5 | E9: 1255 | F9: 1255
A10: 6 | E10: 841 | F10: 841
A11: 7 | E11: 731 | F11: 731
A12: 8 | E12: 706 | F12: 706
A13: 9 | E13: 976 | F13: 976
A14: 10 | E14: 850 | F14: 850
A15: 11 | E15: 791 | F15: 791
A16: 12 | E16: 685 | F16: 685
... A18: 14 | E18: 594 | F18: 594
A19: 15 | B19: 537 | F19: 537
A20: 16 | B20: 508 | F20: 508
A21: 17 | B21: 495 | F21: 495
A22: 18 | B22: 585 | F22: 585
A23: 19 | B23: 549 | F23: 549
A24: 20 | B24: 500 | F24: 500
A25: 21 | B25: 525 | F25: 525
A26: 22 | B26: 520 | F26: 520
A27: 23 | B27: 511 | F27: 511
A28: 24 | B28: 507 | F28: 507
A29: 25 | B29: 500 | F29: 500
A30: 26 | B30: 511 | F30: 511
... A39: 35 | B39: 734 | F39: 734
A40: 36 | C40: 930 | F40: 930
A41: 37 | C41: 1136 | F41: 1136
A42: 38 | C42: 2229 | F42: 2229
A43: 39 | C43: 1946 | F43: 1946
A44: 40 | C44: 2228 | F44: 2228
A45: 41 | C45: 3617 | F45: 3617
A46: 42 | C46: 2482 | F46: 2482
A47: 43 | C47: 2896 | F47: 2896
A48: 44 | C48: 1585 | F48: 1585
A49: 45 | C49: 1689 | F49: 1689
A50: 46 | C50: 1030 | F50: 1030
A51: 47 | C51: 1166 | F51: 1166
... A56: 52 | C56: 1137 | F56: 1137
A57: 53 | D57: 912 | F57: 912
A58: 54 | D58: 909 | F58: 909
A59: 55 | D59: 848 | F59: 848
A60: 56 | D60: 896 | F60: 896
A61: 57 | D61: 789 | F61: 789
A62: 58 | D62: 762 | F62: 762
A63: 59 | D63: 750 | F63: 750
A64: 60 | D64: 828 | F64: 828
A65: 61 | D65: 811 | F65: 811
A66: 62 | D66: 828 | F66: 828
A67: 63 | D67: 737 | F67: 737
A68: 64 | D68: 718 | F68: 718
... A70: 66 | D70: 709 | F70: 709
A71: Grand Total | B71: 10853 | C71: 29560 | D71: 11211 | E71: 13663 | F71: 65287
A76: Sum of Revenue | B76: PhraseDesc
A77: WeekCode | B77: 2 - Pre-Promo | C77: 3 - Promo | D77: 4 - Post-Promo | E77: 1 - Initial Period | F77: Grand Total
A78: 1 | E78: 480728.01 | F78: 480728.01
A79: 2 | E79: 641155.48 | F79: 641155.48
A80: 3 | E80: 890076.65 | F80: 890076.65
A81: 4 | E81: 552673.98 | F81: 552673.98
A82: 5 | E82: 750776.98 | F82: 750776.98
A83: 6 | E83: 553054.69 | F83: 553054.69
A84: 7 | E84: 274567.61 | F84: 274567.61
A85: 8 | E85: 619284.64 | F85: 619284.64
A86: 9 | E86: 674484.59 | F86: 674484.59
A87: 10 | E87: 762559.12 | F87: 762559.12
A88: 11 | E88: 479084.17 | F88: 479084.17
A89: 12 | E89: 528270.72 | F89: 528270.72
... A91: 14 | E91: 768109.11 | F91: 768109.11
A92: 15 | B92: 403820.11 | F92: 403820.11
A93: 16 | B93: 388745.03 | F93: 388745.03
A94: 17 | B94: 622367.3 | F94: 622367.3
A95: 18 | B95: 456011.81 | F95: 456011.81
A96: 19 | B96: 951216.16 | F96: 951216.16
A97: 20 | B97: 534541.68 | F97: 534541.68
A98: 21 | B98: 537651.89 | F98: 537651.89
A99: 22 | B99: 623710.09 | F99: 623710.09
A100: 23 | B100: 764838.99 | F100: 764838.99
A101: 24 | B101: 315647.11 | F101: 315647.11
A102: 25 | B102: 610984.66 | F102: 610984.66
A103: 26 | B103: 563524.69 | F103: 563524.69
... A112: 35 | B112: 519934.14 | F112: 519934.14
A113: 36 | C113: 614454.7 | F113: 614454.7
A114: 37 | C114: 516269.92 | F114: 516269.92
A115: 38 | C115: 297812.75 | F115: 297812.75
A116: 39 | C116: 692677.09 | F116: 692677.09
A117: 40 | C117: 897163.71 | F117: 897163.71
A118: 41 | C118: 417727.33 | F118: 417727.33
A119: 42 | C119: 326968.75 | F119: 326968.75
A120: 43 | C120: 326482.16 | F120: 326482.16
A121: 44 | C121: 508026.89 | F121: 508026.89
A122: 45 | C122: 413937.08 | F122: 413937.08
A123: 46 | C123: 422487.91 | F123: 422487.91
A124: 47 | C124: 376751.08 | F124: 376751.08
... A129: 52 | C129: 397140.04 | F129: 397140.04
A130: 53 | D130: 370914.26 | F130: 370914.26
A131: 54 | D131: 299424.67 | F131: 299424.67
A132: 55 | D132: 297325.95 | F132: 297325.95
A133: 56 | D133: 336761.58 | F133: 336761.58
...

Sheet Q1
A1: Prepared by (learners):
B2: Gumpal, Peter-Paul
B3: Zuñiga, Ma. Angelica Monina
B5: Unique Visits Week-on-Week (WoW)
B6: May 25 to August 29
B29: Revenue WoW
B30: May 25 to August 29
B53: Profit WoW
B54: May 25 to August 29
B78: Volume WoW
B79: May 25 to August 29

Sheet Q2
A1: Descriptive Statistics
A4: Initial Period | B4: Visits | C4: Unique Visits | D4: Revenue | E4: Profit | F4: Volume
A5: Mean | B5: 1055.2143 | C5: 975.92857 | D5: 608250.12 | E5: 200233.41 | F5: 18736.714
A6: Standard Error | B6: 94.88664 | C6: 85.415948 | D6: 41674.152 | E6: 16220.5 | F6: 1450.5282
A7: Median | B7: 899 | C7: 845.5 | D7: 586169.66 | E7: 208913 | F7: 17270
A8: Mode | B8: 1632 | C8: 1509 | D8: 890076.65 | E8: 275218.1 | F8: 28053
A9: Standard Deviation | B9: 355.0333 | C9: 319.59721 | D9: 155930.4 | E9: 60691.553 | F9: 5427.3795
A10: Sample Variance | B10: 126048.64 | C10: 102142.38 | D10: 2.4314289e+10 | E10: 3.6834646e+09 | F10: 29456448
A11: Kurtosis | B11: -1.4406592 | C11: -1.3957937 | D11: 0.50255719 | E11: 0.50365497 | F11: -0.30015322
A12: Skewness | B12: 0.54328993 | C12: 0.53717466 | D12: -0.21719204 | E12: -0.86903315 | F12: 0.21304576
A13: Range | B13: 1006 | C13: 915 | D13: 615509.04 | E13: 212637.7 | F13: 19420
A14: Minimum | B14: 626 | C14: 594 | D14: 274567.61 | E14: 62580.4 | F14: 8633
A15: Maximum | B15: 1632 | C15: 1509 | D15: 890076.65 | E15: 275218.1 | F15: 28053
A16: Sum | B16: 14773 | C16: 13663 | D16: 8515501.7 | E16: 2803267.7 | F16: 262314
... A18: Confidence Level(95%) | B18: 204.99012 | C18: 184.52994 | D18: 90031.531 | E18: 35042.259 | F18: 3133.6756
A23: Pre-Promo | B23: Visits | C23: Unique Visits | D23: Revenue | E23: Profit | F23: Volume
A24: Mean | B24: 562.95238 | C24: 516.80952 | D24: 534313.52 | E24: 159932.03 | F24: 18440.857
A25: Standard Error | B25: 17.647538 | C25: 15.48019 | D25: 32842.408 | E25: 9314.1252 | F25: 1301.8851
A26: Median | B26: 558 | C26: 510 | D26: 534541.68 | E26: 152476.4 | F26: 17215
A27: Mode | B27: 558 | C27: 511 | D27: 951216.16 | E27: 273174.7 | F27: 31972
A28: Standard Deviation | B28: 80.871179 | C28: 70.939142 | D28: 150502.82 | E28: 42682.684 | F28: 5965.9868
A29: Sample Variance | B29: 6540.1476 | C29: 5032.3619 | D29: 2.2651099e+10 | E29: 1.8218115e+09 | F29: 35592999
A30: Kurtosis | B30: 3.9301211 | C30: 4.7254532 | D30: 1.6047885 | E30: 1.0407275 | F30: -0.1383475
A31: Skewness | B31: 0.37569574 | C31: 0.79501239 | D31: 1.0069038 | E31: 1.086959 | F31: 0.57271931
A32: Range | B32: 412 | C32: 368 | D32: 635569.05 | E32: 172786.3 | F32: 22980
A33: Minimum | B33: 383 | C33: 366 | D33: 315647.11 | E33: 100388.4 | F33: 8992
A34: Maximum | B34: 795 | C34: 734 | D34: 951216.16 | E34: 273174.7 | F34: 31972
A35: Sum | B35: 11822 | C35: 10853 | D35: 11220584 | E35: 3358572.7 | F35: 387258
... A37: Confidence Level(95%) | B37: 36.812119 | C37: 32.29111 | D37: 68508.061 | E37: 19428.924 | F37: 2715.6846
A41: Promo | B41: Visits | C41: Unique Visits | D41: Revenue | E41: Profit | F41: Volume
A42: Mean | B42: 1814.3529 | C42: 1738.8235 | D42: 456398.85 | E42: 131929.9 | F42: 17112.824
A43: Standard Error | B43: 183.86666 | C43: 180.21012 | D43: 39227.979 | E43: 11587.587 | F43: 1581.1111
A44: Median | B44: 1663 | C44: 1585 | D44: 413937.08 | E44: 114328.4 | F44: 17299
A45: Mode | B45: 3726 | C45: 3617 | D45: 897163.71 | E45: 266476.7 | F45: 31496
A46: Standard Deviation | B46: 758.10165 | C46: 743.02534 | D46: 161741.1 | E46: 47776.847 | F46: 6519.0879
A47: Sample Variance | B47: 574718.12 | C47: 552086.65 | D47: 2.6160183e+10 | E47: 2.2826271e+09 | F47: 42498507
A48: Kurtosis | B48: 1.0640496 | C48: 1.0862724 | D48: 2.2535303 | E48: 2.8000506 | F48: 0.19342307
A49: Skewness | B49: 1.2069843 | C49: 1.2075731 | D49: 1.4320288 | E49: 1.5545284 | F49: 0.63987382
A50: Range | B50: 2726 | C50: 2687 | D50: 629004.2 | E50: 184635.3 | F50: 23682
A51: Minimum | B51: 1000 | C51: 930 | D51: 268159.51 | E51: 81841.4 | F51: 7814
A52: Maximum | B52: 3726 | C52: 3617 | D52: 897163.71 | E52: 266476.7 | F52: 31496
A53: Sum | B53: 30844 | C53: 29560 | D53: 7758780.4 | E53: 2242808.3 | F53: 290918
... A55: Confidence Level(95%) | B55: 389.7799 | C55: 382.02838 | D55: 83159.599 | E55: 24564.588 | F55: 3351.8057
A60: Post-Promo | B60: Visits | C60: Unique Visits | D60: Revenue | E60: Profit | F60: Volume
A61: Mean | B61: 856.57143 | C61: 800.78571 | D61: 371728.02 | E61: 111045.82 | F61: 14577.857
A62: Standard Error | B62: 18.945762 | C62: 19.337994 | D62: 38947.535 | E62: 13113.246 | F62: 1587.9758
A63: Median | B63: 847.5 | C63: 800 | D63: 348397.09 | E63: 104530.45 | F63: 13647
A64: Mode | B64: 963 | C64: 828 | D64: 615950.17 | E64: 206441.2 | F64: 23762
A65: Standard Deviation | B65: 70.888552 | C65: 72.356148 | D65: 145728.33 | E65: 49065.272 | F65: 5941.6614 | R65: Revenue
A66: Sample Variance | B66: 5025.1868 | C66: 5235.4121 | D66: 2.1236747e+10 | E66: 2.4074009e+09 | F66: 35303340
A67: Kurtosis | B67: -1.5784283 | C67: -1.2578557 | D67: -0.26590372 | E67: 0.0378826 | F67: -0.63510283 | R67: Mean | S67: 371728.02
A68: Skewness | B68: 0.28120509 | C68: 0.2861453 | D68: 0.47455056 | E68: 0.51063025 | F68: 0.035810473 | R68: Standard Error | S68: 38947.535
A69: Range | B69: 191 | C69: 203 | D69: 481983.27 | E69: 173615.9 | F69: 19936 | R69: Median | S69: 348397.09
A70: Minimum | B70: 772 | C70: 709 | D70: 133966.9 | E70: 32825.3 | F70: 3826 | R70: Mode | S70: 615950.17
A71: Maximum | B71: 963 | C71: 912 | D71: 615950.17 | E71: 206441.2 | F71: 23762 | R71: Standard Deviation | S71: 145728.33
A72: Sum | B72: 11992 | C72: 11211 | D72: 5204192.2 | E72: 1554641.5 | F72: 204090 | R72: Sample Variance | S72: 2.1236747e+10
A73: Count | B73: 14 | C73: 14 | D73: 14 | E73: 14 | F73: 14 | R73: Kurtosis | S73: -0.26590372
A74: Confidence Level(95%) | B74: 40.929831 | C74: 41.777196 | D74: 84141.035 | E74: 28329.445 | F74: 3430.6131 | R74: Skewness | S74: 0.47455056
U75: Range | V75: 481983.27
U76: Minimum | V76: 133966.9
U77: Maximum | V77: 615950.17
U78: Sum | V78: 5204192.2
U79: Count | V79: 14
U80: Confidence Level(95%) | V80: 84141.035

Sheet Q3
A1: Prepared by (learners):
B2: Gumpal, Peter-Paul
B3: Zuñiga, Ma. Angelica Monina
B5: MEAN
A6: PhraseDesc | B6: .Visits. | C6: .Unique Visits. | D6: .Revenue. | E6: .Profit. | F6: .Volume.
A7: 1 - Initial Period | B7: 1055.2143 | C7: 975.92857 | D7: 608250.12 | E7: 200233.41 | F7: 18736.714
A8: 2 - Pre-Promo | B8: 562.95238 | C8: 516.80952 | D8: 534313.52 | E8: 159932.03 | F8: 18440.857
A9: 3 - Promo | B9: 1814.3529 | C9: 1738.8235 | D9: 456398.85 | E9: 131929.9 | F9: 17112.824
A10: 4 - Post-Promo | B10: 856.57143 | C10: 800.78571 | D10: 371728.02 | E10: 111045.82 | F10: 14577.857
A15: .Visits.
A16: PhraseDesc | B16: Total
A17: 1 - Initial Period | B17: 1055.2143
A18: 2 - Pre-Promo | B18: 562.95238
A19: 3 - Promo | B19: 1814.3529
A20: 4 - Post-Promo | B20: 856.57143
A25: .Unique Visits.
A26: PhraseDesc | B26: Total
A27: 1 - Initial Period | B27: 975.92857
A28: 2 - Pre-Promo | B28: 516.80952
A29: 3 - Promo | B29: 1738.8235
A30: 4 - Post-Promo | B30: 800.78571
A37: .Revenue.
A38: PhraseDesc | B38: Total
A39: 1 - Initial Period | B39: 608250.12
A40: 2 - Pre-Promo | B40: 534313.52
A41: 3 - Promo | B41: 456398.85
A42: 4 - Post-Promo | B42: 371728.02
A49: .Profit.
A50: PhraseDesc | B50: Total
A51: 1 - Initial Period | B51: 200233.41
A52: 2 - Pre-Promo | B52: 159932.03
A53: 3 - Promo | B53: 131929.9
A54: 4 - Post-Promo | B54: 111045.82
A66: .Volume.
A67: PhraseDesc | B67: Total
A68: 1 - Initial Period | B68: 18736.714
A69: 2 - Pre-Promo | B69: 18440.857
A70: 3 - Promo | B70: 17112.824
A71: 4 - Post-Promo | B71: 14577.857

Sheet Q4
A9: Analysis
B10: On Unique Visits Week-on-Week (WoW), the central tendency is during the Promo phase, which shows that the marketing campaign initiated pre-promo is effective.
B11: This could mean that leads (part of the 25K marketing budget) have drawn new customers to QA's website.
B12: A rough WoW trend analysis on QA's Sales performance shows a decline going August 2009.
B13: Based only on mean(average) values comparing the 4 periods, the only significant increase is Web Traffc, but even then that didn't translate to an increase in sales.
A15: To wit-- | C15: MEAN
B16: Phrase | C16: .Visits. | D16: .Volume.
B17: 1 - Initial Period | C17: 1055.2143 | D17: 18736.714
B18: 2 - Pre-Promo | C18: 562.95238 | D18: 18440.857
B19: 3 - Promo | C19: 1814.3529 | D19: 17112.824
B20: 4 - Post-Promo | C20: 856.57143 | D20: 14577.857

Sheet Q5
A1: Prepared by (learners):
B2: Gumpal, Peter-Paul
B3: Zuñiga, Ma. Angelica Monina
A14: Analysis
B15: Based on intuition, an increase in sales volume would also translate to revenue growth.
B34: Correlation | D34: =CORREL(SRC!S1:S67,SRC!R1:R67) -> 0.86893384
B36: Correlation Matrix
C37: Volume | D37: Revenue
B38: Volume | C38: 1
B39: Revenue | C39: 0.86893384 | D39: 1
B40: R2 | C40: =C39^2 -> 0.75504602

Sheet Q6
B24: Correlation | D24: =CORREL(SRC!S2:S67,SRC!I2:I67) -> -0.05939183
B26: Correlation Matrix
C27: Visits | D27: Revenue
B28: Visits | C28: 1
B29: Revenue | C29: -0.05939183 | D29: 1

Sheet Q7
A1: Prepared by (learners):
B2: Gumpal, Peter-Paul
B3: Zuñiga, Ma. Angelica Monina
A5: Analysis
B6: Based on our scatter plot (in Q6), which clustered on the left, an increase in Visits didn't translate to increase in sales.
B7: These "new" buyers that have been redirected to QA's could probably have not made or finished a purchase since the website is not designed to be an e-commerce site.
B8: This can be easily verified by the metric "Revenue per Visit" (WoW Revenue / WoW Visits) which shows the gross sales for each website visitor.
B9: By tabulating the average Revenue per Visit per Week for each of the periods, the Promo phase shows the least revenue made per customer transaction in QAs website.
A11: Row Labels | B11: Average of Revenue Per Visit
A12: 1 - Initial Period | B12: 627.76404
A13: 2 - Pre-Promo | B13: 962.16381
A14: 3 - Promo | B14: 288.11628
A15: 4 - Post-Promo | B15: 434.59484
P16: Average of Revenue Per Visit | Q16: Column Labels
P17: Row Labels | Q17: 1 - Initial Period | R17: 2 - Pre-Promo | S17: 3 - Promo | T17: 4 - Post-Promo | V17: Row Labels | W17: Sum of Revenue | X17: Sum of Bounce Rate | Z17: Row Labels | AA17: Sum of Revenue | AB17: Sum of Bounce Rate
P18: 1 | Q18: 294.56373 | V18: 1 | W18: 480728.01 | X18: 0.7267 | Z18: 1 | AA18: 480728.01 | AB18: 0.7267
P19: 2 | Q19: 405.79461 | V19: 2 | W19: 641155.48 | X19: 0.7551 | Z19: 2 | AA19: 641155.48 | AB19: 0.7551
P20: 3 | Q20: 617.67984 | V20: 3 | W20: 890076.65 | X20: 0.7398 | Z20: 3 | AA20: 890076.65 | AB20: 0.7398
P21: 4 | Q21: 380.62946 | V21: 4 | W21: 552673.98 | X21: 0.7362 | Z21: 4 | AA21: 552673.98 | AB21: 0.7362
P22: 5 | Q22: 560.69976 | V22: 5 | W22: 750776.98 | X22: 0.764 | Z22: 5 | AA22: 750776.98 | AB22: 0.764
P23: 6 | Q23: 620.01647 | V23: 6 | W23: 553054.69 | X23: 0.7365 | Z23: 6 | AA23: 553054.69 | AB23: 0.7365
P24: 7 | Q24: 344.5014 | V24: 7 | W24: 274567.61 | X24: 0.6148 | Z24: 7 | AA24: 274567.61 | AB24: 0.6148
P25: 8 | Q25: 832.37182 | V25: 8 | W25: 619284.64 | X25: 0.5927 | Z25: 8 | AA25: 619284.64 | AB25: 0.5927
P26: 9 | Q26: 646.05803 | V26: 9 | W26: 674484.59 | X26: 0.6034 | Z26: 9 | AA26: 674484.59 | AB26: 0.6034
P27: 10 | Q27: 841.67674 | V27: 10 | W27: 762559.12 | X27: 0.6336 | Z27: 10 | AA27: 762559.12 | AB27: 0.6336
P28: 11 | Q28: 564.29231 | V28: 11 | W28: 479084.17 | X28: 0.6443 | Z28: 11 | AA28: 479084.17 | AB28: 0.6443
P29: 12 | Q29: 716.78523 | V29: 12 | W29: 528270.72 | X29: 0.6282 | Z29: 12 | AA29: 528270.72 | AB29: 0.6282
... P31: 14 | Q31: 1227.0114 | V31: 14 | W31: 768109.11 | X31: 0.6198 | Z31: 14 | AA31: 768109.11 | AB31: 0.6198
P32: 15 | R32: 699.86154 | V32: 15 | W32: 403820.11 | X32: 0.6205 | Z32: 15 | AA32: 403820.11 | AB32: 0.6205
A33: Analysis | P33: 16 | R33: 691.71714 | V33: 16 | W33: 388745.03 | X33: 0.589 | Z33: 16 | AA33: 388745.03 | AB33: 0.589
B34: Another variable pair that could be use to analyze the effectiveness of the website is the Bounce Rate and Revenue. This can definitely tell wether a customer visit translated to a sale. | P34: 17 | R34: 1105.4481 | V34: 17 | W34: 622367.3 | X34: 0.5861 | Z34: 17 | AA34: 622367.3 | AB34: 0.5861
B35: As shown in below grown, as the Bounce Rate (percentage of visitors who leave your website after viewing only one page) goes north, sales figure goes south. | P35: 18 | R35: 699.40461 | V35: 18 | W35: 456011.81 | X35: 0.5613 | Z35: 18 | AA35: 456011.81 | AB35: 0.5613
P36: 19 | R36: 1556.8186 | V36: 19 | W36: 951216.16 | X36: 0.5352 | Z36: 19 | AA36: 951216.16 | AB36: 0.5352
P37: 20 | R37: 952.83721 | V37: 20 | W37: 534541.68 | X37: 0.5365 | Z37: 20 | AA37: 534541.68 | AB37: 0.5365
P38: 21 | R38: 963.53386 | V38: 21 | W38: 537651.89 | X38: 0.6129 | Z38: 21 | AA38: 537651.89 | AB38: 0.6129
P39: 22 | R39: 1094.2282 | V39: 22 | W39: 623710.09 | X39: 0.5737 | Z39: 22 | AA39: 623710.09 | AB39: 0.5737
P40: 23 | R40: 1388.0925 | V40: 23 | W40: 764838.99 | X40: 0.5662 | Z40: 23 | AA40: 764838.99 | AB40: 0.5662
P41: 24 | R41: 587.79722 | V41: 24 | W41: 315647.11 | X41: 0.5698 | Z41: 24 | AA41: 315647.11 | AB41: 0.5698
P42: 25 | R42: 1125.2019 | V42: 25 | W42: 610984.66 | X42: 0.5838 | Z42: 25 | AA42: 610984.66 | AB42: 0.5838
P43: 26 | R43: 1009.9009 | V43: 26 | W43: 563524.69 | X43: 0.5771 | Z43: 26 | AA43: 563524.69 | AB43: 0.5771
P44: 27 | R44: 1036.3754 | V44: 27 | W44: 555497.24 | X44: 0.5765 | Z44: 27 | AA44: 555497.24 | AB44: 0.5765
P45: 28 | R45: 788.08278 | V45: 28 | W45: 432657.45 | X45: 0.612 | Z45: 28 | AA45: 432657.45 | AB45: 0.612
P46: 29 | R46: 897.22141 | V46: 29 | W46: 488985.67 | X46: 0.5908 | Z46: 29 | AA46: 488985.67 | AB46: 0.5908
P47: 30 | R47: 1166.545 | V47: 30 | W47: 689428.11 | X47: 0.6244 | Z47: 30 | AA47: 689428.11 | AB47: 0.6244
... P52: 35 | R52: 654.0052 | V52: 35 | W52: 519934.14 | X52: 0.6579 | Z52: 35 | AA52: 519934.14 | AB52: 0.6579
A53: Analysis | P53: 36 | S53: 614.4547 | V53: 36 | W53: 614454.7 | X53: 0.658 | Z53: 36 | AA53: 614454.7 | AB53: 0.658
B54: Therefore, while an increase in sales volume can contribute to revenue growth, | P54: 37 | S54: 427.72985 | V54: 37 | W54: 516269.92 | X54: 0.7307 | Z54: 37 | AA54: 516269.92 | AB54: 0.7307
B55: it's essential for QA to focus on optimizing other aspects of their sales and marketing strategy to maximize the impact of increased web traffic. | P55: 38 | S55: 128.53377 | V55: 38 | W55: 297812.75 | X55: 0.8226 | Z55: 38 | AA55: 297812.75 | AB55: 0.8226
B56: This includes enhancing website usability, refining pricing and promotional strategies, and maintaining a strong emphasis on product quality and brand reputation. | P56: 39 | S56: 344.10188 | V56: 39 | W56: 692677.09 | X56: 0.8127 | Z56: 39 | AA56: 692677.09 | AB56: 0.8127
P57: 40 | S57: 386.04291 | V57: 40 | W57: 897163.71 | X57: 0.8072 | Z57: 40 | AA57: 897163.71 | AB57: 0.8072
P58: 41 | S58: 112.11147 | V58: 41 | W58: 417727.33 | X58: 0.8578 | Z58: 41 | AA58: 417727.33 | AB58: 0.8578
P59: 42 | S59: 127.57267 | V59: 42 | W59: 326968.75 | X59: 0.8478 | Z59: 42 | AA59: 326968.75 | AB59: 0.8478
P60: 43 | S60: 108.61017 | V60: 43 | W60: 326482.16 | X60: 0.843 | Z60: 43 | AA60: 326482.16 | AB60: 0.843
P61: 44 | S61: 305.48821 | V61: 44 | W61: 508026.89 | X61: 0.7655 | Z61: 44 | AA61: 508026.89 | AB61: 0.7655
P62: 45 | S62: 232.67964 | V62: 45 | W62: 413937.08 | X62: 0.7886 | Z62: 45 | AA62: 413937.08 | AB62: 0.7886
P63: 46 | S63: 389.03122 | V63: 46 | W63: 422487.91 | X63: 0.6934 | Z63: 46 | AA63: 422487.91 | AB63: 0.6934
P64: 47 | S64: 306.05286 | V64: 47 | W64: 376751.08 | X64: 0.7059 | Z64: 47 | AA64: 376751.08 | AB64: 0.7059
P65: 48 | S65: 328.71889 | V65: 48 | W65: 410241.18 | X65: 0.7316 | Z65: 48 | AA65: 410241.18 | AB65: 0.7316
P66: 49 | S66: 328.40509 | V66: 49 | W66: 549750.11 | X66: 0.7855 | Z66: 49 | AA66: 549750.11 | AB66: 0.7855
P67: 50 | S67: 177.11989 | V67: 50 | W67: 268159.51 | X67: 0.7761 | Z67: 50 | AA67: 268159.51 | AB67: 0.7761
P68: 51 | S68: 247.87265 | V68: 51 | W68: 322730.19 | X68: 0.7757 | Z68: 51 | AA68: 322730.19 | AB68: 0.7757
P69: 52 | S69: 333.45092 | V69: 52 | W69: 397140.04 | X69: 0.7347 | Z69: 52 | AA69: 397140.04 | AB69: 0.7347
P70: 53 | T70: 387.58021 | V70: 53 | W70: 370914.26 | X70: 0.7085 | Z70: 53 | AA70: 370914.26 | AB70: 0.7085
P71: 54 | T71: 310.92905 | V71: 54 | W71: 299424.67 | X71: 0.6833 | Z71: 54 | AA71: 299424.67 | AB71: 0.6833
P72: 55 | T72: 337.10426 | V72: 55 | W72: 297325.95 | X72: 0.6995 | Z72: 55 | AA72: 297325.95 | AB72: 0.6995
P73: 56 | T73: 357.49637 | V73: 56 | W73: 336761.58 | X73: 0.6858 | Z73: 56 | AA73: 336761.58 | AB73: 0.6858
P74: 57 | T74: 502.15846 | V74: 57 | W74: 419302.31 | X74: 0.6635 | Z74: 57 | AA74: 419302.31 | AB74: 0.6635
P75: 58 | T75: 238.36855 | V75: 58 | W75: 191171.58 | X75: 0.6571 | Z75: 58 | AA75: 191171.58 | AB75: 0.6571
P76: 59 | T76: 166.21204 | V76: 59 | W76: 133966.9 | X76: 0.6526 | Z76: 59 | AA76: 133966.9 | AB76: 0.6526
P77: 60 | T77: 684.12531 | V77: 60 | W77: 615712.78 | X77: 0.6456 | Z77: 60 | AA77: 615712.78 | AB77: 0.6456
P78: 61 | T78: 418.64255 | V78: 61 | W78: 360032.6 | X78: 0.6465 | Z78: 61 | AA78: 360032.6 | AB78: 0.6465
P79: 62 | T79: 621.12387 | V79: 62 | W79: 573918.45 | X79: 0.6418 | Z79: 62 | AA79: 573918.45 | AB79: 0.6418
P80: 63 | T80: 501.9572 | V80: 63 | W80: 397550.1 | X80: 0.6818 | Z80: 63 | AA80: 397550.1 | AB80: 0.6818
P81: 64 | T81: 361.13298 | V81: 64 | W81: 282044.86 | X81: 0.6633 | Z81: 64 | AA81: 282044.86 | AB81: 0.6633
... P83: 66 | T83: 797.86292 | V83: 66 | W83: 615950.17 | X83: 0.6192 | Z83: 66 | AA83: 615950.17 | AB83: 0.6192

Sheet Q8
A5: 8.a | B5: Descriptive Statistics
B7: Lbs. Sold
B9: Mean | C9: 18681.555
B10: Standard Error | C10: 401.68846
B11: Median | C11: 17673
B12: Mode | C12: 28865
B13: Standard Deviation | C13: 6840.5079
B14: Sample Variance | C14: 46792549
B15: Kurtosis | C15: 0.56366144
B16: Skewness | C16: 0.63230748
B17: Range | C17: 40914
B18: Minimum | C18: 3826
B19: Maximum | C19: 44740
B20: Sum | C20: 5417651
... B22: Confidence Level(95%) | C22: 790.60578
A24: 8.b | B24: Histogram
A41: 8.c | B41: The histogram appears to be bell-shaped, however it ishows a positively skewed data (volume sold more than 30K is at the right tail of the graph) , thus not normally distributed.
A43: 8.d
B44: Interval | C44: Theoretical % of data | D44: Theoretical No. Observation | E44: Actual No. Observation | F44: Actual % of Data
B45: mean +-1 std. dev | C45: 0.68 | D45: =D67 -> 197.2 | E45: =52+72+50 -> 174 | F45: =E45/290 -> 0.6
B46: mean +-2 std. dev | C46: 0.95 | D46: =E67 -> 275.5 | E46: =E45+23+38 -> 235 | F46: =E46/290 -> 0.81034483
B47: mean +-3 std. dev | C47: 0.997 | D47: =F67 -> 289.13 | E47: =E46+7+29 -> 271 | F47: =E47/290 -> 0.93448276
B53: Interval | C53: Actual Observed | D53: stdev | E53: (+-2 stdev) | F53: (+-3 stdev)
B54: 3826 to 7426 | C54: 7 | D54: =C54*$C$45 -> 4.76 | E54: =C54*$C$46 -> 6.65 | F54: =C54*$C$47 -> 6.979 | I54: =61/290 -> 0.21034483
B55: 7426 to 11026 | C55: 23 | D55: =C55*$C$45 -> 15.64 | E55: =C55*$C$46 -> 21.85 | F55: =C55*$C$47 -> 22.931
B56: 11026 to 14626 | C56: 52 | D56: =C56*$C$45 -> 35.36 | E56: =C56*$C$46 -> 49.4 | F56: =C56*$C$47 -> 51.844 | I56: =36/290 -> 0.12413793
B57: 14626 to 18226 | C57: 72 | D57: =C57*$C$45 -> 48.96 | E57: =C57*$C$46 -> 68.4 | F57: =C57*$C$47 -> 71.784
B58: 18226 to 21826 | C58: 50 | D58: =C58*$C$45 -> 34 | E58: =C58*$C$46 -> 47.5 | F58: =C58*$C$47 -> 49.85
B59: 21826 to 25426 | C59: 38 | D59: =C59*$C$45 -> 25.84 | E59: =C59*$C$46 -> 36.1 | F59: =C59*$C$47 -> 37.886
B60: 25426 to 29026 | C60: 29 | D60: =C60*$C$45 -> 19.72 | E60: =C60*$C$46 -> 27.55 | F60: =C60*$C$47 -> 28.913
B61: 29026 to 32626 | C61: 8 | D61: =C61*$C$45 -> 5.44 | E61: =C61*$C$46 -> 7.6 | F61: =C61*$C$47 -> 7.976
B62: 32626 to 36226 | C62: 7 | D62: =C62*$C$45 -> 4.76 | E62: =C62*$C$46 -> 6.65 | F62: =C62*$C$47 -> 6.979
B63: 36226 o 39826 | C63: 2 | D63: =C63*$C$45 -> 1.36 | E63: =C63*$C$46 -> 1.9 | F63: =C63*$C$47 -> 1.994
B64: 39826 to 43426 | C64: 1 | D64: =C64*$C$45 -> 0.68 | E64: =C64*$C$46 -> 0.95 | F64: =C64*$C$47 -> 0.997
B65: 43426t to 47026 | C65: 1 | D65: =C65*$C$45 -> 0.68 | E65: =C65*$C$46 -> 0.95 | F65: =C65*$C$47 -> 0.997
D67: =SUM(D54:D65) -> 197.2 | E67: =SUM(E54:E65) -> 275.5 | F67: =SUM(F54:F65) -> 289.13
A69: 8.e
B70: Interval | C70: Theoretical % of data | D70: Theoretical No. Observation | E70: Actual No. Observation
B71: mean +1 std. dev | C71: =C45/2 -> 0.34 | D71: =D67*C71 -> 67.048 | E71: 35
B72: mean -1 std. dev | C72: =C45/2 -> 0.34 | D72: =D67*C72 -> 67.048 | E72: 0
B73: 1 std dev to 2 std. dev. | C73: =C46/2 -> 0.475 | D73: =E67*C73 -> 130.8625 | E73: 9
B74: -1 std. dev to -2 std. dev. | C74: =C46/2 -> 0.475 | D74: =E67*C74 -> 130.8625 | E74: 241
B75: 2 std. dev. To 3 std. dev. | C75: =C47/2 -> 0.4985 | D75: =F67*C75 -> 144.13131 | E75: 2
B76: -2 std dev. To -3 std. dev. | C76: =C47/2 -> 0.4985 | D76: =F67*C76 -> 144.13131 | E76: 3
A80: 8.f | B80: Although the histogram of pounds sold initially appears bell-shaped, our analysis reveals it does not conform to a normal distribution. This is evident in the deviation from the Empirical Rule.
B81: In a normal distribution, we expect 68% of data to fall within one standard deviation of the mean, 95% within two, and 99.7% within three.
B82: Observed Data: Our data shows only 60% within one standard deviation (interval 11026 to 18226), 21% within two, and 12% within three.
B83: This significant discrepancy indicates the distribution is not normal.
B84: Additionally, the median (14626 to 18226) does not align with the mean if it were a perfect bell curve, suggesting asymmetry in the data.
B85: This deviation from normality has implications for our analysis. We cannot rely on statistical methods that assume normality.
A88: 8.g | B88: Our analysis reveals that the data exhibits a positively skewed, with a skewness of 0.63 and kurtosis of 0.56.
B89: This means the majority of values are concentrated on the lower end, with a long tail extending towards the higher values.
B90: Additionally, the distribution is more peaked and has heavier tails compared to a normal distribution, suggesting a higher probability of extreme values.
B91: This insight can be visually confirmed in the histogram, which clearly illustrates the right-skewed shape and the concentration of values on the left side of the distribution.

Sheet Q9
A1: Prepared by (learners):
B2: Gumpal, Peter-Paul
B3: Zuñiga, Ma. Angelica Monina
B10: {='Daily Visits'!H1:I16} -> Visits | C10: 0
B11: 0 | C11: 0
B12: Mean | C12: 150.28355
B13: Standard Error | C13: 4.5672581
B14: Median | C14: 122
B15: Mode | C15: 91
B16: Standard Deviation | C16: 98.169492
B17: Sample Variance | C17: 9637.2491
B18: Kurtosis | C18: 5.8619896
B19: Skewness | C19: 2.1669722
B20: Range | C20: 627
B21: Minimum | C21: 37
B22: Maximum | C22: 664
B23: Sum | C23: 69431
... B25: Confidence Level(95%) | C25: 8.9752246
B27: Interval | C27: Theoretical % of data | D27: Theoretical No. Observation | E27: Actual No. Observation | F27: Actual % of data
B28: mean +-1 std. dev | C28: 0.68 | D28: =C28*462 -> 314.16 | E28: =151+92+54 -> 297 | F28: =E28/$C$24 -> 0.64285714
B29: mean +-2 std. dev | C29: 0.95 | D29: =C29*462 -> 438.9 | E29: =E28+85+36 -> 418 | F29: =E29/$C$24 -> 0.9047619
B30: mean +-3 std. dev | C30: 0.997 | D30: =C30*462 -> 460.614 | E30: =E29+11 -> 429 | F30: =E30/$C$24 -> 0.92857143
B35: Interval | C35: Actual Observed | D35: stdev | E35: (+-2 stdev) | F35: (+-3 stdev)
B36: 37 to 81 | C36: 85 | D36: =C36*$C$28 -> 57.8 | E36: =C36*$C$29 -> 80.75 | F36: =C36*$C$30 -> 84.745
B37: 81 to 125 | C37: 151 | D37: =C37*$C$28 -> 102.68 | E37: =C37*$C$29 -> 143.45 | F37: =C37*$C$30 -> 150.547
B38: 125 to 169 | C38: 92 | D38: =C38*$C$28 -> 62.56 | E38: =C38*$C$29 -> 87.4 | F38: =C38*$C$30 -> 91.724
B39: 169 to 213 | C39: 54 | D39: =C39*$C$28 -> 36.72 | E39: =C39*$C$29 -> 51.3 | F39: =C39*$C$30 -> 53.838
B40: 213 to 257 | C40: 36 | D40: =C40*$C$28 -> 24.48 | E40: =C40*$C$29 -> 34.2 | F40: =C40*$C$30 -> 35.892
B41: 257 to 301 | C41: 11 | D41: =C41*$C$28 -> 7.48 | E41: =C41*$C$29 -> 10.45 | F41: =C41*$C$30 -> 10.967
B42: 301 to 345 | C42: 10 | D42: =C42*$C$28 -> 6.8 | E42: =C42*$C$29 -> 9.5 | F42: =C42*$C$30 -> 9.97
B43: 345 to 389 | C43: 4 | D43: =C43*$C$28 -> 2.72 | E43: =C43*$C$29 -> 3.8 | F43: =C43*$C$30 -> 3.988
B44: 389 to 433 | C44: 4 | D44: =C44*$C$28 -> 2.72 | E44: =C44*$C$29 -> 3.8 | F44: =C44*$C$30 -> 3.988
B45: 433 to 477 | C45: 4 | D45: =C45*$C$28 -> 2.72 | E45: =C45*$C$29 -> 3.8 | F45: =C45*$C$30 -> 3.988
B46: 477 to 521 | C46: 5 | D46: =C46*$C$28 -> 3.4 | E46: =C46*$C$29 -> 4.75 | F46: =C46*$C$30 -> 4.985
B47: 521 to 565 | C47: 4 | D47: =C47*$C$28 -> 2.72 | E47: =C47*$C$29 -> 3.8 | F47: =C47*$C$30 -> 3.988
... B50: 653 to 697 | C50: 1 | D50: =C50*$C$28 -> 0.68 | E50: =C50*$C$29 -> 0.95 | F50: =C50*$C$30 -> 0.997
D52: =SUM(D36:D50) -> 314.16 | E52: =SUM(E36:E50) -> 438.9 | F52: =SUM(F36:F50) -> 460.614
B54: Daily Visits | H54: Lbs. Sold
B55: Interval | C55: Theoretical % of data | D55: Theoretical No. Observation | E55: Actual No. Observation | H55: Interval | I55: Theoretical % of data | J55: Theoretical No. Observation | K55: Actual No. Observation
B56: mean +1 std. dev | C56: =C28/2 -> 0.34 | D56: =C56*462 -> 157.08 | E56: 0 | H56: mean +1 std. dev | I56: 0.34 | J56: 67.048 | K56: 35
B57: mean -1 std. dev | C57: =C56 -> 0.34 | D57: =C57*462 -> 157.08 | E57: 24 | H57: mean -1 std. dev | I57: 0.34 | J57: 67.048 | K57: 0
B58: 1 std dev to 2 std. dev. | C58: =C29/2 -> 0.475 | D58: =C58*462 -> 219.45 | E58: 9 | H58: 1 std dev to 2 std. dev. | I58: 0.475 | J58: 130.8625 | K58: 9
B59: -1 std. dev to -2 std. dev. | C59: =C58 -> 0.475 | D59: =C59*462 -> 219.45 | E59: 0 | H59: -1 std. dev to -2 std. dev. | I59: 0.475 | J59: 130.8625 | K59: 241
B60: 2 std. dev. To 3 std. dev. | C60: =C30/2 -> 0.4985 | D60: =C60*462 -> 230.307 | E60: 14 | H60: 2 std. dev. To 3 std. dev. | I60: 0.4985 | J60: 144.13131 | K60: 2
B61: -2 std dev. To -3 std. dev. | C61: =C60 -> 0.4985 | D61: =C61*462 -> 230.307 | E61: 415 | H61: -2 std dev. To -3 std. dev. | I61: 0.4985 | J61: 144.13131 | K61: 3
B79: Skewness: | C79: =C19 -> 2.1669722 | H79: Skewness: | I79: ='Q8'!$C$16 -> 0.63230748
B80: Kurtosis: | C80: =C18 -> 5.8619896 | H80: Kurtosis: | I80: ='Q8'!$C$15 -> 0.56366144
A82: Analysis | B82: Analysis of the kurtosis reveals that neither "Daily Visits" nor "Pounds Sold" follow a normal distribution.
B83: The high kurtosis of 5.86 for "Daily Visits" indicates a distribution with a sharper peak and heavier tails than a normal distribution,
B84: suggesting the website typically experiences lower visitor counts than the average of 150 per day, with occasional spikes in traffic.
B85: Similarly, the kurtosis of 0.56 for "Pounds Sold" indicates a less peaked distribution with lighter tails compared to a normal distribution.
B86: This suggests a concentration of sales around the average at around 18K, with fewer extreme values.
B87: Furthermore, the skewness values of 2.17 for "Daily Visits" and 0.63 for "Pounds Sold" confirm that neither dataset is normally distributed.
B88: The high positive skewness for "Daily Visits" indicates a longer tail on the right side of the distribution, implying a greater frequency of lower daily visits and occasional high-traffic days.
B89: Although the "Pounds Sold" distribution appears somewhat bell-shaped, its positive skewness indicates a longer tail on the right, suggesting more frequent lower sales values and less frequent higher sales values.
B90: In summary, both datasets exhibit deviations from normality, highlighting the importance of considering these characteristics when analyzing and interpreting the data.
B91: These insights will be crucial in making informed decisions and developing effective strategies for the website and sales performance.

Sheet Q10
A1: Prepared by (learners):
B2: Gumpal, Peter-Paul
B3: Zuñiga, Ma. Angelica Monina
A10: Analysis
A11: 1 | B11: The majority of traffic to QA's website (86%) comes from referring sites and search engines, suggesting that the brochure had a limited impact on site visits.
B12: It can be inferred that only 14% of visits may be attributed to direct communication with leads.
A13: 2 | B13: Google AdWords, a separate service from the brochure, contributes significantly to website traffic (approximately 80%).
A14: 3 | B14: With Google being the top search engine source of visits, utilizing Google's ad service remains a viable option for QA.
A15: 4 | B15: The Americas represent QA's largest customer base (71%), while Europe and Asia are potential targets for future marketing campaigns.
A16: 5 | B16: Given that most visitors find QA through Google and primarily use Internet Explorer on Windows PCs (76% of total visits), these insights should inform the design of QA's future website.
A19: Chart 1
A34: Chart 2
A52: Chart 3
A71: Chart 4
A92: Chart 5

Sheet DS_LbsSold
A1: Phase | B1: PhraseDesc | C1: PhaseCode | D1: WeekCode | E1: MonthCode | F1: MonthYear | G1: Year | H1: Week | I1: Lbs. Sold | J1: z-score | K1: Count | N1: Count3 | X1: MonthCode | Y1: Lbs. Sold | AA1: Descriptive Statistics
A2: Pre-WebAnalytics | B2: =_xlfn.CONCAT(C2, " - ", A2) -> 0 - Pre-WebAnalytics | C2: 0 | D2: 1 | E2: =_xlfn.CONCAT(G2, " - ", F2) -> 2005 - 01 | F2: =TEXT(H2,"mm") -> 01 | G2: =TEXT(H2,"YYYY") -> 2005 | H2: 38354 | I2: 23662 | J2: =(I2-$AB$4) / $AB$8 -> 0.72808114 | K2: =IF(J2<=1, "<=1", IF(J2<=2, "<=2", IF(J2<=3, "<=3", "<=3"))) -> <=1 | N2: =IF(J2>=3, 3, IF(J2>=2, 2, IF(J2>=1, 1, IF(J2>=-2, -2, IF(J2>=-3, -3, "Error"))))) -> -2 | X2: 2005 - 01 | Y2: 23662 | AA2: Lbs. Sold
A3: Pre-WebAnalytics | B3: =_xlfn.CONCAT(C3, " - ", A3) -> 0 - Pre-WebAnalytics | C3: 0 | D3: 2 | E3: =_xlfn.CONCAT(G3, " - ", F3) -> 2005 - 01 | F3: =TEXT(H3,"mm") -> 01 | G3: =TEXT(H3,"YYYY") -> 2005 | H3: 38361 | I3: 12699 | J3: =(I3-$AB$4) / $AB$8 -> -0.87457762 | K3: =IF(J3<=1, "<=1", IF(J3<=2, "<=2", IF(J3<=3, "<=3", "<=3"))) -> <=1 | N3: =IF(J3>=3, 3, IF(J3>=2, 2, IF(J3>=1, 1, IF(J3>=-2, -2, IF(J3>=-3, -3, "Error"))))) -> -2 | O3: Sum of Lbs. Sold | P3: Column Labels | X3: 2005 - 01 | Y3: 12699
A4: Pre-WebAnalytics | B4: =_xlfn.CONCAT(C4, " - ", A4) -> 0 - Pre-WebAnalytics | C4: 0 | D4: 3 | E4: =_xlfn.CONCAT(G4, " - ", F4) -> 2005 - 01 | F4: =TEXT(H4,"mm") -> 01 | G4: =TEXT(H4,"YYYY") -> 2005 | H4: 38368 | I4: 23095 | J4: =(I4-$AB$4) / $AB$8 -> 0.64519256 | K4: =IF(J4<=1, "<=1", IF(J4<=2, "<=2", IF(J4<=3, "<=3", "<=3"))) -> <=1 | N4: =IF(J4>=3, 3, IF(J4>=2, 2, IF(J4>=1, 1, IF(J4>=-2, -2, IF(J4>=-3, -3, "Error"))))) -> -2 | O4: Row Labels | P4: 0 | Q4: 1 | R4: 2 | S4: 3 | T4: 4 | U4: 5 | X4: 2005 - 01 | Y4: 23095 | AA4: Mean | AB4: 18681.555
A5: Pre-WebAnalytics | B5: =_xlfn.CONCAT(C5, " - ", A5) -> 0 - Pre-WebAnalytics | C5: 0 | D5: 4 | E5: =_xlfn.CONCAT(G5, " - ", F5) -> 2005 - 01 | F5: =TEXT(H5,"mm") -> 01 | G5: =TEXT(H5,"YYYY") -> 2005 | H5: 38375 | I5: 27944 | J5: =(I5-$AB$4) / $AB$8 -> 1.354058 | K5: =IF(J5<=1, "<=1", IF(J5<=2, "<=2", IF(J5<=3, "<=3", "<=3"))) -> <=2 | N5: =IF(J5>=3, 3, IF(J5>=2, 2, IF(J5>=1, 1, IF(J5>=-2, -2, IF(J5>=-3, -3, "Error"))))) -> 1 | O5: 0 - Pre-WebAnalytics | X5: 2005 - 01 | Y5: 27944 | AA5: Standard Error | AB5: 401.68846
A6: Pre-WebAnalytics | B6: =_xlfn.CONCAT(C6, " - ", A6) -> 0 - Pre-WebAnalytics | C6: 0 | D6: 5 | E6: =_xlfn.CONCAT(G6, " - ", F6) -> 2005 - 01 | F6: =TEXT(H6,"mm") -> 01 | G6: =TEXT(H6,"YYYY") -> 2005 | H6: 38382 | I6: 20516 | J6: =(I6-$AB$4) / $AB$8 -> 0.26817377 | K6: =IF(J6<=1, "<=1", IF(J6<=2, "<=2", IF(J6<=3, "<=3", "<=3"))) -> <=1 | N6: =IF(J6>=3, 3, IF(J6>=2, 2, IF(J6>=1, 1, IF(J6>=-2, -2, IF(J6>=-3, -3, "Error"))))) -> -2 | O6: 1 | P6: 23662 | X6: 2005 - 01 | Y6: 20516 | AA6: Median | AB6: 17673
A7: Pre-WebAnalytics | B7: =_xlfn.CONCAT(C7, " - ", A7) -> 0 - Pre-WebAnalytics | C7: 0 | D7: 6 | E7: =_xlfn.CONCAT(G7, " - ", F7) -> 2005 - 02 | F7: =TEXT(H7,"mm") -> 02 | G7: =TEXT(H7,"YYYY") -> 2005 | H7: 38389 | I7: 25546 | J7: =(I7-$AB$4) / $AB$8 -> 1.0034993 | K7: =IF(J7<=1, "<=1", IF(J7<=2, "<=2", IF(J7<=3, "<=3", "<=3"))) -> <=2 | N7: =IF(J7>=3, 3, IF(J7>=2, 2, IF(J7>=1, 1, IF(J7>=-2, -2, IF(J7>=-3, -3, "Error"))))) -> 1 | O7: 2 | P7: 12699 | X7: 2005 - 02 | Y7: 25546 | AA7: Mode | AB7: 28865
A8: Pre-WebAnalytics | B8: =_xlfn.CONCAT(C8, " - ", A8) -> 0 - Pre-WebAnalytics | C8: 0 | D8: 7 | E8: =_xlfn.CONCAT(G8, " - ", F8) -> 2005 - 02 | F8: =TEXT(H8,"mm") -> 02 | G8: =TEXT(H8,"YYYY") -> 2005 | H8: 38396 | I8: 20023 | J8: =(I8-$AB$4) / $AB$8 -> 0.1961031 | K8: =IF(J8<=1, "<=1", IF(J8<=2, "<=2", IF(J8<=3, "<=3", "<=3"))) -> <=1 | N8: =IF(J8>=3, 3, IF(J8>=2, 2, IF(J8>=1, 1, IF(J8>=-2, -2, IF(J8>=-3, -3, "Error"))))) -> -2 | O8: 3 | P8: 23095 | X8: 2005 - 02 | Y8: 20023 | AA8: Standard Deviation | AB8: 6840.5079
A9: Pre-WebAnalytics | B9: =_xlfn.CONCAT(C9, " - ", A9) -> 0 - Pre-WebAnalytics | C9: 0 | D9: 8 | E9: =_xlfn.CONCAT(G9, " - ", F9) -> 2005 - 02 | F9: =TEXT(H9,"mm") -> 02 | G9: =TEXT(H9,"YYYY") -> 2005 | H9: 38403 | I9: 35247 | J9: =(I9-$AB$4) / $AB$8 -> 2.4216688 | K9: =IF(J9<=1, "<=1", IF(J9<=2, "<=2", IF(J9<=3, "<=3", "<=3"))) -> <=3 | N9: =IF(J9>=3, 3, IF(J9>=2, 2, IF(J9>=1, 1, IF(J9>=-2, -2, IF(J9>=-3, -3, "Error"))))) -> 2 | O9: 4 | P9: 27944 | X9: 2005 - 02 | Y9: 35247 | AA9: Sample Variance | AB9: 46792549
A10: Pre-WebAnalytics | B10: =_xlfn.CONCAT(C10, " - ", A10) -> 0 - Pre-WebAnalytics | C10: 0 | D10: 9 | E10: =_xlfn.CONCAT(G10, " - ", F10) -> 2005 - 02 | F10: =TEXT(H10,"mm") -> 02 | G10: =TEXT(H10,"YYYY") -> 2005 | H10: 38410 | I10: 23615 | J10: =(I10-$AB$4) / $AB$8 -> 0.72121031 | K10: =IF(J10<=1, "<=1", IF(J10<=2, "<=2", IF(J10<=3, "<=3", "<=3"))) -> <=1 | N10: =IF(J10>=3, 3, IF(J10>=2, 2, IF(J10>=1, 1, IF(J10>=-2, -2, IF(J10>=-3, -3, "Error"))))) -> -2 | O10: 5 | P10: 20516 | X10: 2005 - 02 | Y10: 23615 | AA10: Kurtosis | AB10: 0.56366144
A11: Pre-WebAnalytics | B11: =_xlfn.CONCAT(C11, " - ", A11) -> 0 - Pre-WebAnalytics | C11: 0 | D11: 10 | E11: =_xlfn.CONCAT(G11, " - ", F11) -> 2005 - 03 | F11: =TEXT(H11,"mm") -> 03 | G11: =TEXT(H11,"YYYY") -> 2005 | H11: 38417 | I11: 16655 | J11: =(I11-$AB$4) / $AB$8 -> -0.296258 | K11: =IF(J11<=1, "<=1", IF(J11<=2, "<=2", IF(J11<=3, "<=3", "<=3"))) -> <=1 | N11: =IF(J11>=3, 3, IF(J11>=2, 2, IF(J11>=1, 1, IF(J11>=-2, -2, IF(J11>=-3, -3, "Error"))))) -> -2 | O11: 6 | P11: 25546 | X11: 2005 - 03 | Y11: 16655 | AA11: Skewness | AB11: 0.63230748
A12: Pre-WebAnalytics | B12: =_xlfn.CONCAT(C12, " - ", A12) -> 0 - Pre-WebAnalytics | C12: 0 | D12: 11 | E12: =_xlfn.CONCAT(G12, " - ", F12) -> 2005 - 03 | F12: =TEXT(H12,"mm") -> 03 | G12: =TEXT(H12,"YYYY") -> 2005 | H12: 38424 | I12: 14748 | J12: =(I12-$AB$4) / $AB$8 -> -0.57503846 | K12: =IF(J12<=1, "<=1", IF(J12<=2, "<=2", IF(J12<=3, "<=3", "<=3"))) -> <=1 | N12: =IF(J12>=3, 3, IF(J12>=2, 2, IF(J12>=1, 1, IF(J12>=-2, -2, IF(J12>=-3, -3, "Error"))))) -> -2 | O12: 7 | P12: 20023 | X12: 2005 - 03 | Y12: 14748 | AA12: Range | AB12: 40914
A13: Pre-WebAnalytics | B13: =_xlfn.CONCAT(C13, " - ", A13) -> 0 - Pre-WebAnalytics | C13: 0 | D13: 12 | E13: =_xlfn.CONCAT(G13, " - ", F13) -> 2005 - 03 | F13: =TEXT(H13,"mm") -> 03 | G13: =TEXT(H13,"YYYY") -> 2005 | H13: 38431 | I13: 18159 | J13: =(I13-$AB$4) / $AB$8 -> -0.076391282 | K13: =IF(J13<=1, "<=1", IF(J13<=2, "<=2", IF(J13<=3, "<=3", "<=3"))) -> <=1 | N13: =IF(J13>=3, 3, IF(J13>=2, 2, IF(J13>=1, 1, IF(J13>=-2, -2, IF(J13>=-3, -3, "Error"))))) -> -2 | O13: 8 | P13: 35247 | X13: 2005 - 03 | Y13: 18159 | AA13: Minimum | AB13: 3826
A14: Pre-WebAnalytics | B14: =_xlfn.CONCAT(C14, " - ", A14) -> 0 - Pre-WebAnalytics | C14: 0 | D14: 13 | E14: =_xlfn.CONCAT(G14, " - ", F14) -> 2005 - 03 | F14: =TEXT(H14,"mm") -> 03 | G14: =TEXT(H14,"YYYY") -> 2005 | H14: 38438 | I14: 22149 | J14: =(I14-$AB$4) / $AB$8 -> 0.50689874 | K14: =IF(J14<=1, "<=1", IF(J14<=2, "<=2", IF(J14<=3, "<=3", "<=3"))) -> <=1 | N14: =IF(J14>=3, 3, IF(J14>=2, 2, IF(J14>=1, 1, IF(J14>=-2, -2, IF(J14>=-3, -3, "Error"))))) -> -2 | O14: 9 | P14: 23615 | X14: 2005 - 03 | Y14: 22149 | AA14: Maximum | AB14: 44740
A15: Pre-WebAnalytics | B15: =_xlfn.CONCAT(C15, " - ", A15) -> 0 - Pre-WebAnalytics | C15: 0 | D15: 14 | E15: =_xlfn.CONCAT(G15, " - ", F15) -> 2005 - 04 | F15: =TEXT(H15,"mm") -> 04 | G15: =TEXT(H15,"YYYY") -> 2005 | H15: 38445 | I15: 14492 | J15: =(I15-$AB$4) / $AB$8 -> -0.61246258 | K15: =IF(J15<=1, "<=1", IF(J15<=2, "<=2", IF(J15<=3, "<=3", "<=3"))) -> <=1 | N15: =IF(J15>=3, 3, IF(J15>=2, 2, IF(J15>=1, 1, IF(J15>=-2, -2, IF(J15>=-3, -3, "Error"))))) -> -2 | O15: 10 | P15: 16655 | X15: 2005 - 04 | Y15: 14492 | AA15: Sum | AB15: 5417651
A16: Pre-WebAnalytics | B16: =_xlfn.CONCAT(C16, " - ", A16) -> 0 - Pre-WebAnalytics | C16: 0 | D16: 15 | E16: =_xlfn.CONCAT(G16, " - ", F16) -> 2005 - 04 | F16: =TEXT(H16,"mm") -> 04 | G16: =TEXT(H16,"YYYY") -> 2005 | H16: 38452 | I16: 19012 | J16: =(I16-$AB$4) / $AB$8 -> 0.04830706 | K16: =IF(J16<=1, "<=1", IF(J16<=2, "<=2", IF(J16<=3, "<=3", "<=3"))) -> <=1 | N16: =IF(J16>=3, 3, IF(J16>=2, 2, IF(J16>=1, 1, IF(J16>=-2, -2, IF(J16>=-3, -3, "Error"))))) -> -2 | O16: 11 | P16: 14748 | X16: 2005 - 04 | Y16: 19012 | AA16: Count | AB16: 290
A17: Pre-WebAnalytics | B17: =_xlfn.CONCAT(C17, " - ", A17) -> 0 - Pre-WebAnalytics | C17: 0 | D17: 16 | E17: =_xlfn.CONCAT(G17, " - ", F17) -> 2005 - 04 | F17: =TEXT(H17,"mm") -> 04 | G17: =TEXT(H17,"YYYY") -> 2005 | H17: 38459 | I17: 14678 | J17: =(I17-$AB$4) / $AB$8 -> -0.58527162 | K17: =IF(J17<=1, "<=1", IF(J17<=2, "<=2", IF(J17<=3, "<=3", "<=3"))) -> <=1 | N17: =IF(J17>=3, 3, IF(J17>=2, 2, IF(J17>=1, 1, IF(J17>=-2, -2, IF(J17>=-3, -3, "Error"))))) -> -2 | O17: 12 | P17: 18159 | X17: 2005 - 04 | Y17: 14678 | AA17: Confidence Level(95%) | AB17: 790.60578
A18: Pre-WebAnalytics | B18: =_xlfn.CONCAT(C18, " - ", A18) -> 0 - Pre-WebAnalytics | C18: 0 | D18: 17 | E18: =_xlfn.CONCAT(G18, " - ", F18) -> 2005 - 04 | F18: =TEXT(H18,"mm") -> 04 | G18: =TEXT(H18,"YYYY") -> 2005 | H18: 38466 | I18: 30844 | J18: =(I18-$AB$4) / $AB$8 -> 1.7780032 | K18: =IF(J18<=1, "<=1", IF(J18<=2, "<=2", IF(J18<=3, "<=3", "<=3"))) -> <=2 | N18: =IF(J18>=3, 3, IF(J18>=2, 2, IF(J18>=1, 1, IF(J18>=-2, -2, IF(J18>=-3, -3, "Error"))))) -> 1 | O18: 13 | P18: 22149 | X18: 2005 - 04 | Y18: 30844
A19: Pre-WebAnalytics | B19: =_xlfn.CONCAT(C19, " - ", A19) -> 0 - Pre-WebAnalytics | C19: 0 | D19: 18 | E19: =_xlfn.CONCAT(G19, " - ", F19) -> 2005 - 05 | F19: =TEXT(H19,"mm") -> 05 | G19: =TEXT(H19,"YYYY") -> 2005 | H19: 38473 | I19: 17701 | J19: =(I19-$AB$4) / $AB$8 -> -0.14334537 | K19: =IF(J19<=1, "<=1", IF(J19<=2, "<=2", IF(J19<=3, "<=3", "<=3"))) -> <=1 | N19: =IF(J19>=3, 3, IF(J19>=2, 2, IF(J19>=1, 1, IF(J19>=-2, -2, IF(J19>=-3, -3, "Error"))))) -> -2 | O19: 14 | P19: 14492 | X19: 2005 - 05 | Y19: 17701
A20: Pre-WebAnalytics | B20: =_xlfn.CONCAT(C20, " - ", A20) -> 0 - Pre-WebAnalytics | C20: 0 | D20: 19 | E20: =_xlfn.CONCAT(G20, " - ", F20) -> 2005 - 05 | F20: =TEXT(H20,"mm") -> 05 | G20: =TEXT(H20,"YYYY") -> 2005 | H20: 38480 | I20: 15220 | J20: =(I20-$AB$4) / $AB$8 -> -0.50603774 | K20: =IF(J20<=1, "<=1", IF(J20<=2, "<=2", IF(J20<=3, "<=3", "<=3"))) -> <=1 | N20: =IF(J20>=3, 3, IF(J20>=2, 2, IF(J20>=1, 1, IF(J20>=-2, -2, IF(J20>=-3, -3, "Error"))))) -> -2 | O20: 15 | P20: 19012 | X20: 2005 - 05 | Y20: 15220
A21: Pre-WebAnalytics | B21: =_xlfn.CONCAT(C21, " - ", A21) -> 0 - Pre-WebAnalytics | C21: 0 | D21: 20 | E21: =_xlfn.CONCAT(G21, " - ", F21) -> 2005 - 05 | F21: =TEXT(H21,"mm") -> 05 | G21: =TEXT(H21,"YYYY") -> 2005 | H21: 38487 | I21: 15504 | J21: =(I21-$AB$4) / $AB$8 -> -0.46452035 | K21: =IF(J21<=1, "<=1", IF(J21<=2, "<=2", IF(J21<=3, "<=3", "<=3"))) -> <=1 | N21: =IF(J21>=3, 3, IF(J21>=2, 2, IF(J21>=1, 1, IF(J21>=-2, -2, IF(J21>=-3, -3, "Error"))))) -> -2 | O21: 16 | P21: 14678 | X21: 2005 - 05 | Y21: 15504
A22: Pre-WebAnalytics | B22: =_xlfn.CONCAT(C22, " - ", A22) -> 0 - Pre-WebAnalytics | C22: 0 | D22: 21 | E22: =_xlfn.CONCAT(G22, " - ", F22) -> 2005 - 05 | F22: =TEXT(H22,"mm") -> 05 | G22: =TEXT(H22,"YYYY") -> 2005 | H22: 38494 | I22: 23957 | J22: =(I22-$AB$4) / $AB$8 -> 0.77120659 | K22: =IF(J22<=1, "<=1", IF(J22<=2, "<=2", IF(J22<=3, "<=3", "<=3"))) -> <=1 | N22: =IF(J22>=3, 3, IF(J22>=2, 2, IF(J22>=1, 1, IF(J22>=-2, -2, IF(J22>=-3, -3, "Error"))))) -> -2 | O22: 17 | P22: 30844 | X22: 2005 - 05 | Y22: 23957
A23: Pre-WebAnalytics | B23: =_xlfn.CONCAT(C23, " - ", A23) -> 0 - Pre-WebAnalytics | C23: 0 | D23: 22 | E23: =_xlfn.CONCAT(G23, " - ", F23) -> 2005 - 05 | F23: =TEXT(H23,"mm") -> 05 | G23: =TEXT(H23,"YYYY") -> 2005 | H23: 38501 | I23: 16153 | J23: =(I23-$AB$4) / $AB$8 -> -0.36964436 | K23: =IF(J23<=1, "<=1", IF(J23<=2, "<=2", IF(J23<=3, "<=3", "<=3"))) -> <=1 | N23: =IF(J23>=3, 3, IF(J23>=2, 2, IF(J23>=1, 1, IF(J23>=-2, -2, IF(J23>=-3, -3, "Error"))))) -> -2 | O23: 18 | P23: 17701 | X23: 2005 - 05 | Y23: 16153
A24: Pre-WebAnalytics | B24: =_xlfn.CONCAT(C24, " - ", A24) -> 0 - Pre-WebAnalytics | C24: 0 | D24: 23 | E24: =_xlfn.CONCAT(G24, " - ", F24) -> 2005 - 06 | F24: =TEXT(H24,"mm") -> 06 | G24: =TEXT(H24,"YYYY") -> 2005 | H24: 38508 | I24: 15901 | J24: =(I24-$AB$4) / $AB$8 -> -0.40648373 | K24: =IF(J24<=1, "<=1", IF(J24<=2, "<=2", IF(J24<=3, "<=3", "<=3"))) -> <=1 | N24: =IF(J24>=3, 3, IF(J24>=2, 2, IF(J24>=1, 1, IF(J24>=-2, -2, IF(J24>=-3, -3, "Error"))))) -> -2 | O24: 19 | P24: 15220 | X24: 2005 - 06 | Y24: 15901
A25: Pre-WebAnalytics | B25: =_xlfn.CONCAT(C25, " - ", A25) -> 0 - Pre-WebAnalytics | C25: 0 | D25: 24 | E25: =_xlfn.CONCAT(G25, " - ", F25) -> 2005 - 06 | F25: =TEXT(H25,"mm") -> 06 | G25: =TEXT(H25,"YYYY") -> 2005 | H25: 38515 | I25: 26637 | J25: =(I25-$AB$4) / $AB$8 -> 1.1629904 | K25: =IF(J25<=1, "<=1", IF(J25<=2, "<=2", IF(J25<=3, "<=3", "<=3"))) -> <=2 | N25: =IF(J25>=3, 3, IF(J25>=2, 2, IF(J25>=1, 1, IF(J25>=-2, -2, IF(J25>=-3, -3, "Error"))))) -> 1 | O25: 20 | P25: 15504 | X25: 2005 - 06 | Y25: 26637
A26: Pre-WebAnalytics | B26: =_xlfn.CONCAT(C26, " - ", A26) -> 0 - Pre-WebAnalytics | C26: 0 | D26: 25 | E26: =_xlfn.CONCAT(G26, " - ", F26) -> 2005 - 06 | F26: =TEXT(H26,"mm") -> 06 | G26: =TEXT(H26,"YYYY") -> 2005 | H26: 38522 | I26: 16538 | J26: =(I26-$AB$4) / $AB$8 -> -0.31336199 | K26: =IF(J26<=1, "<=1", IF(J26<=2, "<=2", IF(J26<=3, "<=3", "<=3"))) -> <=1 | N26: =IF(J26>=3, 3, IF(J26>=2, 2, IF(J26>=1, 1, IF(J26>=-2, -2, IF(J26>=-3, -3, "Error"))))) -> -2 | O26: 21 | P26: 23957 | X26: 2005 - 06 | Y26: 16538
A27: Pre-WebAnalytics | B27: =_xlfn.CONCAT(C27, " - ", A27) -> 0 - Pre-WebAnalytics | C27: 0 | D27: 26 | E27: =_xlfn.CONCAT(G27, " - ", F27) -> 2005 - 06 | F27: =TEXT(H27,"mm") -> 06 | G27: =TEXT(H27,"YYYY") -> 2005 | H27: 38529 | I27: 26581 | J27: =(I27-$AB$4) / $AB$8 -> 1.1548038 | K27: =IF(J27<=1, "<=1", IF(J27<=2, "<=2", IF(J27<=3, "<=3", "<=3"))) -> <=2 | N27: =IF(J27>=3, 3, IF(J27>=2, 2, IF(J27>=1, 1, IF(J27>=-2, -2, IF(J27>=-3, -3, "Error"))))) -> 1 | O27: 22 | P27: 16153 | X27: 2005 - 06 | Y27: 26581
A28: Pre-WebAnalytics | B28: =_xlfn.CONCAT(C28, " - ", A28) -> 0 - Pre-WebAnalytics | C28: 0 | D28: 27 | E28: =_xlfn.CONCAT(G28, " - ", F28) -> 2005 - 07 | F28: =TEXT(H28,"mm") -> 07 | G28: =TEXT(H28,"YYYY") -> 2005 | H28: 38536 | I28: 4536 | J28: =(I28-$AB$4) / $AB$8 -> -2.0679101 | K28: =IF(J28<=1, "<=1", IF(J28<=2, "<=2", IF(J28<=3, "<=3", "<=3"))) -> <=1 | N28: =IF(J28>=3, 3, IF(J28>=2, 2, IF(J28>=1, 1, IF(J28>=-2, -2, IF(J28>=-3, -3, "Error"))))) -> -3 | O28: 23 | P28: 15901 | X28: 2005 - 07 | Y28: 4536
A29: Pre-WebAnalytics | B29: =_xlfn.CONCAT(C29, " - ", A29) -> 0 - Pre-WebAnalytics | C29: 0 | D29: 28 | E29: =_xlfn.CONCAT(G29, " - ", F29) -> 2005 - 07 | F29: =TEXT(H29,"mm") -> 07 | G29: =TEXT(H29,"YYYY") -> 2005 | H29: 38543 | I29: 26737 | J29: =(I29-$AB$4) / $AB$8 -> 1.1776092 | K29: =IF(J29<=1, "<=1", IF(J29<=2, "<=2", IF(J29<=3, "<=3", "<=3"))) -> <=2 | N29: =IF(J29>=3, 3, IF(J29>=2, 2, IF(J29>=1, 1, IF(J29>=-2, -2, IF(J29>=-3, -3, "Error"))))) -> 1 | O29: 24 | P29: 26637 | X29: 2005 - 07 | Y29: 26737
... A117: Pre-WebAnalytics | B117: =_xlfn.CONCAT(C117, " - ", A117) -> 0 - Pre-WebAnalytics | C117: 0 | D117: 116 | E117: =_xlfn.CONCAT(G117, " - ", F117) -> 2007 - 03 | F117: =TEXT(H117,"mm") -> 03 | G117: =TEXT(H117,"YYYY") -> 2007 | H117: 39159 | I117: 12426 | J117: =(I117-$AB$4) / $AB$8 -> -0.91448694 | K117: =IF(J117<=1, "<=1", IF(J117<=2, "<=2", IF(J117<=3, "<=3", "<=3"))) -> <=1 | N117: =IF(J117>=3, 3, IF(J117>=2, 2, IF(J117>=1, 1, IF(J117>=-2, -2, IF(J117>=-3, -3, "Error"))))) -> -2 | O117: 112 | P117: 23178 | X117: 2007 - 03 | Y117: 12426
A118: Pre-WebAnalytics | B118: =_xlfn.CONCAT(C118, " - ", A118) -> 0 - Pre-WebAnalytics | C118: 0 | D118: 117 | E118: =_xlfn.CONCAT(G118, " - ", F118) -> 2007 - 03 | F118: =TEXT(H118,"mm") -> 03 | G118: =TEXT(H118,"YYYY") -> 2007 | H118: 39166 | I118: 32266 | J118: =(I118-$AB$4) / $AB$8 -> 1.9858825 | K118: =IF(J118<=1, "<=1", IF(J118<=2, "<=2", IF(J118<=3, "<=3", "<=3"))) -> <=2 | L118: =COUNTA(K84:K118) -> 35 | M118: =1-(L118/L133) -> #DIV/0! | N118: =IF(J118>=3, 3, IF(J118>=2, 2, IF(J118>=1, 1, IF(J118>=-2, -2, IF(J118>=-3, -3, "Error"))))) -> 1 | O118: 113 | P118: 24919 | X118: 2007 - 03 | Y118: 32266
A119: Pre-WebAnalytics | B119: =_xlfn.CONCAT(C119, " - ", A119) -> 0 - Pre-WebAnalytics | C119: 0 | D119: 118 | E119: =_xlfn.CONCAT(G119, " - ", F119) -> 2007 - 04 | F119: =TEXT(H119,"mm") -> 04 | G119: =TEXT(H119,"YYYY") -> 2007 | H119: 39173 | I119: 21981 | J119: =(I119-$AB$4) / $AB$8 -> 0.48233916 | K119: =IF(J119<=1, "<=1", IF(J119<=2, "<=2", IF(J119<=3, "<=3", "<=3"))) -> <=1 | N119: =IF(J119>=3, 3, IF(J119>=2, 2, IF(J119>=1, 1, IF(J119>=-2, -2, IF(J119>=-3, -3, "Error"))))) -> -2 | O119: 114 | P119: 15258 | X119: 2007 - 04 | Y119: 21981
A120: Pre-WebAnalytics | B120: =_xlfn.CONCAT(C120, " - ", A120) -> 0 - Pre-WebAnalytics | C120: 0 | D120: 119 | E120: =_xlfn.CONCAT(G120, " - ", F120) -> 2007 - 04 | F120: =TEXT(H120,"mm") -> 04 | G120: =TEXT(H120,"YYYY") -> 2007 | H120: 39180 | I120: 12558 | J120: =(I120-$AB$4) / $AB$8 -> -0.89519013 | K120: =IF(J120<=1, "<=1", IF(J120<=2, "<=2", IF(J120<=3, "<=3", "<=3"))) -> <=1 | N120: =IF(J120>=3, 3, IF(J120>=2, 2, IF(J120>=1, 1, IF(J120>=-2, -2, IF(J120>=-3, -3, "Error"))))) -> -2 | O120: 115 | P120: 8492 | X120: 2007 - 04 | Y120: 12558
A121: Pre-WebAnalytics | B121: =_xlfn.CONCAT(C121, " - ", A121) -> 0 - Pre-WebAnalytics | C121: 0 | D121: 120 | E121: =_xlfn.CONCAT(G121, " - ", F121) -> 2007 - 04 | F121: =TEXT(H121,"mm") -> 04 | G121: =TEXT(H121,"YYYY") -> 2007 | H121: 39187 | I121: 9299 | J121: =(I121-$AB$4) / $AB$8 -> -1.3716167 | K121: =IF(J121<=1, "<=1", IF(J121<=2, "<=2", IF(J121<=3, "<=3", "<=3"))) -> <=1 | N121: =IF(J121>=3, 3, IF(J121>=2, 2, IF(J121>=1, 1, IF(J121>=-2, -2, IF(J121>=-3, -3, "Error"))))) -> -2 | O121: 116 | P121: 12426 | X121: 2007 - 04 | Y121: 9299
A122: Pre-WebAnalytics | B122: =_xlfn.CONCAT(C122, " - ", A122) -> 0 - Pre-WebAnalytics | C122: 0 | D122: 121 | E122: =_xlfn.CONCAT(G122, " - ", F122) -> 2007 - 04 | F122: =TEXT(H122,"mm") -> 04 | G122: =TEXT(H122,"YYYY") -> 2007 | H122: 39194 | I122: 25516 | J122: =(I122-$AB$4) / $AB$8 -> 0.99911365 | K122: =IF(J122<=1, "<=1", IF(J122<=2, "<=2", IF(J122<=3, "<=3", "<=3"))) -> <=1 | L122: =COUNTA(K32:K122) -> 91 | M122: =L122/L172 -> #DIV/0! | N122: =IF(J122>=3, 3, IF(J122>=2, 2, IF(J122>=1, 1, IF(J122>=-2, -2, IF(J122>=-3, -3, "Error"))))) -> -2 | O122: 117 | P122: 32266 | X122: 2007 - 04 | Y122: 25516
A123: Pre-WebAnalytics | B123: =_xlfn.CONCAT(C123, " - ", A123) -> 0 - Pre-WebAnalytics | C123: 0 | D123: 122 | E123: =_xlfn.CONCAT(G123, " - ", F123) -> 2007 - 04 | F123: =TEXT(H123,"mm") -> 04 | G123: =TEXT(H123,"YYYY") -> 2007 | H123: 39201 | I123: 15326 | J123: =(I123-$AB$4) / $AB$8 -> -0.49054181 | K123: =IF(J123<=1, "<=1", IF(J123<=2, "<=2", IF(J123<=3, "<=3", "<=3"))) -> <=1 | N123: =IF(J123>=3, 3, IF(J123>=2, 2, IF(J123>=1, 1, IF(J123>=-2, -2, IF(J123>=-3, -3, "Error"))))) -> -2 | O123: 118 | P123: 21981 | X123: 2007 - 04 | Y123: 15326
A124: Pre-WebAnalytics | B124: =_xlfn.CONCAT(C124, " - ", A124) -> 0 - Pre-WebAnalytics | C124: 0 | D124: 123 | E124: =_xlfn.CONCAT(G124, " - ", F124) -> 2007 - 05 | F124: =TEXT(H124,"mm") -> 05 | G124: =TEXT(H124,"YYYY") -> 2007 | H124: 39208 | I124: 13354 | J124: =(I124-$AB$4) / $AB$8 -> -0.7788245 | K124: =IF(J124<=1, "<=1", IF(J124<=2, "<=2", IF(J124<=3, "<=3", "<=3"))) -> <=1 | N124: =IF(J124>=3, 3, IF(J124>=2, 2, IF(J124>=1, 1, IF(J124>=-2, -2, IF(J124>=-3, -3, "Error"))))) -> -2 | O124: 119 | P124: 12558 | X124: 2007 - 05 | Y124: 13354
A125: Pre-WebAnalytics | B125: =_xlfn.CONCAT(C125, " - ", A125) -> 0 - Pre-WebAnalytics | C125: 0 | D125: 124 | E125: =_xlfn.CONCAT(G125, " - ", F125) -> 2007 - 05 | F125: =TEXT(H125,"mm") -> 05 | G125: =TEXT(H125,"YYYY") -> 2007 | H125: 39215 | I125: 21417 | J125: =(I125-$AB$4) / $AB$8 -> 0.39988914 | K125: =IF(J125<=1, "<=1", IF(J125<=2, "<=2", IF(J125<=3, "<=3", "<=3"))) -> <=1 | N125: =IF(J125>=3, 3, IF(J125>=2, 2, IF(J125>=1, 1, IF(J125>=-2, -2, IF(J125>=-3, -3, "Error"))))) -> -2 | O125: 120 | P125: 9299 | X125: 2007 - 05 | Y125: 21417
A126: Pre-WebAnalytics | B126: =_xlfn.CONCAT(C126, " - ", A126) -> 0 - Pre-WebAnalytics | C126: 0 | D126: 125 | E126: =_xlfn.CONCAT(G126, " - ", F126) -> 2007 - 05 | F126: =TEXT(H126,"mm") -> 05 | G126: =TEXT(H126,"YYYY") -> 2007 | H126: 39222 | I126: 25529 | J126: =(I126-$AB$4) / $AB$8 -> 1.0010141 | K126: =IF(J126<=1, "<=1", IF(J126<=2, "<=2", IF(J126<=3, "<=3", "<=3"))) -> <=2 | N126: =IF(J126>=3, 3, IF(J126>=2, 2, IF(J126>=1, 1, IF(J126>=-2, -2, IF(J126>=-3, -3, "Error"))))) -> 1 | O126: 121 | P126: 25516 | X126: 2007 - 05 | Y126: 25529
A127: Pre-WebAnalytics | B127: =_xlfn.CONCAT(C127, " - ", A127) -> 0 - Pre-WebAnalytics | C127: 0 | D127: 126 | E127: =_xlfn.CONCAT(G127, " - ", F127) -> 2007 - 05 | F127: =TEXT(H127,"mm") -> 05 | G127: =TEXT(H127,"YYYY") -> 2007 | H127: 39229 | I127: 19585 | J127: =(I127-$AB$4) / $AB$8 -> 0.13207277 | K127: =IF(J127<=1, "<=1", IF(J127<=2, "<=2", IF(J127<=3, "<=3", "<=3"))) -> <=1 | N127: =IF(J127>=3, 3, IF(J127>=2, 2, IF(J127>=1, 1, IF(J127>=-2, -2, IF(J127>=-3, -3, "Error"))))) -> -2 | O127: 122 | P127: 15326 | X127: 2007 - 05 | Y127: 19585
A128: Pre-WebAnalytics | B128: =_xlfn.CONCAT(C128, " - ", A128) -> 0 - Pre-WebAnalytics | C128: 0 | D128: 127 | E128: =_xlfn.CONCAT(G128, " - ", F128) -> 2007 - 06 | F128: =TEXT(H128,"mm") -> 06 | G128: =TEXT(H128,"YYYY") -> 2007 | H128: 39236 | I128: 28865 | J128: =(I128-$AB$4) / $AB$8 -> 1.4886972 | K128: =IF(J128<=1, "<=1", IF(J128<=2, "<=2", IF(J128<=3, "<=3", "<=3"))) -> <=2 | N128: =IF(J128>=3, 3, IF(J128>=2, 2, IF(J128>=1, 1, IF(J128>=-2, -2, IF(J128>=-3, -3, "Error"))))) -> 1 | O128: 123 | P128: 13354 | X128: 2007 - 06 | Y128: 28865
A129: Pre-WebAnalytics | B129: =_xlfn.CONCAT(C129, " - ", A129) -> 0 - Pre-WebAnalytics | C129: 0 | D129: 128 | E129: =_xlfn.CONCAT(G129, " - ", F129) -> 2007 - 06 | F129: =TEXT(H129,"mm") -> 06 | G129: =TEXT(H129,"YYYY") -> 2007 | H129: 39243 | I129: 14905 | J129: =(I129-$AB$4) / $AB$8 -> -0.55208695 | K129: =IF(J129<=1, "<=1", IF(J129<=2, "<=2", IF(J129<=3, "<=3", "<=3"))) -> <=1 | N129: =IF(J129>=3, 3, IF(J129>=2, 2, IF(J129>=1, 1, IF(J129>=-2, -2, IF(J129>=-3, -3, "Error"))))) -> -2 | O129: 124 | P129: 21417 | X129: 2007 - 06 | Y129: 14905
A130: Pre-WebAnalytics | B130: =_xlfn.CONCAT(C130, " - ", A130) -> 0 - Pre-WebAnalytics | C130: 0 | D130: 129 | E130: =_xlfn.CONCAT(G130, " - ", F130) -> 2007 - 06 | F130: =TEXT(H130,"mm") -> 06 | G130: =TEXT(H130,"YYYY") -> 2007 | H130: 39250 | I130: 16386 | J130: =(I130-$AB$4) / $AB$8 -> -0.33558256 | K130: =IF(J130<=1, "<=1", IF(J130<=2, "<=2", IF(J130<=3, "<=3", "<=3"))) -> <=1 | N130: =IF(J130>=3, 3, IF(J130>=2, 2, IF(J130>=1, 1, IF(J130>=-2, -2, IF(J130>=-3, -3, "Error"))))) -> -2 | O130: 125 | P130: 25529 | X130: 2007 - 06 | Y130: 16386
A131: Pre-WebAnalytics | B131: =_xlfn.CONCAT(C131, " - ", A131) -> 0 - Pre-WebAnalytics | C131: 0 | D131: 130 | E131: =_xlfn.CONCAT(G131, " - ", F131) -> 2007 - 06 | F131: =TEXT(H131,"mm") -> 06 | G131: =TEXT(H131,"YYYY") -> 2007 | H131: 39257 | I131: 20385 | J131: =(I131-$AB$4) / $AB$8 -> 0.24902315 | K131: =IF(J131<=1, "<=1", IF(J131<=2, "<=2", IF(J131<=3, "<=3", "<=3"))) -> <=1 | N131: =IF(J131>=3, 3, IF(J131>=2, 2, IF(J131>=1, 1, IF(J131>=-2, -2, IF(J131>=-3, -3, "Error"))))) -> -2 | O131: 126 | P131: 19585 | X131: 2007 - 06 | Y131: 20385
A132: Pre-WebAnalytics | B132: =_xlfn.CONCAT(C132, " - ", A132) -> 0 - Pre-WebAnalytics | C132: 0 | D132: 131 | E132: =_xlfn.CONCAT(G132, " - ", F132) -> 2007 - 07 | F132: =TEXT(H132,"mm") -> 07 | G132: =TEXT(H132,"YYYY") -> 2007 | H132: 39264 | I132: 4173 | J132: =(I132-$AB$4) / $AB$8 -> -2.1209763 | K132: =IF(J132<=1, "<=1", IF(J132<=2, "<=2", IF(J132<=3, "<=3", "<=3"))) -> <=1 | N132: =IF(J132>=3, 3, IF(J132>=2, 2, IF(J132>=1, 1, IF(J132>=-2, -2, IF(J132>=-3, -3, "Error"))))) -> -3 | O132: 127 | P132: 28865 | X132: 2007 - 07 | Y132: 4173
A133: Pre-WebAnalytics | B133: =_xlfn.CONCAT(C133, " - ", A133) -> 0 - Pre-WebAnalytics | C133: 0 | D133: 132 | E133: =_xlfn.CONCAT(G133, " - ", F133) -> 2007 - 07 | F133: =TEXT(H133,"mm") -> 07 | G133: =TEXT(H133,"YYYY") -> 2007 | H133: 39271 | I133: 20030 | J133: =(I133-$AB$4) / $AB$8 -> 0.19712642 | K133: =IF(J133<=1, "<=1", IF(J133<=2, "<=2", IF(J133<=3, "<=3", "<=3"))) -> <=1 | N133: =IF(J133>=3, 3, IF(J133>=2, 2, IF(J133>=1, 1, IF(J133>=-2, -2, IF(J133>=-3, -3, "Error"))))) -> -2 | O133: 128 | P133: 14905 | X133: 2007 - 07 | Y133: 20030
A134: Pre-WebAnalytics | B134: =_xlfn.CONCAT(C134, " - ", A134) -> 0 - Pre-WebAnalytics | C134: 0 | D134: 133 | E134: =_xlfn.CONCAT(G134, " - ", F134) -> 2007 - 07 | F134: =TEXT(H134,"mm") -> 07 | G134: =TEXT(H134,"YYYY") -> 2007 | H134: 39278 | I134: 11964 | J134: =(I134-$AB$4) / $AB$8 -> -0.98202578 | K134: =IF(J134<=1, "<=1", IF(J134<=2, "<=2", IF(J134<=3, "<=3", "<=3"))) -> <=1 | N134: =IF(J134>=3, 3, IF(J134>=2, 2, IF(J134>=1, 1, IF(J134>=-2, -2, IF(J134>=-3, -3, "Error"))))) -> -2 | O134: 129 | P134: 16386 | X134: 2007 - 07 | Y134: 11964
... A174: Pre-WebAnalytics | B174: =_xlfn.CONCAT(C174, " - ", A174) -> 0 - Pre-WebAnalytics | C174: 0 | D174: 173 | E174: =_xlfn.CONCAT(G174, " - ", F174) -> 2008 - 04 | F174: =TEXT(H174,"mm") -> 04 | G174: =TEXT(H174,"YYYY") -> 2008 | H174: 39558 | I174: 17188 | J174: =(I174-$AB$4) / $AB$8 -> -0.21833981 | K174: =IF(J174<=1, "<=1", IF(J174<=2, "<=2", IF(J174<=3, "<=3", "<=3"))) -> <=1 | N174: =IF(J174>=3, 3, IF(J174>=2, 2, IF(J174>=1, 1, IF(J174>=-2, -2, IF(J174>=-3, -3, "Error"))))) -> -2 | O174: 169 | P174: 34894 | X174: 2008 - 04 | Y174: 17188
A175: Pre-WebAnalytics | B175: =_xlfn.CONCAT(C175, " - ", A175) -> 0 - Pre-WebAnalytics | C175: 0 | D175: 174 | E175: =_xlfn.CONCAT(G175, " - ", F175) -> 2008 - 04 | F175: =TEXT(H175,"mm") -> 04 | G175: =TEXT(H175,"YYYY") -> 2008 | H175: 39565 | I175: 44740 | J175: =(I175-$AB$4) / $AB$8 -> 3.8094313 | K175: =IF(J175<=1, "<=1", IF(J175<=2, "<=2", IF(J175<=3, "<=3", "<=3"))) -> <=3 | L175: =COUNTA(K165:K175) -> 11 | M175: =1-(L175/L179) -> #DIV/0! | N175: =IF(J175>=3, 3, IF(J175>=2, 2, IF(J175>=1, 1, IF(J175>=-2, -2, IF(J175>=-3, -3, "Error"))))) -> 3 | O175: 170 | P175: 31014 | X175: 2008 - 04 | Y175: 44740
A176: Pre-WebAnalytics | B176: =_xlfn.CONCAT(C176, " - ", A176) -> 0 - Pre-WebAnalytics | C176: 0 | D176: 175 | E176: =_xlfn.CONCAT(G176, " - ", F176) -> 2008 - 05 | F176: =TEXT(H176,"mm") -> 05 | G176: =TEXT(H176,"YYYY") -> 2008 | H176: 39572 | I176: 17902 | J176: =(I176-$AB$4) / $AB$8 -> -0.11396159 | K176: =IF(J176<=1, "<=1", IF(J176<=2, "<=2", IF(J176<=3, "<=3", "<=3"))) -> <=1 | N176: =IF(J176>=3, 3, IF(J176>=2, 2, IF(J176>=1, 1, IF(J176>=-2, -2, IF(J176>=-3, -3, "Error"))))) -> -2 | O176: 171 | P176: 21431 | X176: 2008 - 05 | Y176: 17902
A177: Pre-WebAnalytics | B177: =_xlfn.CONCAT(C177, " - ", A177) -> 0 - Pre-WebAnalytics | C177: 0 | D177: 176 | E177: =_xlfn.CONCAT(G177, " - ", F177) -> 2008 - 05 | F177: =TEXT(H177,"mm") -> 05 | G177: =TEXT(H177,"YYYY") -> 2008 | H177: 39579 | I177: 14145 | J177: =(I177-$AB$4) / $AB$8 -> -0.66318981 | K177: =IF(J177<=1, "<=1", IF(J177<=2, "<=2", IF(J177<=3, "<=3", "<=3"))) -> <=1 | N177: =IF(J177>=3, 3, IF(J177>=2, 2, IF(J177>=1, 1, IF(J177>=-2, -2, IF(J177>=-3, -3, "Error"))))) -> -2 | O177: 172 | P177: 15735 | X177: 2008 - 05 | Y177: 14145
A178: Pre-WebAnalytics | B178: =_xlfn.CONCAT(C178, " - ", A178) -> 0 - Pre-WebAnalytics | C178: 0 | D178: 177 | E178: =_xlfn.CONCAT(G178, " - ", F178) -> 2008 - 05 | F178: =TEXT(H178,"mm") -> 05 | G178: =TEXT(H178,"YYYY") -> 2008 | H178: 39586 | I178: 11076 | J178: =(I178-$AB$4) / $AB$8 -> -1.1118407 | K178: =IF(J178<=1, "<=1", IF(J178<=2, "<=2", IF(J178<=3, "<=3", "<=3"))) -> <=1 | N178: =IF(J178>=3, 3, IF(J178>=2, 2, IF(J178>=1, 1, IF(J178>=-2, -2, IF(J178>=-3, -3, "Error"))))) -> -2 | O178: 173 | P178: 17188 | X178: 2008 - 05 | Y178: 11076
A179: Initial Period | B179: =_xlfn.CONCAT(C179, " - ", A179) -> 1 - Initial Period | C179: 1 | D179: 178 | E179: =_xlfn.CONCAT(G179, " - ", F179) -> 2008 - 05 | F179: =TEXT(H179,"mm") -> 05 | G179: =TEXT(H179,"YYYY") -> 2008 | H179: 39593 | I179: 16585 | J179: =(I179-$AB$4) / $AB$8 -> -0.30649115 | K179: =IF(J179<=1, "<=1", IF(J179<=2, "<=2", IF(J179<=3, "<=3", "<=3"))) -> <=1 | N179: =IF(J179>=3, 3, IF(J179>=2, 2, IF(J179>=1, 1, IF(J179>=-2, -2, IF(J179>=-3, -3, "Error"))))) -> -2 | O179: 174 | P179: 44740 | X179: 2008 - 05 | Y179: 16585
A180: Initial Period | B180: =_xlfn.CONCAT(C180, " - ", A180) -> 1 - Initial Period | C180: 1 | D180: 179 | E180: =_xlfn.CONCAT(G180, " - ", F180) -> 2008 - 06 | F180: =TEXT(H180,"mm") -> 06 | G180: =TEXT(H180,"YYYY") -> 2008 | H180: 39600 | I180: 18906 | J180: =(I180-$AB$4) / $AB$8 -> 0.032811135 | K180: =IF(J180<=1, "<=1", IF(J180<=2, "<=2", IF(J180<=3, "<=3", "<=3"))) -> <=1 | N180: =IF(J180>=3, 3, IF(J180>=2, 2, IF(J180>=1, 1, IF(J180>=-2, -2, IF(J180>=-3, -3, "Error"))))) -> -2 | O180: 175 | P180: 17902 | X180: 2008 - 06 | Y180: 18906
A181: Initial Period | B181: =_xlfn.CONCAT(C181, " - ", A181) -> 1 - Initial Period | C181: 1 | D181: 180 | E181: =_xlfn.CONCAT(G181, " - ", F181) -> 2008 - 06 | F181: =TEXT(H181,"mm") -> 06 | G181: =TEXT(H181,"YYYY") -> 2008 | H181: 39607 | I181: 28053 | J181: =(I181-$AB$4) / $AB$8 -> 1.3699925 | K181: =IF(J181<=1, "<=1", IF(J181<=2, "<=2", IF(J181<=3, "<=3", "<=3"))) -> <=2 | N181: =IF(J181>=3, 3, IF(J181>=2, 2, IF(J181>=1, 1, IF(J181>=-2, -2, IF(J181>=-3, -3, "Error"))))) -> 1 | O181: 176 | P181: 14145 | X181: 2008 - 06 | Y181: 28053
A182: Initial Period | B182: =_xlfn.CONCAT(C182, " - ", A182) -> 1 - Initial Period | C182: 1 | D182: 181 | E182: =_xlfn.CONCAT(G182, " - ", F182) -> 2008 - 06 | F182: =TEXT(H182,"mm") -> 06 | G182: =TEXT(H182,"YYYY") -> 2008 | H182: 39614 | I182: 19382 | J182: =(I182-$AB$4) / $AB$8 -> 0.10239661 | K182: =IF(J182<=1, "<=1", IF(J182<=2, "<=2", IF(J182<=3, "<=3", "<=3"))) -> <=1 | N182: =IF(J182>=3, 3, IF(J182>=2, 2, IF(J182>=1, 1, IF(J182>=-2, -2, IF(J182>=-3, -3, "Error"))))) -> -2 | O182: 177 | P182: 11076 | X182: 2008 - 06 | Y182: 19382
A183: Initial Period | B183: =_xlfn.CONCAT(C183, " - ", A183) -> 1 - Initial Period | C183: 1 | D183: 182 | E183: =_xlfn.CONCAT(G183, " - ", F183) -> 2008 - 06 | F183: =TEXT(H183,"mm") -> 06 | G183: =TEXT(H183,"YYYY") -> 2008 | H183: 39621 | I183: 24274 | J183: =(I183-$AB$4) / $AB$8 -> 0.81754818 | K183: =IF(J183<=1, "<=1", IF(J183<=2, "<=2", IF(J183<=3, "<=3", "<=3"))) -> <=1 | N183: =IF(J183>=3, 3, IF(J183>=2, 2, IF(J183>=1, 1, IF(J183>=-2, -2, IF(J183>=-3, -3, "Error"))))) -> -2 | O183: 1 - Initial Period | X183: 2008 - 06 | Y183: 24274
A184: Initial Period | B184: =_xlfn.CONCAT(C184, " - ", A184) -> 1 - Initial Period | C184: 1 | D184: 183 | E184: =_xlfn.CONCAT(G184, " - ", F184) -> 2008 - 06 | F184: =TEXT(H184,"mm") -> 06 | G184: =TEXT(H184,"YYYY") -> 2008 | H184: 39628 | I184: 15309 | J184: =(I184-$AB$4) / $AB$8 -> -0.49302701 | K184: =IF(J184<=1, "<=1", IF(J184<=2, "<=2", IF(J184<=3, "<=3", "<=3"))) -> <=1 | N184: =IF(J184>=3, 3, IF(J184>=2, 2, IF(J184>=1, 1, IF(J184>=-2, -2, IF(J184>=-3, -3, "Error"))))) -> -2 | O184: 178 | Q184: 16585 | X184: 2008 - 06 | Y184: 15309
A185: Initial Period | B185: =_xlfn.CONCAT(C185, " - ", A185) -> 1 - Initial Period | C185: 1 | D185: 184 | E185: =_xlfn.CONCAT(G185, " - ", F185) -> 2008 - 07 | F185: =TEXT(H185,"mm") -> 07 | G185: =TEXT(H185,"YYYY") -> 2008 | H185: 39635 | I185: 8633 | J185: =(I185-$AB$4) / $AB$8 -> -1.4689779 | K185: =IF(J185<=1, "<=1", IF(J185<=2, "<=2", IF(J185<=3, "<=3", "<=3"))) -> <=1 | N185: =IF(J185>=3, 3, IF(J185>=2, 2, IF(J185>=1, 1, IF(J185>=-2, -2, IF(J185>=-3, -3, "Error"))))) -> -2 | O185: 179 | Q185: 18906 | X185: 2008 - 07 | Y185: 8633
A186: Initial Period | B186: =_xlfn.CONCAT(C186, " - ", A186) -> 1 - Initial Period | C186: 1 | D186: 185 | E186: =_xlfn.CONCAT(G186, " - ", F186) -> 2008 - 07 | F186: =TEXT(H186,"mm") -> 07 | G186: =TEXT(H186,"YYYY") -> 2008 | H186: 39642 | I186: 17216 | J186: =(I186-$AB$4) / $AB$8 -> -0.21424654 | K186: =IF(J186<=1, "<=1", IF(J186<=2, "<=2", IF(J186<=3, "<=3", "<=3"))) -> <=1 | N186: =IF(J186>=3, 3, IF(J186>=2, 2, IF(J186>=1, 1, IF(J186>=-2, -2, IF(J186>=-3, -3, "Error"))))) -> -2 | O186: 180 | Q186: 28053 | X186: 2008 - 07 | Y186: 17216
A187: Initial Period | B187: =_xlfn.CONCAT(C187, " - ", A187) -> 1 - Initial Period | C187: 1 | D187: 186 | E187: =_xlfn.CONCAT(G187, " - ", F187) -> 2008 - 07 | F187: =TEXT(H187,"mm") -> 07 | G187: =TEXT(H187,"YYYY") -> 2008 | H187: 39649 | I187: 17309 | J187: =(I187-$AB$4) / $AB$8 -> -0.20065106 | K187: =IF(J187<=1, "<=1", IF(J187<=2, "<=2", IF(J187<=3, "<=3", "<=3"))) -> <=1 | N187: =IF(J187>=3, 3, IF(J187>=2, 2, IF(J187>=1, 1, IF(J187>=-2, -2, IF(J187>=-3, -3, "Error"))))) -> -2 | O187: 181 | Q187: 19382 | X187: 2008 - 07 | Y187: 17309
A188: Initial Period | B188: =_xlfn.CONCAT(C188, " - ", A188) -> 1 - Initial Period | C188: 1 | D188: 187 | E188: =_xlfn.CONCAT(G188, " - ", F188) -> 2008 - 07 | F188: =TEXT(H188,"mm") -> 07 | G188: =TEXT(H188,"YYYY") -> 2008 | H188: 39656 | I188: 24571 | J188: =(I188-$AB$4) / $AB$8 -> 0.86096601 | K188: =IF(J188<=1, "<=1", IF(J188<=2, "<=2", IF(J188<=3, "<=3", "<=3"))) -> <=1 | N188: =IF(J188>=3, 3, IF(J188>=2, 2, IF(J188>=1, 1, IF(J188>=-2, -2, IF(J188>=-3, -3, "Error"))))) -> -2 | O188: 182 | Q188: 24274 | X188: 2008 - 07 | Y188: 24571
A189: Initial Period | B189: =_xlfn.CONCAT(C189, " - ", A189) -> 1 - Initial Period | C189: 1 | D189: 188 | E189: =_xlfn.CONCAT(G189, " - ", F189) -> 2008 - 08 | F189: =TEXT(H189,"mm") -> 08 | G189: =TEXT(H189,"YYYY") -> 2008 | H189: 39663 | I189: 14390 | J189: =(I189-$AB$4) / $AB$8 -> -0.62737376 | K189: =IF(J189<=1, "<=1", IF(J189<=2, "<=2", IF(J189<=3, "<=3", "<=3"))) -> <=1 | N189: =IF(J189>=3, 3, IF(J189>=2, 2, IF(J189>=1, 1, IF(J189>=-2, -2, IF(J189>=-3, -3, "Error"))))) -> -2 | O189: 183 | Q189: 15309 | X189: 2008 - 08 | Y189: 14390
A190: Initial Period | B190: =_xlfn.CONCAT(C190, " - ", A190) -> 1 - Initial Period | C190: 1 | D190: 189 | E190: =_xlfn.CONCAT(G190, " - ", F190) -> 2008 - 08 | F190: =TEXT(H190,"mm") -> 08 | G190: =TEXT(H190,"YYYY") -> 2008 | H190: 39670 | I190: 17231 | J190: =(I190-$AB$4) / $AB$8 -> -0.21205372 | K190: =IF(J190<=1, "<=1", IF(J190<=2, "<=2", IF(J190<=3, "<=3", "<=3"))) -> <=1 | N190: =IF(J190>=3, 3, IF(J190>=2, 2, IF(J190>=1, 1, IF(J190>=-2, -2, IF(J190>=-3, -3, "Error"))))) -> -2 | O190: 184 | Q190: 8633 | X190: 2008 - 08 | Y190: 17231
A191: Initial Period | B191: =_xlfn.CONCAT(C191, " - ", A191) -> 1 - Initial Period | C191: 1 | D191: 190 | E191: =_xlfn.CONCAT(G191, " - ", F191) -> 2008 - 08 | F191: =TEXT(H191,"mm") -> 08 | G191: =TEXT(H191,"YYYY") -> 2008 | H191: 39677 | I191: 13802 | J191: =(I191-$AB$4) / $AB$8 -> -0.71333229 | K191: =IF(J191<=1, "<=1", IF(J191<=2, "<=2", IF(J191<=3, "<=3", "<=3"))) -> <=1 | N191: =IF(J191>=3, 3, IF(J191>=2, 2, IF(J191>=1, 1, IF(J191>=-2, -2, IF(J191>=-3, -3, "Error"))))) -> -2 | O191: 185 | Q191: 17216 | X191: 2008 - 08 | Y191: 13802
A192: Initial Period | B192: =_xlfn.CONCAT(C192, " - ", A192) -> 1 - Initial Period | C192: 1 | D192: 191 | E192: =_xlfn.CONCAT(G192, " - ", F192) -> 2008 - 08 | F192: =TEXT(H192,"mm") -> 08 | G192: =TEXT(H192,"YYYY") -> 2008 | H192: 39684 | I192: 26653 | J192: =(I192-$AB$4) / $AB$8 -> 1.1653294 | K192: =IF(J192<=1, "<=1", IF(J192<=2, "<=2", IF(J192<=3, "<=3", "<=3"))) -> <=2 | N192: =IF(J192>=3, 3, IF(J192>=2, 2, IF(J192>=1, 1, IF(J192>=-2, -2, IF(J192>=-3, -3, "Error"))))) -> 1 | O192: 186 | Q192: 17309 | X192: 2008 - 08 | Y192: 26653
A193: Pre-Promo | B193: =_xlfn.CONCAT(C193, " - ", A193) -> 2 - Pre-Promo | C193: 2 | D193: 192 | E193: =_xlfn.CONCAT(G193, " - ", F193) -> 2008 - 08 | F193: =TEXT(H193,"mm") -> 08 | G193: =TEXT(H193,"YYYY") -> 2008 | H193: 39691 | I193: 12403 | J193: =(I193-$AB$4) / $AB$8 -> -0.91784926 | K193: =IF(J193<=1, "<=1", IF(J193<=2, "<=2", IF(J193<=3, "<=3", "<=3"))) -> <=1 | N193: =IF(J193>=3, 3, IF(J193>=2, 2, IF(J193>=1, 1, IF(J193>=-2, -2, IF(J193>=-3, -3, "Error"))))) -> -2 | O193: 187 | Q193: 24571 | X193: 2008 - 08 | Y193: 12403
A194: Pre-Promo | B194: =_xlfn.CONCAT(C194, " - ", A194) -> 2 - Pre-Promo | C194: 2 | D194: 193 | E194: =_xlfn.CONCAT(G194, " - ", F194) -> 2008 - 09 | F194: =TEXT(H194,"mm") -> 09 | G194: =TEXT(H194,"YYYY") -> 2008 | H194: 39698 | I194: 11695 | J194: =(I194-$AB$4) / $AB$8 -> -1.0213503 | K194: =IF(J194<=1, "<=1", IF(J194<=2, "<=2", IF(J194<=3, "<=3", "<=3"))) -> <=1 | N194: =IF(J194>=3, 3, IF(J194>=2, 2, IF(J194>=1, 1, IF(J194>=-2, -2, IF(J194>=-3, -3, "Error"))))) -> -2 | O194: 188 | Q194: 14390 | X194: 2008 - 09 | Y194: 11695
A195: Pre-Promo | B195: =_xlfn.CONCAT(C195, " - ", A195) -> 2 - Pre-Promo | C195: 2 | D195: 194 | E195: =_xlfn.CONCAT(G195, " - ", F195) -> 2008 - 09 | F195: =TEXT(H195,"mm") -> 09 | G195: =TEXT(H195,"YYYY") -> 2008 | H195: 39705 | I195: 26362 | J195: =(I195-$AB$4) / $AB$8 -> 1.1227887 | K195: =IF(J195<=1, "<=1", IF(J195<=2, "<=2", IF(J195<=3, "<=3", "<=3"))) -> <=2 | N195: =IF(J195>=3, 3, IF(J195>=2, 2, IF(J195>=1, 1, IF(J195>=-2, -2, IF(J195>=-3, -3, "Error"))))) -> 1 | O195: 189 | Q195: 17231 | X195: 2008 - 09 | Y195: 26362
... A197: Pre-Promo | B197: =_xlfn.CONCAT(C197, " - ", A197) -> 2 - Pre-Promo | C197: 2 | D197: 196 | E197: =_xlfn.CONCAT(G197, " - ", F197) -> 2008 - 09 | F197: =TEXT(H197,"mm") -> 09 | G197: =TEXT(H197,"YYYY") -> 2008 | H197: 39719 | I197: 31972 | J197: =(I197-$AB$4) / $AB$8 -> 1.9429032 | K197: =IF(J197<=1, "<=1", IF(J197<=2, "<=2", IF(J197<=3, "<=3", "<=3"))) -> <=2 | N197: =IF(J197>=3, 3, IF(J197>=2, 2, IF(J197>=1, 1, IF(J197>=-2, -2, IF(J197>=-3, -3, "Error"))))) -> 1 | O197: 191 | Q197: 26653 | X197: 2008 - 09 | Y197: 31972
A198: Pre-Promo | B198: =_xlfn.CONCAT(C198, " - ", A198) -> 2 - Pre-Promo | C198: 2 | D198: 197 | E198: =_xlfn.CONCAT(G198, " - ", F198) -> 2008 - 10 | F198: =TEXT(H198,"mm") -> 10 | G198: =TEXT(H198,"YYYY") -> 2008 | H198: 39726 | I198: 15531 | J198: =(I198-$AB$4) / $AB$8 -> -0.46057328 | K198: =IF(J198<=1, "<=1", IF(J198<=2, "<=2", IF(J198<=3, "<=3", "<=3"))) -> <=1 | N198: =IF(J198>=3, 3, IF(J198>=2, 2, IF(J198>=1, 1, IF(J198>=-2, -2, IF(J198>=-3, -3, "Error"))))) -> -2 | O198: 2 - Pre-Promo | X198: 2008 - 10 | Y198: 15531
A199: Pre-Promo | B199: =_xlfn.CONCAT(C199, " - ", A199) -> 2 - Pre-Promo | C199: 2 | D199: 198 | E199: =_xlfn.CONCAT(G199, " - ", F199) -> 2008 - 10 | F199: =TEXT(H199,"mm") -> 10 | G199: =TEXT(H199,"YYYY") -> 2008 | H199: 39733 | I199: 19734 | J199: =(I199-$AB$4) / $AB$8 -> 0.15385478 | K199: =IF(J199<=1, "<=1", IF(J199<=2, "<=2", IF(J199<=3, "<=3", "<=3"))) -> <=1 | N199: =IF(J199>=3, 3, IF(J199>=2, 2, IF(J199>=1, 1, IF(J199>=-2, -2, IF(J199>=-3, -3, "Error"))))) -> -2 | O199: 192 | R199: 12403 | X199: 2008 - 10 | Y199: 19734
A200: Pre-Promo | B200: =_xlfn.CONCAT(C200, " - ", A200) -> 2 - Pre-Promo | C200: 2 | D200: 199 | E200: =_xlfn.CONCAT(G200, " - ", F200) -> 2008 - 10 | F200: =TEXT(H200,"mm") -> 10 | G200: =TEXT(H200,"YYYY") -> 2008 | H200: 39740 | I200: 17193 | J200: =(I200-$AB$4) / $AB$8 -> -0.21760887 | K200: =IF(J200<=1, "<=1", IF(J200<=2, "<=2", IF(J200<=3, "<=3", "<=3"))) -> <=1 | N200: =IF(J200>=3, 3, IF(J200>=2, 2, IF(J200>=1, 1, IF(J200>=-2, -2, IF(J200>=-3, -3, "Error"))))) -> -2 | O200: 193 | R200: 11695 | X200: 2008 - 10 | Y200: 17193
A201: Pre-Promo | B201: =_xlfn.CONCAT(C201, " - ", A201) -> 2 - Pre-Promo | C201: 2 | D201: 200 | E201: =_xlfn.CONCAT(G201, " - ", F201) -> 2008 - 10 | F201: =TEXT(H201,"mm") -> 10 | G201: =TEXT(H201,"YYYY") -> 2008 | H201: 39747 | I201: 22591 | J201: =(I201-$AB$4) / $AB$8 -> 0.57151382 | K201: =IF(J201<=1, "<=1", IF(J201<=2, "<=2", IF(J201<=3, "<=3", "<=3"))) -> <=1 | N201: =IF(J201>=3, 3, IF(J201>=2, 2, IF(J201>=1, 1, IF(J201>=-2, -2, IF(J201>=-3, -3, "Error"))))) -> -2 | O201: 194 | R201: 26362 | X201: 2008 - 10 | Y201: 22591
A202: Pre-Promo | B202: =_xlfn.CONCAT(C202, " - ", A202) -> 2 - Pre-Promo | C202: 2 | D202: 201 | E202: =_xlfn.CONCAT(G202, " - ", F202) -> 2008 - 11 | F202: =TEXT(H202,"mm") -> 11 | G202: =TEXT(H202,"YYYY") -> 2008 | H202: 39754 | I202: 8992 | J202: =(I202-$AB$4) / $AB$8 -> -1.4164964 | K202: =IF(J202<=1, "<=1", IF(J202<=2, "<=2", IF(J202<=3, "<=3", "<=3"))) -> <=1 | N202: =IF(J202>=3, 3, IF(J202>=2, 2, IF(J202>=1, 1, IF(J202>=-2, -2, IF(J202>=-3, -3, "Error"))))) -> -2 | O202: 195 | R202: 15772 | X202: 2008 - 11 | Y202: 8992
A203: Pre-Promo | B203: =_xlfn.CONCAT(C203, " - ", A203) -> 2 - Pre-Promo | C203: 2 | D203: 202 | E203: =_xlfn.CONCAT(G203, " - ", F203) -> 2008 - 11 | F203: =TEXT(H203,"mm") -> 11 | G203: =TEXT(H203,"YYYY") -> 2008 | H203: 39761 | I203: 19104 | J203: =(I203-$AB$4) / $AB$8 -> 0.061756354 | K203: =IF(J203<=1, "<=1", IF(J203<=2, "<=2", IF(J203<=3, "<=3", "<=3"))) -> <=1 | N203: =IF(J203>=3, 3, IF(J203>=2, 2, IF(J203>=1, 1, IF(J203>=-2, -2, IF(J203>=-3, -3, "Error"))))) -> -2 | O203: 196 | R203: 31972 | X203: 2008 - 11 | Y203: 19104
A204: Pre-Promo | B204: =_xlfn.CONCAT(C204, " - ", A204) -> 2 - Pre-Promo | C204: 2 | D204: 203 | E204: =_xlfn.CONCAT(G204, " - ", F204) -> 2008 - 11 | F204: =TEXT(H204,"mm") -> 11 | G204: =TEXT(H204,"YYYY") -> 2008 | H204: 39768 | I204: 21455 | J204: =(I204-$AB$4) / $AB$8 -> 0.40544428 | K204: =IF(J204<=1, "<=1", IF(J204<=2, "<=2", IF(J204<=3, "<=3", "<=3"))) -> <=1 | N204: =IF(J204>=3, 3, IF(J204>=2, 2, IF(J204>=1, 1, IF(J204>=-2, -2, IF(J204>=-3, -3, "Error"))))) -> -2 | O204: 197 | R204: 15531 | X204: 2008 - 11 | Y204: 21455
A205: Pre-Promo | B205: =_xlfn.CONCAT(C205, " - ", A205) -> 2 - Pre-Promo | C205: 2 | D205: 204 | E205: =_xlfn.CONCAT(G205, " - ", F205) -> 2008 - 11 | F205: =TEXT(H205,"mm") -> 11 | G205: =TEXT(H205,"YYYY") -> 2008 | H205: 39775 | I205: 18784 | J205: =(I205-$AB$4) / $AB$8 -> 0.014976202 | K205: =IF(J205<=1, "<=1", IF(J205<=2, "<=2", IF(J205<=3, "<=3", "<=3"))) -> <=1 | N205: =IF(J205>=3, 3, IF(J205>=2, 2, IF(J205>=1, 1, IF(J205>=-2, -2, IF(J205>=-3, -3, "Error"))))) -> -2 | O205: 198 | R205: 19734 | X205: 2008 - 11 | Y205: 18784
A206: Pre-Promo | B206: =_xlfn.CONCAT(C206, " - ", A206) -> 2 - Pre-Promo | C206: 2 | D206: 205 | E206: =_xlfn.CONCAT(G206, " - ", F206) -> 2008 - 11 | F206: =TEXT(H206,"mm") -> 11 | G206: =TEXT(H206,"YYYY") -> 2008 | H206: 39782 | I206: 14298 | J206: =(I206-$AB$4) / $AB$8 -> -0.64082305 | K206: =IF(J206<=1, "<=1", IF(J206<=2, "<=2", IF(J206<=3, "<=3", "<=3"))) -> <=1 | N206: =IF(J206>=3, 3, IF(J206>=2, 2, IF(J206>=1, 1, IF(J206>=-2, -2, IF(J206>=-3, -3, "Error"))))) -> -2 | O206: 199 | R206: 17193 | X206: 2008 - 11 | Y206: 14298
A207: Pre-Promo | B207: =_xlfn.CONCAT(C207, " - ", A207) -> 2 - Pre-Promo | C207: 2 | D207: 206 | E207: =_xlfn.CONCAT(G207, " - ", F207) -> 2008 - 12 | F207: =TEXT(H207,"mm") -> 12 | G207: =TEXT(H207,"YYYY") -> 2008 | H207: 39789 | I207: 17215 | J207: =(I207-$AB$4) / $AB$8 -> -0.21439273 | K207: =IF(J207<=1, "<=1", IF(J207<=2, "<=2", IF(J207<=3, "<=3", "<=3"))) -> <=1 | N207: =IF(J207>=3, 3, IF(J207>=2, 2, IF(J207>=1, 1, IF(J207>=-2, -2, IF(J207>=-3, -3, "Error"))))) -> -2 | O207: 200 | R207: 22591 | X207: 2008 - 12 | Y207: 17215
A208: Pre-Promo | B208: =_xlfn.CONCAT(C208, " - ", A208) -> 2 - Pre-Promo | C208: 2 | D208: 207 | E208: =_xlfn.CONCAT(G208, " - ", F208) -> 2008 - 12 | F208: =TEXT(H208,"mm") -> 12 | G208: =TEXT(H208,"YYYY") -> 2008 | H208: 39796 | I208: 27257 | J208: =(I208-$AB$4) / $AB$8 -> 1.2536269 | K208: =IF(J208<=1, "<=1", IF(J208<=2, "<=2", IF(J208<=3, "<=3", "<=3"))) -> <=2 | N208: =IF(J208>=3, 3, IF(J208>=2, 2, IF(J208>=1, 1, IF(J208>=-2, -2, IF(J208>=-3, -3, "Error"))))) -> 1 | O208: 201 | R208: 8992 | X208: 2008 - 12 | Y208: 27257
A209: Pre-Promo | B209: =_xlfn.CONCAT(C209, " - ", A209) -> 2 - Pre-Promo | C209: 2 | D209: 208 | E209: =_xlfn.CONCAT(G209, " - ", F209) -> 2008 - 12 | F209: =TEXT(H209,"mm") -> 12 | G209: =TEXT(H209,"YYYY") -> 2008 | H209: 39803 | I209: 11292 | J209: =(I209-$AB$4) / $AB$8 -> -1.0802641 | K209: =IF(J209<=1, "<=1", IF(J209<=2, "<=2", IF(J209<=3, "<=3", "<=3"))) -> <=1 | N209: =IF(J209>=3, 3, IF(J209>=2, 2, IF(J209>=1, 1, IF(J209>=-2, -2, IF(J209>=-3, -3, "Error"))))) -> -2 | O209: 202 | R209: 19104 | X209: 2008 - 12 | Y209: 11292
A210: Pre-Promo | B210: =_xlfn.CONCAT(C210, " - ", A210) -> 2 - Pre-Promo | C210: 2 | D210: 209 | E210: =_xlfn.CONCAT(G210, " - ", F210) -> 2008 - 12 | F210: =TEXT(H210,"mm") -> 12 | G210: =TEXT(H210,"YYYY") -> 2008 | H210: 39810 | I210: 20148 | J210: =(I210-$AB$4) / $AB$8 -> 0.2143766 | K210: =IF(J210<=1, "<=1", IF(J210<=2, "<=2", IF(J210<=3, "<=3", "<=3"))) -> <=1 | N210: =IF(J210>=3, 3, IF(J210>=2, 2, IF(J210>=1, 1, IF(J210>=-2, -2, IF(J210>=-3, -3, "Error"))))) -> -2 | O210: 203 | R210: 21455 | X210: 2008 - 12 | Y210: 20148
... A219: Promo | B219: =_xlfn.CONCAT(C219, " - ", A219) -> 3 - Promo | C219: 3 | D219: 218 | E219: =_xlfn.CONCAT(G219, " - ", F219) -> 2009 - 03 | F219: =TEXT(H219,"mm") -> 03 | G219: =TEXT(H219,"YYYY") -> 2009 | H219: 39873 | I219: 10181 | J219: =(I219-$AB$4) / $AB$8 -> -1.2426789 | K219: =IF(J219<=1, "<=1", IF(J219<=2, "<=2", IF(J219<=3, "<=3", "<=3"))) -> <=1 | N219: =IF(J219>=3, 3, IF(J219>=2, 2, IF(J219>=1, 1, IF(J219>=-2, -2, IF(J219>=-3, -3, "Error"))))) -> -2 | O219: 212 | R219: 26303 | X219: 2009 - 03 | Y219: 10181
A220: Promo | B220: =_xlfn.CONCAT(C220, " - ", A220) -> 3 - Promo | C220: 3 | D220: 219 | E220: =_xlfn.CONCAT(G220, " - ", F220) -> 2009 - 03 | F220: =TEXT(H220,"mm") -> 03 | G220: =TEXT(H220,"YYYY") -> 2009 | H220: 39880 | I220: 9727 | J220: =(I220-$AB$4) / $AB$8 -> -1.3090483 | K220: =IF(J220<=1, "<=1", IF(J220<=2, "<=2", IF(J220<=3, "<=3", "<=3"))) -> <=1 | N220: =IF(J220>=3, 3, IF(J220>=2, 2, IF(J220>=1, 1, IF(J220>=-2, -2, IF(J220>=-3, -3, "Error"))))) -> -2 | O220: 3 - Promo | X220: 2009 - 03 | Y220: 9727
A221: Promo | B221: =_xlfn.CONCAT(C221, " - ", A221) -> 3 - Promo | C221: 3 | D221: 220 | E221: =_xlfn.CONCAT(G221, " - ", F221) -> 2009 - 03 | F221: =TEXT(H221,"mm") -> 03 | G221: =TEXT(H221,"YYYY") -> 2009 | H221: 39887 | I221: 18323 | J221: =(I221-$AB$4) / $AB$8 -> -0.052416454 | K221: =IF(J221<=1, "<=1", IF(J221<=2, "<=2", IF(J221<=3, "<=3", "<=3"))) -> <=1 | N221: =IF(J221>=3, 3, IF(J221>=2, 2, IF(J221>=1, 1, IF(J221>=-2, -2, IF(J221>=-3, -3, "Error"))))) -> -2 | O221: 213 | S221: 22199 | X221: 2009 - 03 | Y221: 18323
A222: Promo | B222: =_xlfn.CONCAT(C222, " - ", A222) -> 3 - Promo | C222: 3 | D222: 221 | E222: =_xlfn.CONCAT(G222, " - ", F222) -> 2009 - 03 | F222: =TEXT(H222,"mm") -> 03 | G222: =TEXT(H222,"YYYY") -> 2009 | H222: 39894 | I222: 17299 | J222: =(I222-$AB$4) / $AB$8 -> -0.20211294 | K222: =IF(J222<=1, "<=1", IF(J222<=2, "<=2", IF(J222<=3, "<=3", "<=3"))) -> <=1 | N222: =IF(J222>=3, 3, IF(J222>=2, 2, IF(J222>=1, 1, IF(J222>=-2, -2, IF(J222>=-3, -3, "Error"))))) -> -2 | O222: 214 | S222: 16535 | X222: 2009 - 03 | Y222: 17299
A223: Promo | B223: =_xlfn.CONCAT(C223, " - ", A223) -> 3 - Promo | C223: 3 | D223: 222 | E223: =_xlfn.CONCAT(G223, " - ", F223) -> 2009 - 03 | F223: =TEXT(H223,"mm") -> 03 | G223: =TEXT(H223,"YYYY") -> 2009 | H223: 39901 | I223: 13862 | J223: =(I223-$AB$4) / $AB$8 -> -0.70456101 | K223: =IF(J223<=1, "<=1", IF(J223<=2, "<=2", IF(J223<=3, "<=3", "<=3"))) -> <=1 | N223: =IF(J223>=3, 3, IF(J223>=2, 2, IF(J223>=1, 1, IF(J223>=-2, -2, IF(J223>=-3, -3, "Error"))))) -> -2 | O223: 215 | S223: 7814 | X223: 2009 - 03 | Y223: 13862
A224: Promo | B224: =_xlfn.CONCAT(C224, " - ", A224) -> 3 - Promo | C224: 3 | D224: 223 | E224: =_xlfn.CONCAT(G224, " - ", F224) -> 2009 - 04 | F224: =TEXT(H224,"mm") -> 04 | G224: =TEXT(H224,"YYYY") -> 2009 | H224: 39908 | I224: 19007 | J224: =(I224-$AB$4) / $AB$8 -> 0.04757612 | K224: =IF(J224<=1, "<=1", IF(J224<=2, "<=2", IF(J224<=3, "<=3", "<=3"))) -> <=1 | N224: =IF(J224>=3, 3, IF(J224>=2, 2, IF(J224>=1, 1, IF(J224>=-2, -2, IF(J224>=-3, -3, "Error"))))) -> -2 | O224: 216 | S224: 28041 | X224: 2009 - 04 | Y224: 19007
A225: Promo | B225: =_xlfn.CONCAT(C225, " - ", A225) -> 3 - Promo | C225: 3 | D225: 224 | E225: =_xlfn.CONCAT(G225, " - ", F225) -> 2009 - 04 | F225: =TEXT(H225,"mm") -> 04 | G225: =TEXT(H225,"YYYY") -> 2009 | H225: 39915 | I225: 23284 | J225: =(I225-$AB$4) / $AB$8 -> 0.67282209 | K225: =IF(J225<=1, "<=1", IF(J225<=2, "<=2", IF(J225<=3, "<=3", "<=3"))) -> <=1 | N225: =IF(J225>=3, 3, IF(J225>=2, 2, IF(J225>=1, 1, IF(J225>=-2, -2, IF(J225>=-3, -3, "Error"))))) -> -2 | O225: 217 | S225: 31496 | X225: 2009 - 04 | Y225: 23284
A226: Promo | B226: =_xlfn.CONCAT(C226, " - ", A226) -> 3 - Promo | C226: 3 | D226: 225 | E226: =_xlfn.CONCAT(G226, " - ", F226) -> 2009 - 04 | F226: =TEXT(H226,"mm") -> 04 | G226: =TEXT(H226,"YYYY") -> 2009 | H226: 39922 | I226: 17374 | J226: =(I226-$AB$4) / $AB$8 -> -0.19114884 | K226: =IF(J226<=1, "<=1", IF(J226<=2, "<=2", IF(J226<=3, "<=3", "<=3"))) -> <=1 | N226: =IF(J226>=3, 3, IF(J226>=2, 2, IF(J226>=1, 1, IF(J226>=-2, -2, IF(J226>=-3, -3, "Error"))))) -> -2 | O226: 218 | S226: 10181 | X226: 2009 - 04 | Y226: 17374
A227: Promo | B227: =_xlfn.CONCAT(C227, " - ", A227) -> 3 - Promo | C227: 3 | D227: 226 | E227: =_xlfn.CONCAT(G227, " - ", F227) -> 2009 - 04 | F227: =TEXT(H227,"mm") -> 04 | G227: =TEXT(H227,"YYYY") -> 2009 | H227: 39929 | I227: 18195 | J227: =(I227-$AB$4) / $AB$8 -> -0.071128515 | K227: =IF(J227<=1, "<=1", IF(J227<=2, "<=2", IF(J227<=3, "<=3", "<=3"))) -> <=1 | N227: =IF(J227>=3, 3, IF(J227>=2, 2, IF(J227>=1, 1, IF(J227>=-2, -2, IF(J227>=-3, -3, "Error"))))) -> -2 | O227: 219 | S227: 9727 | X227: 2009 - 04 | Y227: 18195
A228: Promo | B228: =_xlfn.CONCAT(C228, " - ", A228) -> 3 - Promo | C228: 3 | D228: 227 | E228: =_xlfn.CONCAT(G228, " - ", F228) -> 2009 - 05 | F228: =TEXT(H228,"mm") -> 05 | G228: =TEXT(H228,"YYYY") -> 2009 | H228: 39936 | I228: 9176 | J228: =(I228-$AB$4) / $AB$8 -> -1.3895979 | K228: =IF(J228<=1, "<=1", IF(J228<=2, "<=2", IF(J228<=3, "<=3", "<=3"))) -> <=1 | N228: =IF(J228>=3, 3, IF(J228>=2, 2, IF(J228>=1, 1, IF(J228>=-2, -2, IF(J228>=-3, -3, "Error"))))) -> -2 | O228: 220 | S228: 18323 | X228: 2009 - 05 | Y228: 9176
A229: Promo | B229: =_xlfn.CONCAT(C229, " - ", A229) -> 3 - Promo | C229: 3 | D229: 228 | E229: =_xlfn.CONCAT(G229, " - ", F229) -> 2009 - 05 | F229: =TEXT(H229,"mm") -> 05 | G229: =TEXT(H229,"YYYY") -> 2009 | H229: 39943 | I229: 12881 | J229: =(I229-$AB$4) / $AB$8 -> -0.84797141 | K229: =IF(J229<=1, "<=1", IF(J229<=2, "<=2", IF(J229<=3, "<=3", "<=3"))) -> <=1 | N229: =IF(J229>=3, 3, IF(J229>=2, 2, IF(J229>=1, 1, IF(J229>=-2, -2, IF(J229>=-3, -3, "Error"))))) -> -2 | O229: 221 | S229: 17299 | X229: 2009 - 05 | Y229: 12881
A230: Promo | B230: =_xlfn.CONCAT(C230, " - ", A230) -> 3 - Promo | C230: 3 | D230: 229 | E230: =_xlfn.CONCAT(G230, " - ", F230) -> 2009 - 05 | F230: =TEXT(H230,"mm") -> 05 | G230: =TEXT(H230,"YYYY") -> 2009 | H230: 39950 | I230: 15524 | J230: =(I230-$AB$4) / $AB$8 -> -0.46159659 | K230: =IF(J230<=1, "<=1", IF(J230<=2, "<=2", IF(J230<=3, "<=3", "<=3"))) -> <=1 | N230: =IF(J230>=3, 3, IF(J230>=2, 2, IF(J230>=1, 1, IF(J230>=-2, -2, IF(J230>=-3, -3, "Error"))))) -> -2 | O230: 222 | S230: 13862 | X230: 2009 - 05 | Y230: 15524
A231: Post-Promo | B231: =_xlfn.CONCAT(C231, " - ", A231) -> 4 - Post-Promo | C231: 4 | D231: 230 | E231: =_xlfn.CONCAT(G231, " - ", F231) -> 2009 - 05 | F231: =TEXT(H231,"mm") -> 05 | G231: =TEXT(H231,"YYYY") -> 2009 | H231: 39957 | I231: 15406 | J231: =(I231-$AB$4) / $AB$8 -> -0.47884678 | K231: =IF(J231<=1, "<=1", IF(J231<=2, "<=2", IF(J231<=3, "<=3", "<=3"))) -> <=1 | N231: =IF(J231>=3, 3, IF(J231>=2, 2, IF(J231>=1, 1, IF(J231>=-2, -2, IF(J231>=-3, -3, "Error"))))) -> -2 | O231: 223 | S231: 19007 | X231: 2009 - 05 | Y231: 15406
A232: Post-Promo | B232: =_xlfn.CONCAT(C232, " - ", A232) -> 4 - Post-Promo | C232: 4 | D232: 231 | E232: =_xlfn.CONCAT(G232, " - ", F232) -> 2009 - 05 | F232: =TEXT(H232,"mm") -> 05 | G232: =TEXT(H232,"YYYY") -> 2009 | H232: 39964 | I232: 14536 | J232: =(I232-$AB$4) / $AB$8 -> -0.60603031 | K232: =IF(J232<=1, "<=1", IF(J232<=2, "<=2", IF(J232<=3, "<=3", "<=3"))) -> <=1 | N232: =IF(J232>=3, 3, IF(J232>=2, 2, IF(J232>=1, 1, IF(J232>=-2, -2, IF(J232>=-3, -3, "Error"))))) -> -2 | O232: 224 | S232: 23284 | X232: 2009 - 05 | Y232: 14536
... A237: Post-Promo | B237: =_xlfn.CONCAT(C237, " - ", A237) -> 4 - Post-Promo | C237: 4 | D237: 236 | E237: =_xlfn.CONCAT(G237, " - ", F237) -> 2009 - 07 | F237: =TEXT(H237,"mm") -> 07 | G237: =TEXT(H237,"YYYY") -> 2009 | H237: 39999 | I237: 3826 | J237: =(I237-$AB$4) / $AB$8 -> -2.1717035 | K237: =IF(J237<=1, "<=1", IF(J237<=2, "<=2", IF(J237<=3, "<=3", "<=3"))) -> <=1 | N237: =IF(J237>=3, 3, IF(J237>=2, 2, IF(J237>=1, 1, IF(J237>=-2, -2, IF(J237>=-3, -3, "Error"))))) -> -3 | O237: 229 | S237: 15524 | X237: 2009 - 07 | Y237: 3826
A238: Post-Promo | B238: =_xlfn.CONCAT(C238, " - ", A238) -> 4 - Post-Promo | C238: 4 | D238: 237 | E238: =_xlfn.CONCAT(G238, " - ", F238) -> 2009 - 07 | F238: =TEXT(H238,"mm") -> 07 | G238: =TEXT(H238,"YYYY") -> 2009 | H238: 40006 | I238: 22821 | J238: =(I238-$AB$4) / $AB$8 -> 0.60513705 | K238: =IF(J238<=1, "<=1", IF(J238<=2, "<=2", IF(J238<=3, "<=3", "<=3"))) -> <=1 | N238: =IF(J238>=3, 3, IF(J238>=2, 2, IF(J238>=1, 1, IF(J238>=-2, -2, IF(J238>=-3, -3, "Error"))))) -> -2 | O238: 4 - Post-Promo | X238: 2009 - 07 | Y238: 22821
A239: Post-Promo | B239: =_xlfn.CONCAT(C239, " - ", A239) -> 4 - Post-Promo | C239: 4 | D239: 238 | E239: =_xlfn.CONCAT(G239, " - ", F239) -> 2009 - 07 | F239: =TEXT(H239,"mm") -> 07 | G239: =TEXT(H239,"YYYY") -> 2009 | H239: 40013 | I239: 12758 | J239: =(I239-$AB$4) / $AB$8 -> -0.86595253 | K239: =IF(J239<=1, "<=1", IF(J239<=2, "<=2", IF(J239<=3, "<=3", "<=3"))) -> <=1 | N239: =IF(J239>=3, 3, IF(J239>=2, 2, IF(J239>=1, 1, IF(J239>=-2, -2, IF(J239>=-3, -3, "Error"))))) -> -2 | O239: 230 | T239: 15406 | X239: 2009 - 07 | Y239: 12758
...

Sheet DS_Financials
A1: Phase | B1: PhaseCode | C1: WeekCode | D1: MonthYear | E1: Year | F1: Week (2008-2009) | G1: Revenue | H1: Profit | I1: Lbs. Sold | J1: Inquiries
A2: Shakedown | B2: 1 | C2: 1 | D2: 05 | E2: 2008 | F2: May 25 - May 31 | G2: 480728.01 | H2: 118683.8 | I2: 16585.183 | J2: 13
A3: Shakedown | B3: 1 | C3: 2 | D3: 06 | E3: 2008 | F3: Jun 1 - Jun 7 | G3: 641155.48 | H3: 269604.7 | I3: 18906.38 | J3: 7
A4: Shakedown | B4: 1 | C4: 3 | D4: 06 | E4: 2008 | F4: Jun 8 - Jun 14 | G4: 890076.65 | H4: 275218.1 | I4: 28052.924 | J4: 5
A5: Shakedown | B5: 1 | C5: 4 | D5: 06 | E5: 2008 | F5: Jun 15 - Jun 21 | G5: 552673.98 | H5: 204153 | I5: 19382.312 | J5: 3
A6: Shakedown | B6: 1 | C6: 5 | D6: 06 | E6: 2008 | F6: Jun 22 - Jun 28 | G6: 750776.98 | H6: 256091.4 | I6: 24274.249 | J6: 3
A7: Shakedown | B7: 1 | C7: 6 | D7: 06 | E7: 2008 | F7: Jun 29 - Jul 5 | G7: 553054.69 | H7: 178134.5 | I7: 15308.721 | J7: 5
A8: Shakedown | B8: 1 | C8: 7 | D8: 07 | E8: 2008 | F8: Jul 6 - Jul 12 | G8: 274567.61 | H8: 62580.4 | I8: 8633.059 | J8: 16
A9: Shakedown | B9: 1 | C9: 8 | D9: 07 | E9: 2008 | F9: Jul 13 - Jul 19 | G9: 619284.64 | H9: 248458.4 | I9: 17216.342 | J9: 7
A10: Shakedown | B10: 1 | C10: 9 | D10: 07 | E10: 2008 | F10: Jul 20 - Jul 26 | G10: 674484.59 | H10: 238498.1 | I10: 17308.567 | J10: 6
A11: Shakedown | B11: 1 | C11: 10 | D11: 07 | E11: 2008 | F11: Jul 27 - Aug 2 | G11: 762559.12 | H11: 230237.8 | I11: 24571.171 | J11: 6
A12: Shakedown | B12: 1 | C12: 11 | D12: 08 | E12: 2008 | F12: Aug 3 - Aug 9 | G12: 479084.17 | H12: 156660.1 | I12: 14389.769 | J12: 4
A13: Shakedown | B13: 1 | C13: 12 | D13: 08 | E13: 2008 | F13: Aug 10 - Aug 16 | G13: 528270.72 | H13: 186775.6 | I13: 17230.826 | J13: 9
... A67: Post-Promo | B67: 4 | C67: 66 | D67: 08 | E67: 2009 | F67: Aug 23 - Aug 29 | G67: 615950.17 | H67: 206441.2 | I67: 23761.614 | J67: 8
G70: =MAX(I2:I67) -> 31968.976

Sheet Columbia CaseWorks
A1: Web Analytics at Quality Alloys, Inc.
A2: Author: | B2: Rob Weitz and David Rosenthal
A3: Columbia CaseWorks ID: 110203
F5: Copyright Information
F6: © 2010 by The Trustees of Columbia University in the City of New York. All rights reserved.
F7: Neither this spreadsheet nor the associated case can be used or reproduced
A8: Abstract: | F8: without explicit permission from Columbia CaseWorks.
A9: This spreadsheet accompanies the Web Analytics at Quality Alloys, Inc case. | F9: To obtain permission, please visit:
F10: www.gsb.columbia.edu/CaseWorks
F11: or e-mail:
F12: ColumbiaCaseWorks@gsb.columbia.edu

Sheet Weekly Visits
A1: Quality Alloys
A2: Weekly Web Analytics | E2: Initial "Shakedown" Period | H2: Pre and Post Promotion Periods
A3: May 25, 2008 - August 29, 2009 | E3: Promotion Period | H3: are unshaded.
J4: Bounce Rate is defined as the percentage of visitors who leave a webpage without taking any action, such as clicking on a link, filling out a form, or making a purchase. Essentially, it measures how many visitors “bounce” away after viewing only one page without engaging further with the site1. A high bounce rate can indicate issues with content, user experience, page layout, or copywriting. For example, if a visitor lands on a page and immediately leaves without interacting further, that contributes to the bounce rate. In Google Analytics, bounce rate is calculated as:
A5: Week (2008-2009) | B5: Visits | C5: Unique Visits | D5: Pageviews | E5: Pages/Visit | F5: Avg. Time on Site (secs.) | G5: Bounce Rate | H5: % New Visits
A6: May 25 - May 31 | B6: 1632 | C6: 1509 | D6: 3328 | E6: 2.04 | F6: 71 | G6: 0.7267 | H6: 0.8854 | J6: Bounce Rate=Total Number of SessionsSingle-Page Sessions​×100
A7: Jun 1 - Jun 7 | B7: 1580 | C7: 1450 | D7: 3097 | E7: 1.96 | F7: 56 | G7: 0.7551 | H7: 0.8734
A8: Jun 8 - Jun 14 | B8: 1441 | C8: 1306 | D8: 3202 | E8: 2.22 | F8: 79 | G8: 0.7398 | H8: 0.8432 | J8: The average bounce rate varies by industry and traffic sources. While an average range of 41% to 51% is common, specific benchmarks depend on your website type and where your traffic comes from. For instance, e-commerce sites tend to have lower bounce rates (20% to 45%), while blogs may have higher rates (up to 90%)1. Keep in mind that context matters, and comparing your site’s bounce rate to similar sites in your category provides a more meaningful assessmen
A9: Jun 15 - Jun 21 | B9: 1452 | C9: 1301 | D9: 3170 | E9: 2.18 | F9: 81 | G9: 0.7362 | H9: 0.8437
A10: Jun 22 - Jun 28 | B10: 1339 | C10: 1255 | D10: 2366 | E10: 1.77 | F10: 50 | G10: 0.764 | H10: 0.8925
A11: Jun 29 - Jul 5 | B11: 892 | C11: 841 | D11: 1865 | E11: 2.09 | F11: 71 | G11: 0.7365 | H11: 0.8756
A12: Jul 6 - Jul 12 | B12: 797 | C12: 731 | D12: 1885 | E12: 2.37 | F12: 80 | G12: 0.6148 | H12: 0.857
A13: Jul 13 - Jul 19 | B13: 744 | C13: 706 | D13: 1916 | E13: 2.58 | F13: 96 | G13: 0.5927 | H13: 0.8884
A14: Jul 20 - Jul 26 | B14: 1044 | C14: 976 | D14: 2670 | E14: 2.56 | F14: 82 | G14: 0.6034 | H14: 0.8669
A15: Jul 27 - Aug 2 | B15: 906 | C15: 850 | D15: 2189 | E15: 2.42 | F15: 78 | G15: 0.6336 | H15: 0.8742
A16: Aug 3 - Aug 9 | B16: 849 | C16: 791 | D16: 1947 | E16: 2.29 | F16: 91 | G16: 0.6443 | H16: 0.8704
A17: Aug 10 - Aug 16 | B17: 737 | C17: 685 | D17: 1746 | E17: 2.37 | F17: 98 | G17: 0.6282 | H17: 0.8725
A18: Aug 17 - Aug 23 | B18: 734 | C18: 668 | D18: 1946 | E18: 2.65 | F18: 100 | G18: 0.624 | H18: 0.8433
A19: Aug 24 - Aug 30 | B19: 626 | C19: 594 | D19: 1540 | E19: 2.46 | F19: 91 | G19: 0.6198 | H19: 0.8658
A20: Aug 31 - Sep 6 | B20: 577 | C20: 537 | D20: 1489 | E20: 2.58 | F20: 83 | G20: 0.6205 | H20: 0.8666
... A71: Aug 23 - Aug 29 | B71: 772 | C71: 709 | D71: 1767 | E71: 2.29 | F71: 72 | G71: 0.6192 | H71: 0.8523

Sheet Financials
A1: Quality Alloys
A2: Weekly Financial Data | C2: Initial "Shakedown" Period | F2: Pre and Post Promotion Periods
A3: May 25, 2008 - August 29, 2009 | C3: Promotion Period | F3: are unshaded.
A5: Week (2008-2009) | B5: Revenue | C5: Profit | D5: Lbs. Sold | E5: Inquiries
A6: May 25 - May 31 | B6: 480728.01 | C6: 118683.8 | D6: 16585.183 | E6: 13
A7: Jun 1 - Jun 7 | B7: 641155.48 | C7: 269604.7 | D7: 18906.38 | E7: 7
A8: Jun 8 - Jun 14 | B8: 890076.65 | C8: 275218.1 | D8: 28052.924 | E8: 5
A9: Jun 15 - Jun 21 | B9: 552673.98 | C9: 204153 | D9: 19382.312 | E9: 3
A10: Jun 22 - Jun 28 | B10: 750776.98 | C10: 256091.4 | D10: 24274.249 | E10: 3
A11: Jun 29 - Jul 5 | B11: 553054.69 | C11: 178134.5 | D11: 15308.721 | E11: 5
A12: Jul 6 - Jul 12 | B12: 274567.61 | C12: 62580.4 | D12: 8633.059 | E12: 16
A13: Jul 13 - Jul 19 | B13: 619284.64 | C13: 248458.4 | D13: 17216.342 | E13: 7
A14: Jul 20 - Jul 26 | B14: 674484.59 | C14: 238498.1 | D14: 17308.567 | E14: 6
A15: Jul 27 - Aug 2 | B15: 762559.12 | C15: 230237.8 | D15: 24571.171 | E15: 6
A16: Aug 3 - Aug 9 | B16: 479084.17 | C16: 156660.1 | D16: 14389.769 | E16: 4
A17: Aug 10 - Aug 16 | B17: 528270.72 | C17: 186775.6 | D17: 17230.826 | E17: 9
... A71: Aug 23 - Aug 29 | B71: 615950.17 | C71: 206441.2 | D71: 23761.614 | E71: 8
D74: =MAX(D6:D71) -> 31968.976

Sheet Lbs. Sold
A1: Quality Alloys
A2: Lbs. of Material Sold Per Week
A3: Week of Jan. 3, 2005 through week of July 19, 2010.
A5: Week | B5: Lbs. Sold
A6: 38354 | B6: 23662
A7: 38361 | B7: 12699
A8: 38368 | B8: 23095
A9: 38375 | B9: 27944
A10: 38382 | B10: 20516
A11: 38389 | B11: 25546
A12: 38396 | B12: 20023
A13: 38403 | B13: 35247
A14: 38410 | B14: 23615
A15: 38417 | B15: 16655
A16: 38424 | B16: 14748
A17: 38431 | B17: 18159
... A295: 40377 | B295: 14307

Sheet Daily Visits
A1: Day | B1: Visits | C1: z-score | D1: Count | G1: Count | H1: Visits | L1: Row Labels | M1: Count of Count
A2: Sunday, January 11, 2009 | B2: 37 | C2: =(B2-$I$3)/$I$7 -> -1.1539588 | D2: =IF(C2<=1, "<=1", IF(C2<=2, "<=2", IF(C2<=3, "<=3", "<=3"))) -> <=1 | E2: =COUNTA(D2:D416) -> 415 | F2: =1-(E2/462) -> 0.1017316 | G2: =IF(C2>=3, 3, IF(C2>=2, 2, IF(C2>=1, 1, IF(C2>=-2, -2, IF(C2>=-3, -3, "Error"))))) -> -2 | L2: -2 | M2: 415
A3: Sunday, November 2, 2008 | B3: 39 | C3: =(B3-$I$3)/$I$7 -> -1.1335859 | D3: =IF(C3<=1, "<=1", IF(C3<=2, "<=2", IF(C3<=3, "<=3", "<=3"))) -> <=1 | G3: =IF(C3>=3, 3, IF(C3>=2, 2, IF(C3>=1, 1, IF(C3>=-2, -2, IF(C3>=-3, -3, "Error"))))) -> -2 | H3: Mean | I3: 150.28355 | L3: 1 | M3: 24
A4: Friday, December 26, 2008 | B4: 41 | C4: =(B4-$I$3)/$I$7 -> -1.113213 | D4: =IF(C4<=1, "<=1", IF(C4<=2, "<=2", IF(C4<=3, "<=3", "<=3"))) -> <=1 | G4: =IF(C4>=3, 3, IF(C4>=2, 2, IF(C4>=1, 1, IF(C4>=-2, -2, IF(C4>=-3, -3, "Error"))))) -> -2 | H4: Standard Error | I4: 4.5672581 | L4: 2 | M4: 9
A5: Saturday, December 13, 2008 | B5: 44 | C5: =(B5-$I$3)/$I$7 -> -1.0826536 | D5: =IF(C5<=1, "<=1", IF(C5<=2, "<=2", IF(C5<=3, "<=3", "<=3"))) -> <=1 | G5: =IF(C5>=3, 3, IF(C5>=2, 2, IF(C5>=1, 1, IF(C5>=-2, -2, IF(C5>=-3, -3, "Error"))))) -> -2 | H5: Median | I5: 122 | L5: 3 | M5: 14
A6: Saturday, October 18, 2008 | B6: 46 | C6: =(B6-$I$3)/$I$7 -> -1.0622806 | D6: =IF(C6<=1, "<=1", IF(C6<=2, "<=2", IF(C6<=3, "<=3", "<=3"))) -> <=1 | G6: =IF(C6>=3, 3, IF(C6>=2, 2, IF(C6>=1, 1, IF(C6>=-2, -2, IF(C6>=-3, -3, "Error"))))) -> -2 | H6: Mode | I6: 91 | L6: (blank)
A7: Saturday, December 27, 2008 | B7: 46 | C7: =(B7-$I$3)/$I$7 -> -1.0622806 | D7: =IF(C7<=1, "<=1", IF(C7<=2, "<=2", IF(C7<=3, "<=3", "<=3"))) -> <=1 | G7: =IF(C7>=3, 3, IF(C7>=2, 2, IF(C7>=1, 1, IF(C7>=-2, -2, IF(C7>=-3, -3, "Error"))))) -> -2 | H7: Standard Deviation | I7: 98.169492 | L7: Grand Total | M7: 462
A8: Sunday, October 26, 2008 | B8: 47 | C8: =(B8-$I$3)/$I$7 -> -1.0520942 | D8: =IF(C8<=1, "<=1", IF(C8<=2, "<=2", IF(C8<=3, "<=3", "<=3"))) -> <=1 | G8: =IF(C8>=3, 3, IF(C8>=2, 2, IF(C8>=1, 1, IF(C8>=-2, -2, IF(C8>=-3, -3, "Error"))))) -> -2 | H8: Sample Variance | I8: 9637.2491
A9: Saturday, November 1, 2008 | B9: 47 | C9: =(B9-$I$3)/$I$7 -> -1.0520942 | D9: =IF(C9<=1, "<=1", IF(C9<=2, "<=2", IF(C9<=3, "<=3", "<=3"))) -> <=1 | G9: =IF(C9>=3, 3, IF(C9>=2, 2, IF(C9>=1, 1, IF(C9>=-2, -2, IF(C9>=-3, -3, "Error"))))) -> -2 | H9: Kurtosis | I9: 5.8619896
A10: Saturday, November 15, 2008 | B10: 47 | C10: =(B10-$I$3)/$I$7 -> -1.0520942 | D10: =IF(C10<=1, "<=1", IF(C10<=2, "<=2", IF(C10<=3, "<=3", "<=3"))) -> <=1 | G10: =IF(C10>=3, 3, IF(C10>=2, 2, IF(C10>=1, 1, IF(C10>=-2, -2, IF(C10>=-3, -3, "Error"))))) -> -2 | H10: Skewness | I10: 2.1669722
A11: Sunday, November 9, 2008 | B11: 48 | C11: =(B11-$I$3)/$I$7 -> -1.0419077 | D11: =IF(C11<=1, "<=1", IF(C11<=2, "<=2", IF(C11<=3, "<=3", "<=3"))) -> <=1 | G11: =IF(C11>=3, 3, IF(C11>=2, 2, IF(C11>=1, 1, IF(C11>=-2, -2, IF(C11>=-3, -3, "Error"))))) -> -2 | H11: Range | I11: 627
A12: Saturday, September 13, 2008 | B12: 49 | C12: =(B12-$I$3)/$I$7 -> -1.0317212 | D12: =IF(C12<=1, "<=1", IF(C12<=2, "<=2", IF(C12<=3, "<=3", "<=3"))) -> <=1 | G12: =IF(C12>=3, 3, IF(C12>=2, 2, IF(C12>=1, 1, IF(C12>=-2, -2, IF(C12>=-3, -3, "Error"))))) -> -2 | H12: Minimum | I12: 37
A13: Sunday, December 21, 2008 | B13: 49 | C13: =(B13-$I$3)/$I$7 -> -1.0317212 | D13: =IF(C13<=1, "<=1", IF(C13<=2, "<=2", IF(C13<=3, "<=3", "<=3"))) -> <=1 | G13: =IF(C13>=3, 3, IF(C13>=2, 2, IF(C13>=1, 1, IF(C13>=-2, -2, IF(C13>=-3, -3, "Error"))))) -> -2 | H13: Maximum | I13: 664
A14: Friday, January 2, 2009 | B14: 49 | C14: =(B14-$I$3)/$I$7 -> -1.0317212 | D14: =IF(C14<=1, "<=1", IF(C14<=2, "<=2", IF(C14<=3, "<=3", "<=3"))) -> <=1 | G14: =IF(C14>=3, 3, IF(C14>=2, 2, IF(C14>=1, 1, IF(C14>=-2, -2, IF(C14>=-3, -3, "Error"))))) -> -2 | H14: Sum | I14: 69431
A15: Saturday, September 20, 2008 | B15: 50 | C15: =(B15-$I$3)/$I$7 -> -1.0215348 | D15: =IF(C15<=1, "<=1", IF(C15<=2, "<=2", IF(C15<=3, "<=3", "<=3"))) -> <=1 | G15: =IF(C15>=3, 3, IF(C15>=2, 2, IF(C15>=1, 1, IF(C15>=-2, -2, IF(C15>=-3, -3, "Error"))))) -> -2 | H15: Count | I15: 462
A16: Sunday, January 4, 2009 | B16: 50 | C16: =(B16-$I$3)/$I$7 -> -1.0215348 | D16: =IF(C16<=1, "<=1", IF(C16<=2, "<=2", IF(C16<=3, "<=3", "<=3"))) -> <=1 | G16: =IF(C16>=3, 3, IF(C16>=2, 2, IF(C16>=1, 1, IF(C16>=-2, -2, IF(C16>=-3, -3, "Error"))))) -> -2 | H16: Confidence Level(95%) | I16: 8.9752246
A17: Sunday, October 5, 2008 | B17: 51 | C17: =(B17-$I$3)/$I$7 -> -1.0113483 | D17: =IF(C17<=1, "<=1", IF(C17<=2, "<=2", IF(C17<=3, "<=3", "<=3"))) -> <=1 | G17: =IF(C17>=3, 3, IF(C17>=2, 2, IF(C17>=1, 1, IF(C17>=-2, -2, IF(C17>=-3, -3, "Error"))))) -> -2
A18: Sunday, October 12, 2008 | B18: 51 | C18: =(B18-$I$3)/$I$7 -> -1.0113483 | D18: =IF(C18<=1, "<=1", IF(C18<=2, "<=2", IF(C18<=3, "<=3", "<=3"))) -> <=1 | G18: =IF(C18>=3, 3, IF(C18>=2, 2, IF(C18>=1, 1, IF(C18>=-2, -2, IF(C18>=-3, -3, "Error"))))) -> -2
A19: Saturday, November 8, 2008 | B19: 51 | C19: =(B19-$I$3)/$I$7 -> -1.0113483 | D19: =IF(C19<=1, "<=1", IF(C19<=2, "<=2", IF(C19<=3, "<=3", "<=3"))) -> <=1 | G19: =IF(C19>=3, 3, IF(C19>=2, 2, IF(C19>=1, 1, IF(C19>=-2, -2, IF(C19>=-3, -3, "Error"))))) -> -2
A20: Saturday, November 22, 2008 | B20: 51 | C20: =(B20-$I$3)/$I$7 -> -1.0113483 | D20: =IF(C20<=1, "<=1", IF(C20<=2, "<=2", IF(C20<=3, "<=3", "<=3"))) -> <=1 | G20: =IF(C20>=3, 3, IF(C20>=2, 2, IF(C20>=1, 1, IF(C20>=-2, -2, IF(C20>=-3, -3, "Error"))))) -> -2
A21: Sunday, September 21, 2008 | B21: 52 | C21: =(B21-$I$3)/$I$7 -> -1.0011618 | D21: =IF(C21<=1, "<=1", IF(C21<=2, "<=2", IF(C21<=3, "<=3", "<=3"))) -> <=1 | G21: =IF(C21>=3, 3, IF(C21>=2, 2, IF(C21>=1, 1, IF(C21>=-2, -2, IF(C21>=-3, -3, "Error"))))) -> -2
A22: Sunday, November 16, 2008 | B22: 52 | C22: =(B22-$I$3)/$I$7 -> -1.0011618 | D22: =IF(C22<=1, "<=1", IF(C22<=2, "<=2", IF(C22<=3, "<=3", "<=3"))) -> <=1 | G22: =IF(C22>=3, 3, IF(C22>=2, 2, IF(C22>=1, 1, IF(C22>=-2, -2, IF(C22>=-3, -3, "Error"))))) -> -2
A23: Sunday, December 7, 2008 | B23: 52 | C23: =(B23-$I$3)/$I$7 -> -1.0011618 | D23: =IF(C23<=1, "<=1", IF(C23<=2, "<=2", IF(C23<=3, "<=3", "<=3"))) -> <=1 | G23: =IF(C23>=3, 3, IF(C23>=2, 2, IF(C23>=1, 1, IF(C23>=-2, -2, IF(C23>=-3, -3, "Error"))))) -> -2
A24: Saturday, January 10, 2009 | B24: 52 | C24: =(B24-$I$3)/$I$7 -> -1.0011618 | D24: =IF(C24<=1, "<=1", IF(C24<=2, "<=2", IF(C24<=3, "<=3", "<=3"))) -> <=1 | G24: =IF(C24>=3, 3, IF(C24>=2, 2, IF(C24>=1, 1, IF(C24>=-2, -2, IF(C24>=-3, -3, "Error"))))) -> -2
A25: Saturday, October 11, 2008 | B25: 53 | C25: =(B25-$I$3)/$I$7 -> -0.99097538 | D25: =IF(C25<=1, "<=1", IF(C25<=2, "<=2", IF(C25<=3, "<=3", "<=3"))) -> <=1 | G25: =IF(C25>=3, 3, IF(C25>=2, 2, IF(C25>=1, 1, IF(C25>=-2, -2, IF(C25>=-3, -3, "Error"))))) -> -2
A26: Saturday, October 25, 2008 | B26: 53 | C26: =(B26-$I$3)/$I$7 -> -0.99097538 | D26: =IF(C26<=1, "<=1", IF(C26<=2, "<=2", IF(C26<=3, "<=3", "<=3"))) -> <=1 | G26: =IF(C26>=3, 3, IF(C26>=2, 2, IF(C26>=1, 1, IF(C26>=-2, -2, IF(C26>=-3, -3, "Error"))))) -> -2
A27: Saturday, November 29, 2008 | B27: 53 | C27: =(B27-$I$3)/$I$7 -> -0.99097538 | D27: =IF(C27<=1, "<=1", IF(C27<=2, "<=2", IF(C27<=3, "<=3", "<=3"))) -> <=1 | G27: =IF(C27>=3, 3, IF(C27>=2, 2, IF(C27>=1, 1, IF(C27>=-2, -2, IF(C27>=-3, -3, "Error"))))) -> -2
A28: Saturday, December 6, 2008 | B28: 53 | C28: =(B28-$I$3)/$I$7 -> -0.99097538 | D28: =IF(C28<=1, "<=1", IF(C28<=2, "<=2", IF(C28<=3, "<=3", "<=3"))) -> <=1 | G28: =IF(C28>=3, 3, IF(C28>=2, 2, IF(C28>=1, 1, IF(C28>=-2, -2, IF(C28>=-3, -3, "Error"))))) -> -2
... A416: Monday, May 4, 2009 | B416: 248 | C416: =(B416-$I$3)/$I$7 -> 0.99538511 | D416: =IF(C416<=1, "<=1", IF(C416<=2, "<=2", IF(C416<=3, "<=3", "<=3"))) -> <=1 | G416: =IF(C416>=3, 3, IF(C416>=2, 2, IF(C416>=1, 1, IF(C416>=-2, -2, IF(C416>=-3, -3, "Error"))))) -> -2
A417: Monday, March 30, 2009 | B417: 251 | C417: =(B417-$I$3)/$I$7 -> 1.0259445 | D417: =IF(C417<=1, "<=1", IF(C417<=2, "<=2", IF(C417<=3, "<=3", "<=3"))) -> <=2 | E417: =COUNTA(D417:D440) -> 24 | F417: =1-(E417/462) -> 0.94805195 | G417: =IF(C417>=3, 3, IF(C417>=2, 2, IF(C417>=1, 1, IF(C417>=-2, -2, IF(C417>=-3, -3, "Error"))))) -> 1
A418: Wednesday, June 4, 2008 | B418: 252 | C418: =(B418-$I$3)/$I$7 -> 1.036131 | D418: =IF(C418<=1, "<=1", IF(C418<=2, "<=2", IF(C418<=3, "<=3", "<=3"))) -> <=2 | G418: =IF(C418>=3, 3, IF(C418>=2, 2, IF(C418>=1, 1, IF(C418>=-2, -2, IF(C418>=-3, -3, "Error"))))) -> 1
A419: Thursday, April 2, 2009 | B419: 253 | C419: =(B419-$I$3)/$I$7 -> 1.0463174 | D419: =IF(C419<=1, "<=1", IF(C419<=2, "<=2", IF(C419<=3, "<=3", "<=3"))) -> <=2 | G419: =IF(C419>=3, 3, IF(C419>=2, 2, IF(C419>=1, 1, IF(C419>=-2, -2, IF(C419>=-3, -3, "Error"))))) -> 1
A420: Sunday, February 8, 2009 | B420: 262 | C420: =(B420-$I$3)/$I$7 -> 1.1379956 | D420: =IF(C420<=1, "<=1", IF(C420<=2, "<=2", IF(C420<=3, "<=3", "<=3"))) -> <=2 | G420: =IF(C420>=3, 3, IF(C420>=2, 2, IF(C420>=1, 1, IF(C420>=-2, -2, IF(C420>=-3, -3, "Error"))))) -> 1
A421: Thursday, May 29, 2008 | B421: 263 | C421: =(B421-$I$3)/$I$7 -> 1.1481821 | D421: =IF(C421<=1, "<=1", IF(C421<=2, "<=2", IF(C421<=3, "<=3", "<=3"))) -> <=2 | G421: =IF(C421>=3, 3, IF(C421>=2, 2, IF(C421>=1, 1, IF(C421>=-2, -2, IF(C421>=-3, -3, "Error"))))) -> 1
A422: Tuesday, March 31, 2009 | B422: 267 | C422: =(B422-$I$3)/$I$7 -> 1.1889279 | D422: =IF(C422<=1, "<=1", IF(C422<=2, "<=2", IF(C422<=3, "<=3", "<=3"))) -> <=2 | G422: =IF(C422>=3, 3, IF(C422>=2, 2, IF(C422>=1, 1, IF(C422>=-2, -2, IF(C422>=-3, -3, "Error"))))) -> 1
A423: Thursday, April 30, 2009 | B423: 271 | C423: =(B423-$I$3)/$I$7 -> 1.2296738 | D423: =IF(C423<=1, "<=1", IF(C423<=2, "<=2", IF(C423<=3, "<=3", "<=3"))) -> <=2 | G423: =IF(C423>=3, 3, IF(C423>=2, 2, IF(C423>=1, 1, IF(C423>=-2, -2, IF(C423>=-3, -3, "Error"))))) -> 1
A424: Tuesday, February 17, 2009 | B424: 276 | C424: =(B424-$I$3)/$I$7 -> 1.2806061 | D424: =IF(C424<=1, "<=1", IF(C424<=2, "<=2", IF(C424<=3, "<=3", "<=3"))) -> <=2 | G424: =IF(C424>=3, 3, IF(C424>=2, 2, IF(C424>=1, 1, IF(C424>=-2, -2, IF(C424>=-3, -3, "Error"))))) -> 1
A425: Monday, February 16, 2009 | B425: 277 | C425: =(B425-$I$3)/$I$7 -> 1.2907926 | D425: =IF(C425<=1, "<=1", IF(C425<=2, "<=2", IF(C425<=3, "<=3", "<=3"))) -> <=2 | G425: =IF(C425>=3, 3, IF(C425>=2, 2, IF(C425>=1, 1, IF(C425>=-2, -2, IF(C425>=-3, -3, "Error"))))) -> 1
A426: Wednesday, May 28, 2008 | B426: 282 | C426: =(B426-$I$3)/$I$7 -> 1.3417249 | D426: =IF(C426<=1, "<=1", IF(C426<=2, "<=2", IF(C426<=3, "<=3", "<=3"))) -> <=2 | G426: =IF(C426>=3, 3, IF(C426>=2, 2, IF(C426>=1, 1, IF(C426>=-2, -2, IF(C426>=-3, -3, "Error"))))) -> 1
A427: Friday, May 1, 2009 | B427: 283 | C427: =(B427-$I$3)/$I$7 -> 1.3519113 | D427: =IF(C427<=1, "<=1", IF(C427<=2, "<=2", IF(C427<=3, "<=3", "<=3"))) -> <=2 | G427: =IF(C427>=3, 3, IF(C427>=2, 2, IF(C427>=1, 1, IF(C427>=-2, -2, IF(C427>=-3, -3, "Error"))))) -> 1
A428: Friday, April 3, 2009 | B428: 285 | C428: =(B428-$I$3)/$I$7 -> 1.3722843 | D428: =IF(C428<=1, "<=1", IF(C428<=2, "<=2", IF(C428<=3, "<=3", "<=3"))) -> <=2 | G428: =IF(C428>=3, 3, IF(C428>=2, 2, IF(C428>=1, 1, IF(C428>=-2, -2, IF(C428>=-3, -3, "Error"))))) -> 1
A429: Wednesday, February 18, 2009 | B429: 288 | C429: =(B429-$I$3)/$I$7 -> 1.4028437 | D429: =IF(C429<=1, "<=1", IF(C429<=2, "<=2", IF(C429<=3, "<=3", "<=3"))) -> <=2 | G429: =IF(C429>=3, 3, IF(C429>=2, 2, IF(C429>=1, 1, IF(C429>=-2, -2, IF(C429>=-3, -3, "Error"))))) -> 1
... A440: Saturday, April 4, 2009 | B440: 334 | C440: =(B440-$I$3)/$I$7 -> 1.871421 | D440: =IF(C440<=1, "<=1", IF(C440<=2, "<=2", IF(C440<=3, "<=3", "<=3"))) -> <=2 | G440: =IF(C440>=3, 3, IF(C440>=2, 2, IF(C440>=1, 1, IF(C440>=-2, -2, IF(C440>=-3, -3, "Error"))))) -> 1
A441: Thursday, February 26, 2009 | B441: 357 | C441: =(B441-$I$3)/$I$7 -> 2.1057097 | D441: =IF(C441<=1, "<=1", IF(C441<=2, "<=2", IF(C441<=3, "<=3", "<=3"))) -> <=3 | E441: =COUNTA(D441:D463) -> 23 | F441: =1-(E441/462) -> 0.95021645 | G441: =IF(C441>=3, 3, IF(C441>=2, 2, IF(C441>=1, 1, IF(C441>=-2, -2, IF(C441>=-3, -3, "Error"))))) -> 2
A442: Friday, February 13, 2009 | B442: 361 | C442: =(B442-$I$3)/$I$7 -> 2.1464555 | D442: =IF(C442<=1, "<=1", IF(C442<=2, "<=2", IF(C442<=3, "<=3", "<=3"))) -> <=3 | G442: =IF(C442>=3, 3, IF(C442>=2, 2, IF(C442>=1, 1, IF(C442>=-2, -2, IF(C442>=-3, -3, "Error"))))) -> 2
A443: Saturday, February 28, 2009 | B443: 369 | C443: =(B443-$I$3)/$I$7 -> 2.2279473 | D443: =IF(C443<=1, "<=1", IF(C443<=2, "<=2", IF(C443<=3, "<=3", "<=3"))) -> <=3 | G443: =IF(C443>=3, 3, IF(C443>=2, 2, IF(C443>=1, 1, IF(C443>=-2, -2, IF(C443>=-3, -3, "Error"))))) -> 2
A444: Friday, February 27, 2009 | B444: 375 | C444: =(B444-$I$3)/$I$7 -> 2.289066 | D444: =IF(C444<=1, "<=1", IF(C444<=2, "<=2", IF(C444<=3, "<=3", "<=3"))) -> <=3 | G444: =IF(C444>=3, 3, IF(C444>=2, 2, IF(C444>=1, 1, IF(C444>=-2, -2, IF(C444>=-3, -3, "Error"))))) -> 2
A445: Sunday, February 15, 2009 | B445: 392 | C445: =(B445-$I$3)/$I$7 -> 2.4622359 | D445: =IF(C445<=1, "<=1", IF(C445<=2, "<=2", IF(C445<=3, "<=3", "<=3"))) -> <=3 | G445: =IF(C445>=3, 3, IF(C445>=2, 2, IF(C445>=1, 1, IF(C445>=-2, -2, IF(C445>=-3, -3, "Error"))))) -> 2
A446: Saturday, February 14, 2009 | B446: 407 | C446: =(B446-$I$3)/$I$7 -> 2.6150329 | D446: =IF(C446<=1, "<=1", IF(C446<=2, "<=2", IF(C446<=3, "<=3", "<=3"))) -> <=3 | G446: =IF(C446>=3, 3, IF(C446>=2, 2, IF(C446>=1, 1, IF(C446>=-2, -2, IF(C446>=-3, -3, "Error"))))) -> 2
A447: Friday, March 20, 2009 | B447: 419 | C447: =(B447-$I$3)/$I$7 -> 2.7372705 | D447: =IF(C447<=1, "<=1", IF(C447<=2, "<=2", IF(C447<=3, "<=3", "<=3"))) -> <=3 | G447: =IF(C447>=3, 3, IF(C447>=2, 2, IF(C447>=1, 1, IF(C447>=-2, -2, IF(C447>=-3, -3, "Error"))))) -> 2
A448: Tuesday, February 24, 2009 | B448: 428 | C448: =(B448-$I$3)/$I$7 -> 2.8289486 | D448: =IF(C448<=1, "<=1", IF(C448<=2, "<=2", IF(C448<=3, "<=3", "<=3"))) -> <=3 | G448: =IF(C448>=3, 3, IF(C448>=2, 2, IF(C448>=1, 1, IF(C448>=-2, -2, IF(C448>=-3, -3, "Error"))))) -> 2
A449: Tuesday, March 17, 2009 | B449: 436 | C449: =(B449-$I$3)/$I$7 -> 2.9104403 | D449: =IF(C449<=1, "<=1", IF(C449<=2, "<=2", IF(C449<=3, "<=3", "<=3"))) -> <=3 | G449: =IF(C449>=3, 3, IF(C449>=2, 2, IF(C449>=1, 1, IF(C449>=-2, -2, IF(C449>=-3, -3, "Error"))))) -> 2
A450: Tuesday, March 3, 2009 | B450: 448 | C450: =(B450-$I$3)/$I$7 -> 3.0326779 | D450: =IF(C450<=1, "<=1", IF(C450<=2, "<=2", IF(C450<=3, "<=3", "<=3"))) -> <=3 | G450: =IF(C450>=3, 3, IF(C450>=2, 2, IF(C450>=1, 1, IF(C450>=-2, -2, IF(C450>=-3, -3, "Error"))))) -> 3
A451: Saturday, March 14, 2009 | B451: 470 | C451: =(B451-$I$3)/$I$7 -> 3.2567801 | D451: =IF(C451<=1, "<=1", IF(C451<=2, "<=2", IF(C451<=3, "<=3", "<=3"))) -> <=3 | G451: =IF(C451>=3, 3, IF(C451>=2, 2, IF(C451>=1, 1, IF(C451>=-2, -2, IF(C451>=-3, -3, "Error"))))) -> 3
A452: Sunday, March 15, 2009 | B452: 476 | C452: =(B452-$I$3)/$I$7 -> 3.3178989 | D452: =IF(C452<=1, "<=1", IF(C452<=2, "<=2", IF(C452<=3, "<=3", "<=3"))) -> <=3 | G452: =IF(C452>=3, 3, IF(C452>=2, 2, IF(C452>=1, 1, IF(C452>=-2, -2, IF(C452>=-3, -3, "Error"))))) -> 3
A453: Tuesday, March 10, 2009 | B453: 478 | C453: =(B453-$I$3)/$I$7 -> 3.3382718 | D453: =IF(C453<=1, "<=1", IF(C453<=2, "<=2", IF(C453<=3, "<=3", "<=3"))) -> <=3 | G453: =IF(C453>=3, 3, IF(C453>=2, 2, IF(C453>=1, 1, IF(C453>=-2, -2, IF(C453>=-3, -3, "Error"))))) -> 3
... A463: Monday, March 9, 2009 | B463: 664 | C463: =(B463-$I$3)/$I$7 -> 5.2329542 | D463: =IF(C463<=1, "<=1", IF(C463<=2, "<=2", IF(C463<=3, "<=3", "<=3"))) -> <=3 | G463: =IF(C463>=3, 3, IF(C463>=2, 2, IF(C463>=1, 1, IF(C463>=-2, -2, IF(C463>=-3, -3, "Error"))))) -> 3

Sheet Demographics
A1: Quality Alloys
A2: Source and Other Data
A3: May 25, 2008 - August 29, 2009
A6: 1) | B6: All Traffic Sources
C7: Visits
B8: Referring Sites | C8: 38754
B9: Search Engines | C9: 20964
B10: Direct Traffic | C10: 9709
B11: Other | C11: 4
A13: 2) | B13: Top Ten Referring Sites
C14: Visits
B15: psicofxp.com | C15: 310
B16: mail.google.com | C16: 337
B17: mu.com | C17: 344
B18: thomasnet.com | C18: 379
B19: freepatentsonline.com | C19: 389
B20: searchportal.information.com | C20: 582
B21: globalspec.com | C21: 693
B22: sedoparking.com | C22: 3138
B23: pagead2.googlesyndication.com | C23: 8044 | D23: =C23+C24 -> 23670 | E23: =D23/SUM(C15:C24) -> 0.7931774
B24: googleads.g.doubleclick.net | C24: 15626
A26: 3) | B26: Top Ten Search Engine Sources of Visits
C27: Visits
B28: google | C28: 17681
B29: yahoo | C29: 1250
B30: search | C30: 592
B31: msn | C31: 424
B32: aol | C32: 309
B33: ask | C33: 268
B34: live | C34: 145
B35: bing | C35: 122 | E35: =C28/SUM(C28:C37) -> 0.84679119
B36: voila | C36: 63
B37: netscape | C37: 26
A39: 4) | B39: Top Ten Geographic Sources by Sub Continent Region
C40: Visits
B41: South America | C41: 22616 | E41: =C41/SUM($C$41:$C$50) -> 0.34482969
B42: Northern America | C42: 17509 | E42: =C42/SUM($C$41:$C$50) -> 0.26696246
B43: Central America | C43: 6776 | E43: =C43/SUM($C$41:$C$50) -> 0.10331473
B44: Western Europe | C44: 5214 | E44: =C44/SUM($C$41:$C$50) -> 0.079498673
B45: Eastern Asia | C45: 3228 | E45: =C45/SUM($C$41:$C$50) -> 0.049217821
B46: Northern Europe | C46: 2721 | E46: =C46/SUM($C$41:$C$50) -> 0.041487513
B47: Southern Asia | C47: 2589 | E47: =C47/SUM($C$41:$C$50) -> 0.039474888
B48: South-Eastern Asia | C48: 1968 | E48: =C48/SUM($C$41:$C$50) -> 0.030006404
B49: Southern Europe | C49: 1538 | E49: =C49/SUM($C$41:$C$50) -> 0.023450127
B50: Eastern Europe | C50: 1427 | E50: =C50/SUM($C$41:$C$50) -> 0.021757692
A53: 5) | B53: Top Ten Browsers Used
C54: Visits
B55: Internet Explorer | C55: 53080 | E55: =C55/SUM(C55:C64) -> 0.7649407
B56: Firefox | C56: 13142
B57: Opera | C57: 938
B58: Safari | C58: 850
B59: Chrome | C59: 792
B60: Mozilla | C60: 478
B61: Netscape | C61: 47
B62: Konqueror | C62: 31
B63: SeaMonkey | C63: 24
B64: Camino | C64: 9
A67: 6) | B67: Top Ten Operating Systems Used
C68: Visits
B69: Windows | C69: 67063 | E69: =C69/SUM(C69:C78) -> 0.96601942
B70: Macintosh | C70: 1184
B71: Linux | C71: 1045
B72: (not set) | C72: 48
B73: iPhone | C73: 29
B74: SymbianOS | C74: 20
B75: FreeBSD | C75: 18
B76: iPod | C76: 8
B77: Playstation 3 | C77: 4
B78: Playstation Portable | C78: 3

Sheet WeekCode
A1: WeekCode | B1: Week (2008-2009) | D1: Phase | E1: PhraseDesc | F1: PhaseCode | G1: WeekCode | H1: MonthYear | I1: Year | J1: YearMonth
A2: 1 | B2: May 25 - May 31 | D2: Shakedown | E2: 1 - Shakedown | F2: 1 | G2: 1 | H2: 05 | I2: 2008 | J2: 2008-05
A3: 2 | B3: Jun 1 - Jun 7 | D3: Shakedown | E3: 1 - Shakedown | F3: 1 | G3: 2 | H3: 06 | I3: 2008 | J3: 2008-06
A4: 3 | B4: Jun 8 - Jun 14 | D4: Shakedown | E4: 1 - Shakedown | F4: 1 | G4: 3 | H4: 06 | I4: 2008 | J4: 2008-06
A5: 4 | B5: Jun 15 - Jun 21 | D5: Shakedown | E5: 1 - Shakedown | F5: 1 | G5: 4 | H5: 06 | I5: 2008 | J5: 2008-06
A6: 5 | B6: Jun 22 - Jun 28 | D6: Shakedown | E6: 1 - Shakedown | F6: 1 | G6: 5 | H6: 06 | I6: 2008 | J6: 2008-06
A7: 6 | B7: Jun 29 - Jul 5 | D7: Shakedown | E7: 1 - Shakedown | F7: 1 | G7: 6 | H7: 06 | I7: 2008 | J7: 2008-06
A8: 7 | B8: Jul 6 - Jul 12 | D8: Shakedown | E8: 1 - Shakedown | F8: 1 | G8: 7 | H8: 07 | I8: 2008 | J8: 2008-07
A9: 8 | B9: Jul 13 - Jul 19 | D9: Shakedown | E9: 1 - Shakedown | F9: 1 | G9: 8 | H9: 07 | I9: 2008 | J9: 2008-07
A10: 9 | B10: Jul 20 - Jul 26 | D10: Shakedown | E10: 1 - Shakedown | F10: 1 | G10: 9 | H10: 07 | I10: 2008 | J10: 2008-07
A11: 10 | B11: Jul 27 - Aug 2 | D11: Shakedown | E11: 1 - Shakedown | F11: 1 | G11: 10 | H11: 07 | I11: 2008 | J11: 2008-07
A12: 11 | B12: Aug 3 - Aug 9 | D12: Shakedown | E12: 1 - Shakedown | F12: 1 | G12: 11 | H12: 08 | I12: 2008 | J12: 2008-08
A13: 12 | B13: Aug 10 - Aug 16 | D13: Shakedown | E13: 1 - Shakedown | F13: 1 | G13: 12 | H13: 08 | I13: 2008 | J13: 2008-08
... A67: 66 | B67: Aug 23 - Aug 29 | D67: Post-Promo | E67: 4 - Post-Promo | F67: 4 | G67: 66 | H67: 08 | I67: 2009 | J67: 2009-08

Sheet Others Charts
A1: Prepared by (learners): | V1: Sum of Inquiries | W1: Column Labels
B2: Gumpal, Peter-Paul | V2: Row Labels | W2: 1 - Initial Period | X2: 2 - Pre-Promo | Y2: 3 - Promo | Z2: 4 - Post-Promo | AA2: Grand Total
B3: Zuñiga, Ma. Angelica Monina | V3: 1 | W3: 13 | AA3: 13
V4: 2 | W4: 7 | AA4: 7
V5: 3 | W5: 5 | AA5: 5
V6: 4 | W6: 3 | AA6: 3
V7: 5 | W7: 3 | AA7: 3
V8: 6 | W8: 5 | AA8: 5
V9: 7 | W9: 16 | AA9: 16
V10: 8 | W10: 7 | AA10: 7
V11: 9 | W11: 6 | AA11: 6
V12: 10 | W12: 6 | AA12: 6
V13: 11 | W13: 4 | AA13: 4
V14: 12 | W14: 9 | AA14: 9
V15: 13 | W15: 10 | AA15: 10
V16: 14 | W16: 8 | AA16: 8
V17: 15 | X17: 8 | AA17: 8
V18: 16 | X18: 11 | AA18: 11
V19: 17 | X19: 9 | AA19: 9
V20: 18 | X20: 6 | AA20: 6
V21: 19 | X21: 8 | AA21: 8
V22: 20 | X22: 10 | AA22: 10
V23: 21 | X23: 1 | AA23: 1
V24: 22 | X24: 5 | AA24: 5
V25: 23 | X25: 9 | AA25: 9
V26: 24 | X26: 8 | AA26: 8
V27: 25 | X27: 6 | AA27: 6
V28: 26 | X28: 6 | AA28: 6
... V37: 35 | X37: 6 | AA37: 6
V38: 36 | Y38: 4 | AA38: 4
V39: 37 | Y39: 5 | AA39: 5
V40: 38 | Y40: 7 | AA40: 7
V41: 39 | Y41: 7 | AA41: 7
V42: 40 | Y42: 11 | AA42: 11
V43: 41 | Y43: 9 | AA43: 9
V44: 42 | Y44: 4 | AA44: 4
V45: 43 | Y45: 8 | AA45: 8
V46: 44 | Y46: 6 | AA46: 6
V47: 45 | Y47: 7 | AA47: 7
V48: 46 | Y48: 5 | AA48: 5
V49: 47 | Y49: 9 | AA49: 9
... V54: 52 | Y54: 6 | AA54: 6
V55: 53 | Z55: 5 | AA55: 5
V56: 54 | Z56: 3 | AA56: 3
V57: 55 | Z57: 3 | AA57: 3
V58: 56 | Z58: 6 | AA58: 6
V59: 57 | Z59: 2 | AA59: 2
V60: 58 | Z60: 6 | AA60: 6
V61: 59 | Z61: 7 | AA61: 7
V62: 60 | Z62: 11 | AA62: 11
V63: 61 | Z63: 4 | AA63: 4
V64: 62 | Z64: 4 | AA64: 4
V65: 63 | Z65: 5 | AA65: 5
V66: 64 | Z66: 5 | AA66: 5
... V68: 66 | Z68: 8 | AA68: 8
V69: Grand Total | W69: 102 | X69: 136 | Y69: 108 | Z69: 76 | AA69: 422

Sheet References
B2: Website Traffic Benchmarks by Industry | Databox
U3: Stickiness, as a Key Performance Indicator (KPI), measures how often users return to your website or app within a specific time frame. It's a valuable metric for understanding user engagement and loyalty.
U5: How to Calculate Stickiness:
U7: The most common way to calculate stickiness is by using the following formula:
U9: Stickiness (%) = (Daily Active Users (DAU) / Monthly Active Users (MAU)) * 100
U10: Interpretation:
U11: A higher stickiness percentage indicates that a larger proportion of your monthly active users are returning on a daily basis, suggesting strong engagement and loyalty. Conversely, a low stickiness percentage might signal that users are not finding enough value to return frequently.
U12: General benchmark: A stickiness rate of 20% is considered a good starting point for many businesses. This means that 20% of your monthly active users are returning daily.
U13: High stickiness: A stickiness rate above 30% is often considered excellent, indicating a highly engaged user base.
U14: Low stickiness: A stickiness rate below 10% might raise concerns about user engagement and retention.
U15: The following are some industry benchmarks for stickiness, but remember that these are just averages, and your specific goals may differ:
U17: Social networking: 40-50%
U18: Gaming: 20-30%
... U47: Service sites: 10-30%

Sheet SRC
A1: Phase | B1: PhraseDesc | C1: PhaseCode | D1: WeekCode | E1: MonthYear | F1: Year | G1: YearMonth | H1: Week (2008-2009) | I1: Visits | J1: Unique Visits | K1: Pageviews | L1: Pages/Visit | M1: Total Time on Site (secs.) | N1: Avg. Time on Site (secs.) | O1: Bounce Rate | P1: Bounce Rating | Q1: % New Visits | R1: Volume | S1: Revenue | T1: Profit | U1: Inquiries | V1: Revenue Per Visit | W1: Stickiness | X1: Stickeness Rating | Y1: Cost Per (Visitor) Acquisition | Z1: Marketing ROI per Visitor
A2: Initial Period | B2: =_xlfn.CONCAT(C2, " - ", A2) -> 1 - Initial Period | C2: 1 | D2: 1 | E2: 05 | F2: 2008 | G2: 2008-05 | H2: May 25 - May 31 | I2: 1632 | J2: 1509 | K2: 3328 | L2: 2.04 | M2: =I2*N2 -> 115872 | N2: 71 | O2: 0.7267 | P2: =IF(O2<41%, "Excellent", IF(O2<=55%, "Average", "Poor")) -> Poor | Q2: 0.8854 | R2: 16585 | S2: 480728.01 | T2: 118683.8 | U2: 13 | V2: =S2/I2 -> 294.56373 | W2: =(J2/SUM($J$2:$J$15)) -> 0.11044427 | X2: =IF(W2<5%, "Poor", IF(W2<10%, "Average", "Good")) -> Good
A3: Initial Period | B3: =_xlfn.CONCAT(C3, " - ", A3) -> 1 - Initial Period | C3: 1 | D3: 2 | E3: 06 | F3: 2008 | G3: 2008-06 | H3: Jun 1 - Jun 7 | I3: 1580 | J3: 1450 | K3: 3097 | L3: 1.96 | M3: =I3*N3 -> 88480 | N3: 56 | O3: 0.7551 | P3: =IF(O3<41%, "Excellent", IF(O3<=55%, "Average", "Poor")) -> Poor | Q3: 0.8734 | R3: 18906 | S3: 641155.48 | T3: 269604.7 | U3: 7 | V3: =S3/I3 -> 405.79461 | W3: =(J3/SUM($J$2:$J$15)) -> 0.10612603 | X3: =IF(W3<5%, "Poor", IF(W3<10%, "Average", "Good")) -> Good
A4: Initial Period | B4: =_xlfn.CONCAT(C4, " - ", A4) -> 1 - Initial Period | C4: 1 | D4: 3 | E4: 06 | F4: 2008 | G4: 2008-06 | H4: Jun 8 - Jun 14 | I4: 1441 | J4: 1306 | K4: 3202 | L4: 2.22 | M4: =I4*N4 -> 113839 | N4: 79 | O4: 0.7398 | P4: =IF(O4<41%, "Excellent", IF(O4<=55%, "Average", "Poor")) -> Poor | Q4: 0.8432 | R4: 28053 | S4: 890076.65 | T4: 275218.1 | U4: 5 | V4: =S4/I4 -> 617.67984 | W4: =(J4/SUM($J$2:$J$15)) -> 0.095586621 | X4: =IF(W4<5%, "Poor", IF(W4<10%, "Average", "Good")) -> Average
A5: Initial Period | B5: =_xlfn.CONCAT(C5, " - ", A5) -> 1 - Initial Period | C5: 1 | D5: 4 | E5: 06 | F5: 2008 | G5: 2008-06 | H5: Jun 15 - Jun 21 | I5: 1452 | J5: 1301 | K5: 3170 | L5: 2.18 | M5: =I5*N5 -> 117612 | N5: 81 | O5: 0.7362 | P5: =IF(O5<41%, "Excellent", IF(O5<=55%, "Average", "Poor")) -> Poor | Q5: 0.8437 | R5: 19382 | S5: 552673.98 | T5: 204153 | U5: 3 | V5: =S5/I5 -> 380.62946 | W5: =(J5/SUM($J$2:$J$15)) -> 0.095220669 | X5: =IF(W5<5%, "Poor", IF(W5<10%, "Average", "Good")) -> Average
A6: Initial Period | B6: =_xlfn.CONCAT(C6, " - ", A6) -> 1 - Initial Period | C6: 1 | D6: 5 | E6: 06 | F6: 2008 | G6: 2008-06 | H6: Jun 22 - Jun 28 | I6: 1339 | J6: 1255 | K6: 2366 | L6: 1.77 | M6: =I6*N6 -> 66950 | N6: 50 | O6: 0.764 | P6: =IF(O6<41%, "Excellent", IF(O6<=55%, "Average", "Poor")) -> Poor | Q6: 0.8925 | R6: 24274 | S6: 750776.98 | T6: 256091.4 | U6: 3 | V6: =S6/I6 -> 560.69976 | W6: =(J6/SUM($J$2:$J$15)) -> 0.091853912 | X6: =IF(W6<5%, "Poor", IF(W6<10%, "Average", "Good")) -> Average
A7: Initial Period | B7: =_xlfn.CONCAT(C7, " - ", A7) -> 1 - Initial Period | C7: 1 | D7: 6 | E7: 06 | F7: 2008 | G7: 2008-06 | H7: Jun 29 - Jul 5 | I7: 892 | J7: 841 | K7: 1865 | L7: 2.09 | M7: =I7*N7 -> 63332 | N7: 71 | O7: 0.7365 | P7: =IF(O7<41%, "Excellent", IF(O7<=55%, "Average", "Poor")) -> Poor | Q7: 0.8756 | R7: 15309 | S7: 553054.69 | T7: 178134.5 | U7: 5 | V7: =S7/I7 -> 620.01647 | W7: =(J7/SUM($J$2:$J$15)) -> 0.0615531 | X7: =IF(W7<5%, "Poor", IF(W7<10%, "Average", "Good")) -> Average
A8: Initial Period | B8: =_xlfn.CONCAT(C8, " - ", A8) -> 1 - Initial Period | C8: 1 | D8: 7 | E8: 07 | F8: 2008 | G8: 2008-07 | H8: Jul 6 - Jul 12 | I8: 797 | J8: 731 | K8: 1885 | L8: 2.37 | M8: =I8*N8 -> 63760 | N8: 80 | O8: 0.6148 | P8: =IF(O8<41%, "Excellent", IF(O8<=55%, "Average", "Poor")) -> Poor | Q8: 0.857 | R8: 8633 | S8: 274567.61 | T8: 62580.4 | U8: 16 | V8: =S8/I8 -> 344.5014 | W8: =(J8/SUM($J$2:$J$15)) -> 0.053502159 | X8: =IF(W8<5%, "Poor", IF(W8<10%, "Average", "Good")) -> Average
A9: Initial Period | B9: =_xlfn.CONCAT(C9, " - ", A9) -> 1 - Initial Period | C9: 1 | D9: 8 | E9: 07 | F9: 2008 | G9: 2008-07 | H9: Jul 13 - Jul 19 | I9: 744 | J9: 706 | K9: 1916 | L9: 2.58 | M9: =I9*N9 -> 71424 | N9: 96 | O9: 0.5927 | P9: =IF(O9<41%, "Excellent", IF(O9<=55%, "Average", "Poor")) -> Poor | Q9: 0.8884 | R9: 17216 | S9: 619284.64 | T9: 248458.4 | U9: 7 | V9: =S9/I9 -> 832.37182 | W9: =(J9/SUM($J$2:$J$15)) -> 0.0516724 | X9: =IF(W9<5%, "Poor", IF(W9<10%, "Average", "Good")) -> Average
A10: Initial Period | B10: =_xlfn.CONCAT(C10, " - ", A10) -> 1 - Initial Period | C10: 1 | D10: 9 | E10: 07 | F10: 2008 | G10: 2008-07 | H10: Jul 20 - Jul 26 | I10: 1044 | J10: 976 | K10: 2670 | L10: 2.56 | M10: =I10*N10 -> 85608 | N10: 82 | O10: 0.6034 | P10: =IF(O10<41%, "Excellent", IF(O10<=55%, "Average", "Poor")) -> Poor | Q10: 0.8669 | R10: 17309 | S10: 674484.59 | T10: 238498.1 | U10: 6 | V10: =S10/I10 -> 646.05803 | W10: =(J10/SUM($J$2:$J$15)) -> 0.071433799 | X10: =IF(W10<5%, "Poor", IF(W10<10%, "Average", "Good")) -> Average
A11: Initial Period | B11: =_xlfn.CONCAT(C11, " - ", A11) -> 1 - Initial Period | C11: 1 | D11: 10 | E11: 07 | F11: 2008 | G11: 2008-07 | H11: Jul 27 - Aug 2 | I11: 906 | J11: 850 | K11: 2189 | L11: 2.42 | M11: =I11*N11 -> 70668 | N11: 78 | O11: 0.6336 | P11: =IF(O11<41%, "Excellent", IF(O11<=55%, "Average", "Poor")) -> Poor | Q11: 0.8742 | R11: 24571 | S11: 762559.12 | T11: 230237.8 | U11: 6 | V11: =S11/I11 -> 841.67674 | W11: =(J11/SUM($J$2:$J$15)) -> 0.062211813 | X11: =IF(W11<5%, "Poor", IF(W11<10%, "Average", "Good")) -> Average
A12: Initial Period | B12: =_xlfn.CONCAT(C12, " - ", A12) -> 1 - Initial Period | C12: 1 | D12: 11 | E12: 08 | F12: 2008 | G12: 2008-08 | H12: Aug 3 - Aug 9 | I12: 849 | J12: 791 | K12: 1947 | L12: 2.29 | M12: =I12*N12 -> 77259 | N12: 91 | O12: 0.6443 | P12: =IF(O12<41%, "Excellent", IF(O12<=55%, "Average", "Poor")) -> Poor | Q12: 0.8704 | R12: 14390 | S12: 479084.17 | T12: 156660.1 | U12: 4 | V12: =S12/I12 -> 564.29231 | W12: =(J12/SUM($J$2:$J$15)) -> 0.057893581 | X12: =IF(W12<5%, "Poor", IF(W12<10%, "Average", "Good")) -> Average
A13: Initial Period | B13: =_xlfn.CONCAT(C13, " - ", A13) -> 1 - Initial Period | C13: 1 | D13: 12 | E13: 08 | F13: 2008 | G13: 2008-08 | H13: Aug 10 - Aug 16 | I13: 737 | J13: 685 | K13: 1746 | L13: 2.37 | M13: =I13*N13 -> 72226 | N13: 98 | O13: 0.6282 | P13: =IF(O13<41%, "Excellent", IF(O13<=55%, "Average", "Poor")) -> Poor | Q13: 0.8725 | R13: 17231 | S13: 528270.72 | T13: 186775.6 | U13: 9 | V13: =S13/I13 -> 716.78523 | W13: =(J13/SUM($J$2:$J$15)) -> 0.050135402 | X13: =IF(W13<5%, "Poor", IF(W13<10%, "Average", "Good")) -> Average
... A36: Pre-Promo | B36: =_xlfn.CONCAT(C36, " - ", A36) -> 2 - Pre-Promo | C36: 2 | D36: 35 | E36: 01 | F36: 2009 | G36: 2009-01 | H36: Jan 18 - Jan 24 | I36: 795 | J36: 734 | K36: 1824 | L36: 2.29 | M36: =I36*N36 -> 53265 | N36: 67 | O36: 0.6579 | P36: =IF(O36<41%, "Excellent", IF(O36<=55%, "Average", "Poor")) -> Poor | Q36: 0.8528 | R36: 26303 | S36: 519934.14 | T36: 179883.8 | U36: 6 | V36: =S36/I36 -> 654.0052 | W36: =(J36/SUM($J$2:$J$15)) -> 0.05372173 | X36: =IF(W36<5%, "Poor", IF(W36<10%, "Average", "Good")) -> Average
A37: Promo | B37: =_xlfn.CONCAT(C37, " - ", A37) -> 3 - Promo | C37: 3 | D37: 36 | E37: 01 | F37: 2009 | G37: 2009-01 | H37: Jan 25 - Jan 31 | I37: 1000 | J37: 930 | K37: 2259 | L37: 2.26 | M37: =I37*N37 -> 66000 | N37: 66 | O37: 0.658 | P37: =IF(O37<41%, "Excellent", IF(O37<=55%, "Average", "Poor")) -> Poor | Q37: 0.865 | R37: 22199 | S37: 614454.7 | T37: 113248.9 | U37: 4 | V37: =S37/I37 -> 614.4547 | W37: =(J37/SUM($J$2:$J$15)) -> 0.068067042 | X37: =IF(W37<5%, "Poor", IF(W37<10%, "Average", "Good")) -> Average | Y37: =(25000/COUNT(D37:D53)) /SRC!J37 -> 1.5812777 | Z37: =((S37-(25000/17)) / (25000/17)) / I37 -> 0.41682919 | AA37: =S37*Z37 -> 256122.66
A38: Promo | B38: =_xlfn.CONCAT(C38, " - ", A38) -> 3 - Promo | C38: 3 | D38: 37 | E38: 02 | F38: 2009 | G38: 2009-02 | H38: Feb 1 - Feb 7 | I38: 1207 | J38: 1136 | K38: 2376 | L38: 1.97 | M38: =I38*N38 -> 82076 | N38: 68 | O38: 0.7307 | P38: =IF(O38<41%, "Excellent", IF(O38<=55%, "Average", "Poor")) -> Poor | Q38: 0.8815 | R38: 16535 | S38: 516269.92 | T38: 193465.1 | U38: 5 | V38: =S38/I38 -> 427.72985 | W38: =(J38/SUM($J$2:$J$15)) -> 0.083144258 | X38: =IF(W38<5%, "Poor", IF(W38<10%, "Average", "Good")) -> Average | Y38: =(25000/COUNT(D38:D54)) /SRC!J38 -> 1.2945319 | Z38: =((S38-(25000/17)) / (25000/17)) / I38 -> 0.29002779 | AA38: =S38*Z38 -> 149732.63
A39: Promo | B39: =_xlfn.CONCAT(C39, " - ", A39) -> 3 - Promo | C39: 3 | D39: 38 | E39: 02 | F39: 2009 | G39: 2009-02 | H39: Feb 8 - Feb 14 | I39: 2317 | J39: 2229 | K39: 3814 | L39: 1.65 | M39: =I39*N39 -> 88046 | N39: 38 | O39: 0.8226 | P39: =IF(O39<41%, "Excellent", IF(O39<=55%, "Average", "Poor")) -> Poor | Q39: 0.9309 | R39: 7814 | S39: 297812.75 | T39: 89802.5 | U39: 7 | V39: =S39/I39 -> 128.53377 | W39: =(J39/SUM($J$2:$J$15)) -> 0.16314133 | X39: =IF(W39<5%, "Poor", IF(W39<10%, "Average", "Good")) -> Good | Y39: =(25000/COUNT(D39:D55)) /SRC!J39 -> 0.65975246 | Z39: =((S39-(25000/17)) / (25000/17)) / I39 -> 0.086971372 | AA39: =S39*Z39 -> 25901.183
A40: Promo | B40: =_xlfn.CONCAT(C40, " - ", A40) -> 3 - Promo | C40: 3 | D40: 39 | E40: 02 | F40: 2009 | G40: 2009-02 | H40: Feb 15 - Feb 21 | I40: 2013 | J40: 1946 | K40: 3303 | L40: 1.64 | M40: =I40*N40 -> 84546 | N40: 42 | O40: 0.8127 | P40: =IF(O40<41%, "Excellent", IF(O40<=55%, "Average", "Poor")) -> Poor | Q40: 0.9314 | R40: 28041 | S40: 692677.09 | T40: 184368.4 | U40: 7 | V40: =S40/I40 -> 344.10188 | W40: =(J40/SUM($J$2:$J$15)) -> 0.14242846 | X40: =IF(W40<5%, "Poor", IF(W40<10%, "Average", "Good")) -> Good | Y40: =(25000/COUNT(D40:D56)) /SRC!J40 -> 0.75569796 | Z40: =((S40-(25000/17)) / (25000/17)) / I40 -> 0.23349251 | AA40: =S40*Z40 -> 161734.91
A41: Promo | B41: =_xlfn.CONCAT(C41, " - ", A41) -> 3 - Promo | C41: 3 | D41: 40 | E41: 02 | F41: 2009 | G41: 2009-02 | H41: Feb 22 - Feb 28 | I41: 2324 | J41: 2228 | K41: 3836 | L41: 1.65 | M41: =I41*N41 -> 92960 | N41: 40 | O41: 0.8072 | P41: =IF(O41<41%, "Excellent", IF(O41<=55%, "Average", "Poor")) -> Poor | Q41: 0.9213 | R41: 31496 | S41: 897163.71 | T41: 266476.7 | U41: 11 | V41: =S41/I41 -> 386.04291 | W41: =(J41/SUM($J$2:$J$15)) -> 0.16306814 | X41: =IF(W41<5%, "Poor", IF(W41<10%, "Average", "Good")) -> Good | Y41: =(25000/COUNT(D41:D57)) /SRC!J41 -> 0.66004858 | Z41: =((S41-(25000/17)) / (25000/17)) / I41 -> 0.26207888 | AA41: =S41*Z41 -> 235127.66
A42: Promo | B42: =_xlfn.CONCAT(C42, " - ", A42) -> 3 - Promo | C42: 3 | D42: 41 | E42: 03 | F42: 2009 | G42: 2009-03 | H42: Mar 1 - Mar 7 | I42: 3726 | J42: 3617 | K42: 5291 | L42: 1.42 | M42: =I42*N42 -> 104328 | N42: 28 | O42: 0.8578 | P42: =IF(O42<41%, "Excellent", IF(O42<=55%, "Average", "Poor")) -> Poor | Q42: 0.9479 | R42: 10181 | S42: 417727.33 | T42: 111834.5 | U42: 9 | V42: =S42/I42 -> 112.11147 | W42: =(J42/SUM($J$2:$J$15)) -> 0.26472956 | X42: =IF(W42<5%, "Poor", IF(W42<10%, "Average", "Good")) -> Good | Y42: =(25000/COUNT(D42:D58)) /SRC!J42 -> 0.40657679 | Z42: =((S42-(25000/17)) / (25000/17)) / I42 -> 0.075967414 | AA42: =S42*Z42 -> 31733.665
A43: Promo | B43: =_xlfn.CONCAT(C43, " - ", A43) -> 3 - Promo | C43: 3 | D43: 42 | E43: 03 | F43: 2009 | G43: 2009-03 | H43: Mar 8 - Mar 14 | I43: 2563 | J43: 2482 | K43: 3729 | L43: 1.45 | M43: =I43*N43 -> 79453 | N43: 31 | O43: 0.8478 | P43: =IF(O43<41%, "Excellent", IF(O43<=55%, "Average", "Poor")) -> Poor | Q43: 0.9376 | R43: 9727 | S43: 326968.75 | T43: 122687.3 | U43: 4 | V43: =S43/I43 -> 127.57267 | W43: =(J43/SUM($J$2:$J$15)) -> 0.18165849 | X43: =IF(W43<5%, "Poor", IF(W43<10%, "Average", "Good")) -> Good | Y43: =(25000/COUNT(D43:D59)) /SRC!J43 -> 0.5925013 | Z43: =((S43-(25000/17)) / (25000/17)) / I43 -> 0.086359248 | AA43: =S43*Z43 -> 28236.775
A44: Promo | B44: =_xlfn.CONCAT(C44, " - ", A44) -> 3 - Promo | C44: 3 | D44: 43 | E44: 03 | F44: 2009 | G44: 2009-03 | H44: Mar 15 - Mar 21 | I44: 3006 | J44: 2896 | K44: 4510 | L44: 1.5 | M44: =I44*N44 -> 105210 | N44: 35 | O44: 0.843 | P44: =IF(O44<41%, "Excellent", IF(O44<=55%, "Average", "Poor")) -> Poor | Q44: 0.9311 | R44: 18323 | S44: 326482.16 | T44: 114328.4 | U44: 8 | V44: =S44/I44 -> 108.61017 | W44: =(J44/SUM($J$2:$J$15)) -> 0.21195931 | X44: =IF(W44<5%, "Poor", IF(W44<10%, "Average", "Good")) -> Good | Y44: =(25000/COUNT(D44:D60)) /SRC!J44 -> 0.50779981 | Z44: =((S44-(25000/17)) / (25000/17)) / I44 -> 0.073522245 | AA44: =S44*Z44 -> 24003.702
A45: Promo | B45: =_xlfn.CONCAT(C45, " - ", A45) -> 3 - Promo | C45: 3 | D45: 44 | E45: 03 | F45: 2009 | G45: 2009-03 | H45: Mar 22 - Mar 28 | I45: 1663 | J45: 1585 | K45: 3037 | L45: 1.83 | M45: =I45*N45 -> 86476 | N45: 52 | O45: 0.7655 | P45: =IF(O45<41%, "Excellent", IF(O45<=55%, "Average", "Poor")) -> Poor | Q45: 0.9092 | R45: 17299 | S45: 508026.89 | T45: 159944.5 | U45: 6 | V45: =S45/I45 -> 305.48821 | W45: =(J45/SUM($J$2:$J$15)) -> 0.11600673 | X45: =IF(W45<5%, "Poor", IF(W45<10%, "Average", "Good")) -> Good | Y45: =(25000/COUNT(D45:D61)) /SRC!J45 -> 0.92781592 | Z45: =((S45-(25000/17)) / (25000/17)) / I45 -> 0.20713066 | AA45: =S45*Z45 -> 105227.95
A46: Promo | B46: =_xlfn.CONCAT(C46, " - ", A46) -> 3 - Promo | C46: 3 | D46: 45 | E46: 03 | F46: 2009 | G46: 2009-03 | H46: Mar 29 - Apr 4 | I46: 1779 | J46: 1689 | K46: 2881 | L46: 1.62 | M46: =I46*N46 -> 65823 | N46: 37 | O46: 0.7886 | P46: =IF(O46<41%, "Excellent", IF(O46<=55%, "Average", "Poor")) -> Poor | Q46: 0.9129 | R46: 13862 | S46: 413937.08 | T46: 143253.9 | U46: 7 | V46: =S46/I46 -> 232.67964 | W46: =(J46/SUM($J$2:$J$15)) -> 0.12361853 | X46: =IF(W46<5%, "Poor", IF(W46<10%, "Average", "Good")) -> Good | Y46: =(25000/COUNT(D46:D62)) /SRC!J46 -> 0.87068575 | Z46: =((S46-(25000/17)) / (25000/17)) / I46 -> 0.15766004 | AA46: =S46*Z46 -> 65261.337
A47: Promo | B47: =_xlfn.CONCAT(C47, " - ", A47) -> 3 - Promo | C47: 3 | D47: 46 | E47: 04 | F47: 2009 | G47: 2009-04 | H47: Apr 5 - Apr 11 | I47: 1086 | J47: 1030 | K47: 2313 | L47: 2.13 | M47: =I47*N47 -> 68418 | N47: 63 | O47: 0.6934 | P47: =IF(O47<41%, "Excellent", IF(O47<=55%, "Average", "Poor")) -> Poor | Q47: 0.8849 | R47: 19007 | S47: 422487.91 | T47: 81841.4 | U47: 5 | V47: =S47/I47 -> 389.03122 | W47: =(J47/SUM($J$2:$J$15)) -> 0.075386079 | X47: =IF(W47<5%, "Poor", IF(W47<10%, "Average", "Good")) -> Average | Y47: =(25000/COUNT(D47:D63)) /SRC!J47 -> 1.4277556 | Z47: =((S47-(25000/17)) / (25000/17)) / I47 -> 0.26362042 | AA47: =S47*Z47 -> 111376.44
A48: Promo | B48: =_xlfn.CONCAT(C48, " - ", A48) -> 3 - Promo | C48: 3 | D48: 47 | E48: 04 | F48: 2009 | G48: 2009-04 | H48: Apr 12 - Apr 18 | I48: 1231 | J48: 1166 | K48: 2714 | L48: 2.2 | M48: =I48*N48 -> 84939 | N48: 69 | O48: 0.7059 | P48: =IF(O48<41%, "Excellent", IF(O48<=55%, "Average", "Poor")) -> Poor | Q48: 0.892 | R48: 23284 | S48: 376751.08 | T48: 137256.3 | U48: 9 | V48: =S48/I48 -> 306.05286 | W48: =(J48/SUM($J$2:$J$15)) -> 0.085339969 | X48: =IF(W48<5%, "Poor", IF(W48<10%, "Average", "Good")) -> Average | Y48: =(25000/COUNT(D48:D64)) /SRC!J48 -> 1.2612249 | Z48: =((S48-(25000/17)) / (25000/17)) / I48 -> 0.2073036 | AA48: =S48*Z48 -> 78101.854
... A53: Promo | B53: =_xlfn.CONCAT(C53, " - ", A53) -> 3 - Promo | C53: 3 | D53: 52 | E53: 05 | F53: 2009 | G53: 2009-05 | H53: May 17 - May 23 | I53: 1191 | J53: 1137 | K53: 2400 | L53: 2.02 | M53: =I53*N53 -> 70269 | N53: 59 | O53: 0.7347 | P53: =IF(O53<41%, "Excellent", IF(O53<=55%, "Average", "Poor")) -> Poor | Q53: 0.8976 | R53: 15524 | S53: 397140.04 | T53: 112040.2 | U53: 6 | V53: =S53/I53 -> 333.45092 | W53: =(J53/SUM($J$2:$J$15)) -> 0.083217449 | X53: =IF(W53<5%, "Poor", IF(W53<10%, "Average", "Good")) -> Average | Y53: =(25000/COUNT(D53:D69)) /SRC!J53 -> 1.4658458 | Z53: =((S53-(25000/17)) / (25000/17)) / I53 -> 0.22590699 | AA53: =S53*Z53 -> 89716.713
A54: Post-Promo | B54: =_xlfn.CONCAT(C54, " - ", A54) -> 4 - Post-Promo | C54: 4 | D54: 53 | E54: 05 | F54: 2009 | G54: 2009-05 | H54: May 24 - May 30 | I54: 957 | J54: 912 | K54: 1904 | L54: 1.99 | M54: =I54*N54 -> 51678 | N54: 54 | O54: 0.7085 | P54: =IF(O54<41%, "Excellent", IF(O54<=55%, "Average", "Poor")) -> Poor | Q54: 0.8945 | R54: 15406 | S54: 370914.26 | T54: 102975.8 | U54: 5 | V54: =S54/I54 -> 387.58021 | W54: =(J54/SUM($J$2:$J$15)) -> 0.066749616 | X54: =IF(W54<5%, "Poor", IF(W54<10%, "Average", "Good")) -> Average | AA54: =S54*Z54 -> 0
A55: Post-Promo | B55: =_xlfn.CONCAT(C55, " - ", A55) -> 4 - Post-Promo | C55: 4 | D55: 54 | E55: 05 | F55: 2009 | G55: 2009-05 | H55: May 31 - Jun 6 | I55: 963 | J55: 909 | K55: 2156 | L55: 2.24 | M55: =I55*N55 -> 73188 | N55: 76 | O55: 0.6833 | P55: =IF(O55<41%, "Excellent", IF(O55<=55%, "Average", "Poor")) -> Poor | Q55: 0.8692 | R55: 14536 | S55: 299424.67 | T55: 89826.3 | U55: 3 | V55: =S55/I55 -> 310.92905 | W55: =(J55/SUM($J$2:$J$15)) -> 0.066530045 | X55: =IF(W55<5%, "Poor", IF(W55<10%, "Average", "Good")) -> Average | AA55: =S55*Z55 -> 0
A56: Post-Promo | B56: =_xlfn.CONCAT(C56, " - ", A56) -> 4 - Post-Promo | C56: 4 | D56: 55 | E56: 06 | F56: 2009 | G56: 2009-06 | H56: Jun 7 - Jun 13 | I56: 882 | J56: 848 | K56: 1827 | L56: 2.07 | M56: =I56*N56 -> 44100 | N56: 50 | O56: 0.6995 | P56: =IF(O56<41%, "Excellent", IF(O56<=55%, "Average", "Poor")) -> Poor | Q56: 0.8889 | R56: 10397 | S56: 297325.95 | T56: 106085.1 | U56: 3 | V56: =S56/I56 -> 337.10426 | W56: =(J56/SUM($J$2:$J$15)) -> 0.062065432 | X56: =IF(W56<5%, "Poor", IF(W56<10%, "Average", "Good")) -> Average | AA56: =S56*Z56 -> 0
A57: Post-Promo | B57: =_xlfn.CONCAT(C57, " - ", A57) -> 4 - Post-Promo | C57: 4 | D57: 56 | E57: 06 | F57: 2009 | G57: 2009-06 | H57: Jun 14 - Jun 20 | I57: 942 | J57: 896 | K57: 2068 | L57: 2.2 | M57: =I57*N57 -> 68766 | N57: 73 | O57: 0.6858 | P57: =IF(O57<41%, "Excellent", IF(O57<=55%, "Average", "Poor")) -> Poor | Q57: 0.8843 | R57: 11054 | S57: 336761.58 | T57: 110671.7 | U57: 6 | V57: =S57/I57 -> 357.49637 | W57: =(J57/SUM($J$2:$J$15)) -> 0.06557857 | X57: =IF(W57<5%, "Poor", IF(W57<10%, "Average", "Good")) -> Average | AA57: =S57*Z57 -> 0
A58: Post-Promo | B58: =_xlfn.CONCAT(C58, " - ", A58) -> 4 - Post-Promo | C58: 4 | D58: 57 | E58: 06 | F58: 2009 | G58: 2009-06 | H58: Jun 21 - Jun 27 | I58: 835 | J58: 789 | K58: 1739 | L58: 2.08 | M58: =I58*N58 -> 64295 | N58: 77 | O58: 0.6635 | P58: =IF(O58<41%, "Excellent", IF(O58<=55%, "Average", "Poor")) -> Poor | Q58: 0.8766 | R58: 17855 | S58: 419302.31 | T58: 100318.7 | U58: 2 | V58: =S58/I58 -> 502.15846 | W58: =(J58/SUM($J$2:$J$15)) -> 0.0577472 | X58: =IF(W58<5%, "Poor", IF(W58<10%, "Average", "Good")) -> Average | AA58: =S58*Z58 -> 0
A59: Post-Promo | B59: =_xlfn.CONCAT(C59, " - ", A59) -> 4 - Post-Promo | C59: 4 | D59: 58 | E59: 06 | F59: 2009 | G59: 2009-06 | H59: Jun 28 - Jul 4 | I59: 802 | J59: 762 | K59: 1764 | L59: 2.2 | M59: =I59*N59 -> 58546 | N59: 73 | O59: 0.6571 | P59: =IF(O59<41%, "Excellent", IF(O59<=55%, "Average", "Poor")) -> Poor | Q59: 0.8965 | R59: 7197 | S59: 191171.58 | T59: 46906.4 | U59: 6 | V59: =S59/I59 -> 238.36855 | W59: =(J59/SUM($J$2:$J$15)) -> 0.055771061 | X59: =IF(W59<5%, "Poor", IF(W59<10%, "Average", "Good")) -> Average | AA59: =S59*Z59 -> 0
A60: Post-Promo | B60: =_xlfn.CONCAT(C60, " - ", A60) -> 4 - Post-Promo | C60: 4 | D60: 59 | E60: 07 | F60: 2009 | G60: 2009-07 | H60: Jul 5 - Jul 11 | I60: 806 | J60: 750 | K60: 1741 | L60: 2.16 | M60: =I60*N60 -> 65286 | N60: 81 | O60: 0.6526 | P60: =IF(O60<41%, "Excellent", IF(O60<=55%, "Average", "Poor")) -> Poor | Q60: 0.8462 | R60: 3826 | S60: 133966.9 | T60: 32825.3 | U60: 7 | V60: =S60/I60 -> 166.21204 | W60: =(J60/SUM($J$2:$J$15)) -> 0.054892776 | X60: =IF(W60<5%, "Poor", IF(W60<10%, "Average", "Good")) -> Average | AA60: =S60*Z60 -> 0
A61: Post-Promo | B61: =_xlfn.CONCAT(C61, " - ", A61) -> 4 - Post-Promo | C61: 4 | D61: 60 | E61: 07 | F61: 2009 | G61: 2009-07 | H61: Jul 12 - Jul 18 | I61: 900 | J61: 828 | K61: 2074 | L61: 2.3 | M61: =I61*N61 -> 58500 | N61: 65 | O61: 0.6456 | P61: =IF(O61<41%, "Excellent", IF(O61<=55%, "Average", "Poor")) -> Poor | Q61: 0.8556 | R61: 22821 | S61: 615712.78 | T61: 166567.7 | U61: 11 | V61: =S61/I61 -> 684.12531 | W61: =(J61/SUM($J$2:$J$15)) -> 0.060601625 | X61: =IF(W61<5%, "Poor", IF(W61<10%, "Average", "Good")) -> Average | AA61: =S61*Z61 -> 0
A62: Post-Promo | B62: =_xlfn.CONCAT(C62, " - ", A62) -> 4 - Post-Promo | C62: 4 | D62: 61 | E62: 07 | F62: 2009 | G62: 2009-07 | H62: Jul 19 - Jul 25 | I62: 860 | J62: 811 | K62: 1922 | L62: 2.23 | M62: =I62*N62 -> 64500 | N62: 75 | O62: 0.6465 | P62: =IF(O62<41%, "Excellent", IF(O62<=55%, "Average", "Poor")) -> Poor | Q62: 0.8686 | R62: 12758 | S62: 360032.6 | T62: 121356.2 | U62: 4 | V62: =S62/I62 -> 418.64255 | W62: =(J62/SUM($J$2:$J$15)) -> 0.059357389 | X62: =IF(W62<5%, "Poor", IF(W62<10%, "Average", "Good")) -> Average | AA62: =S62*Z62 -> 0
A63: Post-Promo | B63: =_xlfn.CONCAT(C63, " - ", A63) -> 4 - Post-Promo | C63: 4 | D63: 62 | E63: 07 | F63: 2009 | G63: 2009-07 | H63: Jul 26 - Aug 1 | I63: 924 | J63: 828 | K63: 2131 | L63: 2.31 | M63: =I63*N63 -> 72072 | N63: 78 | O63: 0.6418 | P63: =IF(O63<41%, "Excellent", IF(O63<=55%, "Average", "Poor")) -> Poor | Q63: 0.8193 | R63: 22325 | S63: 573918.45 | T63: 187698.7 | U63: 4 | V63: =S63/I63 -> 621.12387 | W63: =(J63/SUM($J$2:$J$15)) -> 0.060601625 | X63: =IF(W63<5%, "Poor", IF(W63<10%, "Average", "Good")) -> Average | AA63: =S63*Z63 -> 0
A64: Post-Promo | B64: =_xlfn.CONCAT(C64, " - ", A64) -> 4 - Post-Promo | C64: 4 | D64: 63 | E64: 08 | F64: 2009 | G64: 2009-08 | H64: Aug 2 - Aug 8 | I64: 792 | J64: 737 | K64: 1615 | L64: 2.04 | M64: =I64*N64 -> 53064 | N64: 67 | O64: 0.6818 | P64: =IF(O64<41%, "Excellent", IF(O64<=55%, "Average", "Poor")) -> Poor | Q64: 0.8548 | R64: 18566 | S64: 397550.1 | T64: 124640.6 | U64: 5 | V64: =S64/I64 -> 501.9572 | W64: =(J64/SUM($J$2:$J$15)) -> 0.053941301 | X64: =IF(W64<5%, "Poor", IF(W64<10%, "Average", "Good")) -> Average | AA64: =S64*Z64 -> 0
A65: Post-Promo | B65: =_xlfn.CONCAT(C65, " - ", A65) -> 4 - Post-Promo | C65: 4 | D65: 64 | E65: 08 | F65: 2009 | G65: 2009-08 | H65: Aug 9 - Aug 15 | I65: 781 | J65: 718 | K65: 1598 | L65: 2.05 | M65: =I65*N65 -> 53889 | N65: 69 | O65: 0.6633 | P65: =IF(O65<41%, "Excellent", IF(O65<=55%, "Average", "Poor")) -> Poor | Q65: 0.8399 | R65: 12294 | S65: 282044.86 | T65: 75556.5 | U65: 5 | V65: =S65/I65 -> 361.13298 | W65: =(J65/SUM($J$2:$J$15)) -> 0.052550684 | X65: =IF(W65<5%, "Poor", IF(W65<10%, "Average", "Good")) -> Average | AA65: =S65*Z65 -> 0
... A67: Post-Promo | B67: =_xlfn.CONCAT(C67, " - ", A67) -> 4 - Post-Promo | C67: 4 | D67: 66 | E67: 08 | F67: 2009 | G67: 2009-08 | H67: Aug 23 - Aug 29 | I67: 772 | J67: 709 | K67: 1767 | L67: 2.29 | M67: =I67*N67 -> 55584 | N67: 72 | O67: 0.6192 | P67: =IF(O67<41%, "Excellent", IF(O67<=55%, "Average", "Poor")) -> Poor | Q67: 0.8523 | R67: 23762 | S67: 615950.17 | T67: 206441.2 | U67: 8 | V67: =S67/I67 -> 797.86292 | W67: =(J67/SUM($J$2:$J$15)) -> 0.051891971 | X67: =IF(W67<5%, "Poor", IF(W67<10%, "Average", "Good")) -> Average | AA67: =S67*Z67 -> 0

Sheet Sheet1

Sheet Sheet2
D4: {=_xlfn._xlws.PY(0,0)} -> #VALUE!
